Workbook

Sheet SUMMARY
A1: SN | B1: ITEM DESCRIPTION | C1: UoM | D1: QTY
A2: 1 | B2: CABLE INFRASTRUCTURE | C2: m | D2: =SUM('TOTALS(PASSIVE)'!C20,'TOTALS(PASSIVE)'!J20) -> 7268857.6
A3: 2 | B3: POPs | C3: unit | D3: ='TOTALS(ACTIVE)'!C20 -> 54
A4: 3 | B4: CORE DEVICES | C4: unit | D4: =SUM('TOTALS(ACTIVE)'!G20:AC20) -> 102
A5: 4 | B5: CUSTOMER SITES | C5: unit | D5: =SUM('TOTALS(ACTIVE)'!D20:F20) -> 1446
B7: ECG
A8: SN | B8: ITEM DESCRIPTION | C8: UoM | D8: QTY
A9: 1 | B9: CABLE INFRASTRUCTURE | C9: m | D9: =SUM('TOTALS(PASSIVE)'!C3:C10,'TOTALS(PASSIVE)'!J3:J10) -> 5603040.6
A10: 2 | B10: POPs | C10: unit | D10: =SUM('TOTALS(ACTIVE)'!C3:C10) -> 47
A11: 3 | B11: CORE DEVICES | C11: unit | D11: =SUM('TOTALS(ACTIVE)'!G22:AC22) -> 95
A12: 4 | B12: CUSTOMER SITES | C12: unit | D12: =SUM('TOTALS(ACTIVE)'!D22:F22) -> 1442
B14: NEDCO
A15: SN | B15: ITEM DESCRIPTION | C15: UoM | D15: QTY
A16: 1 | B16: CABLE INFRASTRUCTURE | C16: m | D16: =SUM('TOTALS(PASSIVE)'!C11:C18,'TOTALS(PASSIVE)'!J11:J18) -> 1665817
A17: 2 | B17: POPs | C17: unit | D17: ='TOTALS(ACTIVE)'!C23 -> 7
A18: 3 | B18: CORE DEVICES | C18: unit | D18: =SUM('TOTALS(ACTIVE)'!G23:AC23) -> 7
A19: 4 | B19: CUSTOMER SITES | C19: unit | D19: =SUM('TOTALS(ACTIVE)'!D23:F23) -> 4

Sheet AGE
A1: SN | B1: AGE | C1: NUMBER OF POPs(qty) | D1: CPE
D2: MIKROTIK | E2: ONT | F2: Master Backhaul DISTANCE | G2: Master Metro DISTANCE | H2: Total
A3: 1 | B3: 2020 | C3: =COUNTIF('PoP & EQUIPMENT'!$F$6:$F$83,AGE!B3) -> 12 | D3: {=COUNTIFS('MASTER-METRO'!O:O,AGE!B3:B9,'MASTER-METRO'!M:M,AGE!D2)} -> 36 | E3: {=COUNTIFS('MASTER-METRO'!O:O,AGE!B3:B9,'MASTER-METRO'!M:M,AGE!E2)} -> 32 | F3: {=SUMIFS('MASTER-BACKHAUL'!H:H,'MASTER-BACKHAUL'!K:K,AGE!B3:B9)} -> 144000 | G3: {=SUMIFS('MASTER-METRO'!J:J,'MASTER-METRO'!O:O,AGE!B3:B9)} -> 174291.55 | H3: =F3+G3 -> 318291.55
A4: 2 | B4: 2021 | C4: =COUNTIF('PoP & EQUIPMENT'!$F$6:$F$83,AGE!B4) -> 9 | D4: 176 | E4: 203 | F4: 599729.8 | G4: 759003.65 | H4: =F4+G4 -> 1358733.4
A5: 3 | B5: 2022 | C5: =COUNTIF('PoP & EQUIPMENT'!$F$6:$F$83,AGE!B5) -> 11 | D5: 91 | E5: 94 | F5: 685000 | G5: 358077.85 | H5: =F5+G5 -> 1043077.8
A6: 4 | B6: 2023 | C6: =COUNTIF('PoP & EQUIPMENT'!$F$6:$F$83,AGE!B6) -> 12 | D6: 170 | E6: 193 | F6: 2303406 | G6: 376070.9 | H6: =F6+G6 -> 2679476.9
A7: 5 | B7: 2024 | C7: =COUNTIF('PoP & EQUIPMENT'!$F$6:$F$83,AGE!B7) -> 10 | D7: 80 | E7: 306 | F7: 185000 | G7: 323114 | H7: =F7+G7 -> 508114
A8: 6 | B8: 2025 | C8: =COUNTIF('PoP & EQUIPMENT'!$F$6:$F$83,AGE!B8) -> 0 | D8: 57 | E8: 2 | F8: 701601 | G8: 248037.1 | H8: =F8+G8 -> 949638.1
D9: 0 | E9: 0 | F9: 0 | G9: 0 | H9: =F9+G9 -> 0
B10: TOTAL | C10: =SUM(C3:C9) -> 54 | D10: =SUM(D3:D9) -> 610 | E10: =SUM(E3:E9) -> 830 | F10: =SUM(F3:F9) -> 4618736.8 | G10: =SUM(G3:G9) -> 2238595 | H10: =SUM(H3:H9) -> 6857331.8

Sheet TOTALS(ACTIVE)
A1: SN | B1: REGION | C1: NUMBER OF POPs(qty) | D1: CPE | G1: ROUTERS | K1: OLTS | O1: SWITCHES | Z1: SERVERS
D2: MIKROTIK | E2: VSOL 2DAC | F2: ONT | G2: Mikrotik CCR1072-1G-8S+ | H2: Mikrotik CCR2216-1G-12XS-2XQ | I2: Mikrotik RB5009UG+S+ | J2: Cisco ASR1001-X | K2: VSOL OLT | L2: Furukawa OLT LD3008 | M2: Furukawa FK-OLT-G2500_SFU | N2: Furukawa OLT LD3032 | O2: Mikrotik CRS326-24S+2Q+ | P2: Mikrotik CRS305-1G-4S+ | Q2: Mikrotik CRS328-4C-20S-4S+ | R2: Mikrotik CRS317-1G-16S+ | S2: Mikrotik CRS510-8XS-2XQ | T2: FS Campus Switch (S5860-20SQ) | U2: Cisco WS-C3850-24P | V2: PLANET MGSW-28240F 24G + 4 10G | W2: PLANET MGSW-24160F Managed Switch | X2: Raisecom Switch RAX721-A | Y2: Raisecom Switch RAX711-C-R | Z2: HP ProLiant DL380p Gen8 | AA2: Dell PowerEdge R730 | AB2: HP ProLiant DL360 G7 | AC2: 24Online Server
A3: 1 | B3: ASHANTI | C3: =COUNTIF('PoP & EQUIPMENT'!$B$6:$B$83,'TOTALS(ACTIVE)'!B3) -> 4 | D3: {=COUNTIFS('MASTER-METRO'!B:B,'TOTALS(ACTIVE)'!B3:B18,'MASTER-METRO'!M:M,'TOTALS(ACTIVE)'!D2)} -> 44 | E3: {=COUNTIFS('MASTER-METRO'!B:B,'TOTALS(ACTIVE)'!B3:B18,'MASTER-METRO'!L:L,'TOTALS(ACTIVE)'!E2)} -> 0 | F3: {=COUNTIFS('MASTER-METRO'!B:B,'TOTALS(ACTIVE)'!B3:B18,'MASTER-METRO'!M:M,'TOTALS(ACTIVE)'!F2)} -> 53 | G3: {=SUMIF('PoP & EQUIPMENT'!$B:$B,'TOTALS(ACTIVE)'!$B$3:$B$18,'PoP & EQUIPMENT'!Y:AU)} -> 0 | H3: {=SUMIF('PoP & EQUIPMENT'!$B:$B,'TOTALS(ACTIVE)'!$B$3:$B$18,'PoP & EQUIPMENT'!Z:AV)} -> 4 | I3: {=SUMIF('PoP & EQUIPMENT'!$B:$B,'TOTALS(ACTIVE)'!$B$3:$B$18,'PoP & EQUIPMENT'!AF:BA)} -> 0 | J3: {=SUMIF('PoP & EQUIPMENT'!$B:$B,'TOTALS(ACTIVE)'!$B$3:$B$18,'PoP & EQUIPMENT'!AL:BG)} -> 0 | K3: {=SUMIF('PoP & EQUIPMENT'!$B:$B,'TOTALS(ACTIVE)'!$B$3:$B$18,'PoP & EQUIPMENT'!AG:BB)} -> 0 | L3: {=SUMIF('PoP & EQUIPMENT'!$B:$B,'TOTALS(ACTIVE)'!$B$3:$B$18,'PoP & EQUIPMENT'!AH:BC)} -> 0 | M3: {=SUMIF('PoP & EQUIPMENT'!$B:$B,'TOTALS(ACTIVE)'!$B$3:$B$18,'PoP & EQUIPMENT'!AI:BD)} -> 0 | N3: {=SUMIF('PoP & EQUIPMENT'!$B:$B,'TOTALS(ACTIVE)'!$B$3:$B$18,'PoP & EQUIPMENT'!AJ:BE)} -> 1 | O3: {=SUMIF('PoP & EQUIPMENT'!$B:$B,'TOTALS(ACTIVE)'!$B$3:$B$18,'PoP & EQUIPMENT'!AA:AW)} -> 0 | P3: {=SUMIF('PoP & EQUIPMENT'!$B:$B,'TOTALS(ACTIVE)'!$B$3:$B$18,'PoP & EQUIPMENT'!X:AT)} -> 0 | Q3: {=SUMIF('PoP & EQUIPMENT'!$B:$B,'TOTALS(ACTIVE)'!$B$3:$B$18,'PoP & EQUIPMENT'!AB:AX)} -> 1 | R3: {=SUMIF('PoP & EQUIPMENT'!$B:$B,'TOTALS(ACTIVE)'!$B$3:$B$18,'PoP & EQUIPMENT'!AC:AY)} -> 0 | S3: {=SUMIF('PoP & EQUIPMENT'!$B:$B,'TOTALS(ACTIVE)'!$B$3:$B$18,'PoP & EQUIPMENT'!AD:AZ)} -> 0 | T3: {=SUMIF('PoP & EQUIPMENT'!$B:$B,'TOTALS(ACTIVE)'!$B$3:$B$18,'PoP & EQUIPMENT'!AK:BF)} -> 0 | U3: {=SUMIF('PoP & EQUIPMENT'!$B:$B,'TOTALS(ACTIVE)'!$B$3:$B$18,'PoP & EQUIPMENT'!AM:BH)} -> 0 | V3: {=SUMIF('PoP & EQUIPMENT'!$B:$B,'TOTALS(ACTIVE)'!$B$3:$B$18,'PoP & EQUIPMENT'!AN:BI)} -> 0 | W3: {=SUMIF('PoP & EQUIPMENT'!$B:$B,'TOTALS(ACTIVE)'!$B$3:$B$18,'PoP & EQUIPMENT'!AO:BJ)} -> 1 | X3: {=SUMIF('PoP & EQUIPMENT'!$B:$B,'TOTALS(ACTIVE)'!$B$3:$B$18,'PoP & EQUIPMENT'!AP:BK)} -> 2 | Y3: {=SUMIF('PoP & EQUIPMENT'!$B:$B,'TOTALS(ACTIVE)'!$B$3:$B$18,'PoP & EQUIPMENT'!AQ:BL)} -> 0 | Z3: {=SUMIF('PoP & EQUIPMENT'!$B:$B,'TOTALS(ACTIVE)'!$B$3:$B$18,'PoP & EQUIPMENT'!AR:BM)} -> 0 | AA3: {=SUMIF('PoP & EQUIPMENT'!$B:$B,'TOTALS(ACTIVE)'!$B$3:$B$18,'PoP & EQUIPMENT'!AS:BN)} -> 0 | AB3: {=SUMIF('PoP & EQUIPMENT'!$B:$B,'TOTALS(ACTIVE)'!$B$3:$B$18,'PoP & EQUIPMENT'!AT:BO)} -> 0 | AC3: {=SUMIF('PoP & EQUIPMENT'!$B:$B,'TOTALS(ACTIVE)'!$B$3:$B$18,'PoP & EQUIPMENT'!AU:BP)} -> 0
A4: 2 | B4: CENTRAL | C4: =COUNTIF('PoP & EQUIPMENT'!$B$6:$B$83,'TOTALS(ACTIVE)'!B4) -> 5 | D4: 38 | E4: 0 | F4: 2 | G4: 1 | H4: 2 | I4: 0 | J4: 0 | K4: 0 | L4: 0 | M4: 0 | N4: 0 | O4: 0 | P4: 0 | Q4: 0 | R4: 0 | S4: 2 | T4: 0 | U4: 0 | V4: 0 | W4: 0 | X4: 2 | Y4: 0 | Z4: 0 | AA4: 0 | AB4: 0 | AC4: 0
A5: 3 | B5: EASTERN | C5: =COUNTIF('PoP & EQUIPMENT'!$B$6:$B$83,'TOTALS(ACTIVE)'!B5) -> 9 | D5: 55 | E5: 0 | F5: 7 | G5: 2 | H5: 5 | I5: 0 | J5: 0 | K5: 1 | L5: 0 | M5: 0 | N5: 0 | O5: 0 | P5: 0 | Q5: 1 | R5: 0 | S5: 2 | T5: 1 | U5: 0 | V5: 1 | W5: 0 | X5: 1 | Y5: 0 | Z5: 0 | AA5: 0 | AB5: 0 | AC5: 0
A6: 4 | B6: GREATER ACCRA | C6: =COUNTIF('PoP & EQUIPMENT'!$B$6:$B$83,'TOTALS(ACTIVE)'!B6) -> 15 | D6: 384 | E6: 0 | F6: 759 | G6: 1 | H6: 12 | I6: 2 | J6: 1 | K6: 1 | L6: 1 | M6: 1 | N6: 6 | O6: 0 | P6: 0 | Q6: 2 | R6: 1 | S6: 0 | T6: 3 | U6: 2 | V6: 3 | W6: 1 | X6: 4 | Y6: 1 | Z6: 1 | AA6: 1 | AB6: 2 | AC6: 1
A7: 5 | B7: VOLTA | C7: =COUNTIF('PoP & EQUIPMENT'!$B$6:$B$83,'TOTALS(ACTIVE)'!B7) -> 8 | D7: 32 | E7: 0 | F7: 0 | G7: 0 | H7: 2 | I7: 0 | J7: 0 | K7: 0 | L7: 0 | M7: 0 | N7: 0 | O7: 0 | P7: 2 | Q7: 0 | R7: 2 | S7: 1 | T7: 0 | U7: 0 | V7: 0 | W7: 0 | X7: 0 | Y7: 0 | Z7: 0 | AA7: 0 | AB7: 0 | AC7: 0
A8: 6 | B8: OTI | C8: =COUNTIF('PoP & EQUIPMENT'!$B$6:$B$83,'TOTALS(ACTIVE)'!B8) -> 0 | D8: 0 | E8: 0 | F8: 0 | G8: 0 | H8: 0 | I8: 0 | J8: 0 | K8: 0 | L8: 0 | M8: 0 | N8: 0 | O8: 0 | P8: 0 | Q8: 0 | R8: 0 | S8: 0 | T8: 0 | U8: 0 | V8: 0 | W8: 0 | X8: 0 | Y8: 0 | Z8: 0 | AA8: 0 | AB8: 0 | AC8: 0
A9: 7 | B9: WESTERN | C9: =COUNTIF('PoP & EQUIPMENT'!$B$6:$B$83,'TOTALS(ACTIVE)'!B9) -> 6 | D9: 58 | E9: 0 | F9: 10 | G9: 0 | H9: 2 | I9: 1 | J9: 0 | K9: 1 | L9: 0 | M9: 0 | N9: 0 | O9: 0 | P9: 0 | Q9: 0 | R9: 1 | S9: 3 | T9: 0 | U9: 0 | V9: 1 | W9: 0 | X9: 1 | Y9: 1 | Z9: 0 | AA9: 0 | AB9: 0 | AC9: 0
A10: 8 | B10: WESTERN NORTH | C10: =COUNTIF('PoP & EQUIPMENT'!$B$6:$B$83,'TOTALS(ACTIVE)'!B10) -> 0 | D10: 0 | E10: 0 | F10: 0 | G10: 0 | H10: 0 | I10: 0 | J10: 0 | K10: 0 | L10: 0 | M10: 0 | N10: 0 | O10: 0 | P10: 0 | Q10: 0 | R10: 0 | S10: 0 | T10: 0 | U10: 0 | V10: 0 | W10: 0 | X10: 0 | Y10: 0 | Z10: 0 | AA10: 0 | AB10: 0 | AC10: 0
A11: 9 | B11: BONO EAST | C11: =COUNTIF('PoP & EQUIPMENT'!$B$6:$B$83,'TOTALS(ACTIVE)'!B11) -> 0 | D11: 0 | E11: 0 | F11: 0 | G11: 0 | H11: 0 | I11: 0 | J11: 0 | K11: 0 | L11: 0 | M11: 0 | N11: 0 | O11: 0 | P11: 0 | Q11: 0 | R11: 0 | S11: 0 | T11: 0 | U11: 0 | V11: 0 | W11: 0 | X11: 0 | Y11: 0 | Z11: 0 | AA11: 0 | AB11: 0 | AC11: 0
A12: 10 | B12: AHAFO | C12: =COUNTIF('PoP & EQUIPMENT'!$B$6:$B$83,'TOTALS(ACTIVE)'!B12) -> 1 | D12: 0 | E12: 0 | F12: 0 | G12: 0 | H12: 0 | I12: 0 | J12: 0 | K12: 0 | L12: 0 | M12: 0 | N12: 0 | O12: 0 | P12: 1 | Q12: 0 | R12: 0 | S12: 0 | T12: 0 | U12: 0 | V12: 0 | W12: 0 | X12: 0 | Y12: 0 | Z12: 0 | AA12: 0 | AB12: 0 | AC12: 0
A13: 11 | B13: BRONG AHAFO | C13: =COUNTIF('PoP & EQUIPMENT'!$B$6:$B$83,'TOTALS(ACTIVE)'!B13) -> 1 | D13: 2 | E13: 0 | F13: 0 | G13: 1 | H13: 0 | I13: 0 | J13: 0 | K13: 0 | L13: 0 | M13: 0 | N13: 0 | O13: 0 | P13: 0 | Q13: 0 | R13: 0 | S13: 0 | T13: 0 | U13: 0 | V13: 0 | W13: 0 | X13: 0 | Y13: 0 | Z13: 0 | AA13: 0 | AB13: 0 | AC13: 0
A14: 12 | B14: SAVANNAH | C14: =COUNTIF('PoP & EQUIPMENT'!$B$6:$B$83,'TOTALS(ACTIVE)'!B14) -> 1 | D14: 0 | E14: 0 | F14: 0 | G14: 0 | H14: 0 | I14: 0 | J14: 0 | K14: 0 | L14: 0 | M14: 0 | N14: 0 | O14: 0 | P14: 0 | Q14: 0 | R14: 0 | S14: 0 | T14: 0 | U14: 0 | V14: 0 | W14: 0 | X14: 0 | Y14: 0 | Z14: 0 | AA14: 0 | AB14: 0 | AC14: 0
A15: 13 | B15: NORTHERN | C15: =COUNTIF('PoP & EQUIPMENT'!$B$6:$B$83,'TOTALS(ACTIVE)'!B15) -> 2 | D15: 2 | E15: 0 | F15: 0 | G15: 0 | H15: 1 | I15: 0 | J15: 0 | K15: 0 | L15: 0 | M15: 0 | N15: 0 | O15: 0 | P15: 1 | Q15: 1 | R15: 0 | S15: 0 | T15: 0 | U15: 0 | V15: 0 | W15: 0 | X15: 0 | Y15: 0 | Z15: 0 | AA15: 0 | AB15: 0 | AC15: 0
... A18: 16 | B18: UPPER WEST | C18: =COUNTIF('PoP & EQUIPMENT'!$B$6:$B$83,'TOTALS(ACTIVE)'!B18) -> 0 | D18: 0 | E18: 0 | F18: 0 | G18: 0 | H18: 0 | I18: 0 | J18: 0 | K18: 0 | L18: 0 | M18: 0 | N18: 0 | O18: 0 | P18: 0 | Q18: 0 | R18: 0 | S18: 0 | T18: 0 | U18: 0 | V18: 0 | W18: 0 | X18: 0 | Y18: 0 | Z18: 0 | AA18: 0 | AB18: 0 | AC18: 0
B20: TOTAL | C20: =SUM(C3:C19) -> 54 | D20: =SUM(D3:D19) -> 615 | F20: =SUM(F3:F19) -> 831 | G20: =SUM(G3:G19) -> 6 | H20: =SUM(H3:H19) -> 28 | I20: =SUM(I3:I19) -> 3 | J20: =SUM(J3:J19) -> 1 | K20: =SUM(K3:K19) -> 3 | L20: =SUM(L3:L19) -> 1 | M20: =SUM(M3:M19) -> 1 | ... AC20: =SUM(AC3:AC19) -> 1
B22: TOTAL(ECG) | C22: =SUM(C3:C10) -> 47 | D22: =SUM(D3:D10) -> 611 | F22: =SUM(F3:F10) -> 831 | G22: =SUM(G3:G10) -> 4 | H22: =SUM(H3:H10) -> 27 | I22: =SUM(I3:I10) -> 3 | J22: =SUM(J3:J10) -> 1 | K22: =SUM(K3:K10) -> 3 | L22: =SUM(L3:L10) -> 1 | M22: =SUM(M3:M10) -> 1 | ... AC22: =SUM(AC3:AC10) -> 1
B23: TOTAL(NEDCO) | C23: =SUM(C11:C18) -> 7 | D23: =SUM(D11:D18) -> 4 | F23: =SUM(F11:F18) -> 0 | G23: =SUM(G11:G18) -> 2 | H23: =SUM(H11:H18) -> 1 | I23: =SUM(I11:I18) -> 0 | J23: =SUM(J11:J18) -> 0 | K23: =SUM(K11:K18) -> 0 | L23: =SUM(L11:L18) -> 0 | M23: =SUM(M11:M18) -> 0 | ... AC23: =SUM(AC11:AC18) -> 0

Sheet TOTALS(PASSIVE)
A1: SN | B1: REGION | C1: METRO NETWORK | J1: BACKHAUL NETWORK
C2: Distance(m) | D2: Pole Brackets (pcs) | E2: Tension Clamps (pcs) | F2: Suspensions (pcs) | G2: Buckles (pcs) | H2: Steel Band (m) | I2: Closures (pcs) | J2: Distance(m) | K2: Pole Brackets (pcs) | L2: Tension Clamps (pcs) | M2: Suspensions (pcs) | N2: Buckles (pcs) | O2: Steel Band (m) | P2: Closures (pcs)
A3: 1 | B3: ASHANTI | C3: {=SUMIF('MASTER-METRO'!B:B,'TOTALS(PASSIVE)'!B3:B18,'MASTER-METRO'!J:J)} -> 210301.3 | D3: {=SUMIF('MASTER-METRO'!B:B,'TOTALS(PASSIVE)'!B3:B18,'MASTER-ACCESSORIES- METRO'!G:G)} -> 1155.088 | E3: {=SUMIF('MASTER-ACCESSORIES- METRO'!B:B,'TOTALS(PASSIVE)'!B3:B18,'MASTER-ACCESSORIES- METRO'!H:H)} -> 2521.3977 | F3: {=SUMIF('MASTER-ACCESSORIES- METRO'!B:B,'TOTALS(PASSIVE)'!B3:B18,'MASTER-ACCESSORIES- METRO'!I:I)} -> 1891.0483 | G3: {=SUMIF('MASTER-ACCESSORIES- METRO'!B:B,'TOTALS(PASSIVE)'!B3:B18,'MASTER-ACCESSORIES- METRO'!J:J)} -> 3151.7471 | H3: {=SUMIF('MASTER-ACCESSORIES- METRO'!B:B,'TOTALS(PASSIVE)'!B3:B18,'MASTER-ACCESSORIES- METRO'!K:K)} -> 3151.7471 | I3: {=SUMIF('MASTER-ACCESSORIES- METRO'!B:B,'TOTALS(PASSIVE)'!B3:B18,'MASTER-ACCESSORIES- METRO'!L:L)} -> 220.21558 | J3: {=SUMIF('MASTER-BACKHAUL'!B:B,'TOTALS(PASSIVE)'!B3:B18,'MASTER-BACKHAUL'!H:H)} -> 445800 | K3: {=SUMIF('MASTER-ACCESSORIES - BACKHAUL'!B:B,'TOTALS(PASSIVE)'!B3:B18,'MASTER-ACCESSORIES - BACKHAUL'!F:F)} -> 3020.8 | L3: {=SUMIF('MASTER-ACCESSORIES - BACKHAUL'!B:B,'TOTALS(PASSIVE)'!B3:B18,'MASTER-ACCESSORIES - BACKHAUL'!G:G)} -> 6041.6 | M3: {=SUMIF('MASTER-ACCESSORIES - BACKHAUL'!B:B,'TOTALS(PASSIVE)'!B3:B18,'MASTER-ACCESSORIES - BACKHAUL'!H:H)} -> 4531.2 | N3: {=SUMIF('MASTER-ACCESSORIES - BACKHAUL'!B:B,'TOTALS(PASSIVE)'!B3:B18,'MASTER-ACCESSORIES - BACKHAUL'!I:I)} -> 7552 | O3: {=SUMIF('MASTER-ACCESSORIES - BACKHAUL'!B:B,'TOTALS(PASSIVE)'!B3:B18,'MASTER-ACCESSORIES - BACKHAUL'!J:J)} -> 7552 | P3: {=SUMIF('MASTER-ACCESSORIES - BACKHAUL'!B:B,'TOTALS(PASSIVE)'!B3:B18,'MASTER-ACCESSORIES - BACKHAUL'!K:K)} -> 143.95
A4: 2 | B4: CENTRAL | C4: 119608 | D4: 631.55086 | E4: 1414.1371 | F4: 1060.6029 | G4: 1767.6714 | H4: 1767.6714 | I4: 102.65675 | J4: 520000 | K4: 2968.9143 | L4: 5937.8286 | M4: 4453.3714 | N4: 7422.2857 | O4: 7422.2857 | P4: 137.75
A5: 3 | B5: EASTERN | C5: 208681.7 | D5: 1218.518 | E5: 2428.3623 | F5: 1821.2717 | G5: 3035.4529 | H5: 3035.4529 | I5: 131.72043 | J5: 521400 | K5: 2983.0286 | L5: 5966.0571 | M5: 4474.5429 | N5: 7457.5714 | O5: 7457.5714 | P5: 139.35
A6: 4 | B6: GREATER ACCRA | C6: 1507321.2 | D6: 9769.854 | E6: 18453.111 | F6: 13839.834 | G6: 23066.389 | H6: 23066.389 | I6: 2203.6018 | J6: 444800 | K6: 3277.0286 | L6: 6554.0571 | M6: 4915.5429 | N6: 8192.5714 | O6: 8192.5714 | P6: 166.95
A7: 5 | B7: VOLTA | C7: 25159 | D7: 151.97714 | E7: 327.53143 | F7: 245.64857 | G7: 409.41429 | H7: 409.41429 | I7: 56.28975 | J7: 691135.8 | K7: 3954.5474 | L7: 7909.0949 | M7: 5931.8211 | N7: 9886.3686 | O7: 9886.3686 | P7: 185.78395
A8: 6 | B8: OTI | C8: 0 | D8: 0 | E8: 0 | F8: 0 | G8: 0 | H8: 0 | I8: 0 | J8: 0 | K8: 0 | L8: 0 | M8: 0 | N8: 0 | O8: 0 | P8: 0
A9: 7 | B9: WESTERN | C9: 191833.55 | D9: 1072.1423 | E9: 2237.732 | F9: 1678.299 | G9: 2797.165 | H9: 2797.165 | I9: 142.28789 | J9: 483000 | K9: 2293.8286 | L9: 4587.6571 | M9: 3440.7429 | N9: 5734.5714 | O9: 5734.5714 | P9: 106.25
A10: 8 | B10: WESTERN NORTH | C10: 0 | D10: 0 | E10: 0 | F10: 0 | G10: 0 | H10: 0 | I10: 0 | J10: 234000 | K10: 1338.3429 | L10: 2676.6857 | M10: 2007.5143 | N10: 3345.8571 | O10: 3345.8571 | P10: 61.5
A11: 9 | B11: BONO EAST | C11: 0 | D11: 0 | E11: 0 | F11: 0 | G11: 0 | H11: 0 | I11: 0 | J11: 82000 | K11: 469.37143 | L11: 938.74286 | M11: 704.05714 | N11: 1173.4286 | O11: 1173.4286 | P11: 22.5
A12: 10 | B12: AHAFO | C12: 0 | D12: 0 | E12: 0 | F12: 0 | G12: 0 | H12: 0 | I12: 0 | J12: 40000 | K12: 228.97143 | L12: 457.94286 | M12: 343.45714 | N12: 572.42857 | O12: 572.42857 | P12: 11
A13: 11 | B13: BRONG AHAFO | C13: 1948 | D13: 29.702857 | E13: 99.862857 | F13: 74.897143 | G13: 124.82857 | H13: 124.82857 | I13: 21.8345 | J13: 395601 | K13: 1078.92 | L13: 2157.84 | M13: 1618.38 | N13: 2697.3 | O13: 2697.3 | P13: 50.15025
A14: 12 | B14: SAVANNAH | C14: 0 | D14: 0 | E14: 0 | F14: 0 | G14: 0 | H14: 0 | I14: 0 | J14: 217000 | K14: 909.77143 | L14: 1819.5429 | M14: 1364.6571 | N14: 2274.4286 | O14: 2274.4286 | P14: 42.75
A15: 13 | B15: NORTHERN | C15: 2268 | D15: 2.5142857 | E15: 663.30286 | F15: 497.47714 | G15: 829.12857 | H15: 829.12857 | I15: 43.98475 | J15: 350000 | K15: 1910.5714 | L15: 3821.1429 | M15: 2865.8571 | N15: 4776.4286 | O15: 4776.4286 | P15: 88.5
... A18: 16 | B18: UPPER WEST | C18: 0 | D18: 0 | E18: 0 | F18: 0 | G18: 0 | H18: 0 | I18: 0 | J18: 279000 | K18: 1595.8857 | L18: 3191.7714 | M18: 2393.8286 | N18: 3989.7143 | O18: 3989.7143 | P18: 73.75
B20: TOTAL | C20: =SUM(C3:C19) -> 2267120.8 | D20: =SUM(D3:D19) -> 14031.347 | E20: =SUM(E3:E19) -> 28177.095 | F20: =SUM(F3:F19) -> 21132.821 | G20: =SUM(G3:G19) -> 35221.369 | H20: =SUM(H3:H19) -> 35221.369 | I20: =SUM(I3:I19) -> 2924.2665 | J20: =SUM(J3:J19) -> 5001736.8 | ... P20: =SUM(P3:P19) -> 1312.6842
B23: ECG | C23: =SUM(C3:C10) -> 2262904.8 | D23: =SUM(D3:D10) -> 13999.13 | E23: =SUM(E3:E10) -> 27382.272 | F23: =SUM(F3:F10) -> 20536.704 | G23: =SUM(G3:G10) -> 34227.84 | H23: =SUM(H3:H10) -> 34227.84 | I23: =SUM(I3:I10) -> 2856.7722 | J23: =SUM(J3:J10) -> 3340135.8 | ... P23: =SUM(P3:P10) -> 941.53395 | Q23: =SUM(C23:P23) -> 5925659.4
B24: NEDCO | C24: =SUM(C11:C18) -> 4216 | D24: =SUM(D11:D18) -> 32.217143 | E24: =SUM(E11:E18) -> 794.82286 | F24: =SUM(F11:F18) -> 596.11714 | G24: =SUM(G11:G18) -> 993.52857 | H24: =SUM(H11:H18) -> 993.52857 | I24: =SUM(I11:I18) -> 67.49425 | J24: =SUM(J11:J18) -> 1661601 | ... P24: =SUM(P11:P18) -> 371.15025 | Q24: =SUM(C24:P24) -> 1745564.9

Sheet PoP & EQUIPMENT
A3: SN | B3: REGION | C3: TERRITORY | D3: LOCATION | E3: COORDINATES | F3: AGE | G3: POP TYPE | H3: cabinet | T3: ODF | BT3: Power
H4: 4u | I4: 6u | J4: 9u | K4: 10u | L4: 12u | M4: 21u | N4: 22u | O4: 27u | P4: 29u | Q4: 32u | R4: 42u | S4: 9core | T4: 12core | U4: 24core | V4: 48core | W4: 96core | X4: Mikrotik CRS305-1G-4S+ | Y4: Mikrotik CCR1072-1G-8S+ | Z4: Mikrotik CCR2216-1G-12XS-2XQ | AA4: Mikrotik CRS326-24S+2Q+ | AB4: Mikrotik CRS328-4C-20S-4S+ | AC4: Mikrotik CRS317-1G-16S+ | AD4: Mikrotik CRS510-8XS-2XQ | AE4: Mikrotik CRS504-8XS-2XQ | AF4: Mikrotik RB5009UG+S+ | AG4: VSOL OLT | AH4: Furukawa OLT LD3008 | AI4: Furukawa FK-OLT-G2500_SFU | AJ4: Furukawa OLT LD3032 | AK4: FS Campus Switch (S5860-20SQ) | AL4: Cisco ASR1001-X | AM4: Cisco WS-C3850-24P | AN4: PLANET MGSW-28240F 24G + 4 10G | AO4: PLANET MGSW-24160F Managed Switch | AP4: Raisecom Switch RAX721-A | AQ4: Raisecom Switch RAX711-C-R | AR4: HP ProLiant DL380p Gen8 | AS4: Dell PowerEdge R730 | AT4: HP ProLiant DL360 G7 | AU4: 24Online Server | BE4: 10G(Simplex) | BN4: 10G(Duplex) | BS4: GPON | BT4: UPS | BU4: Stabilizer | BV4: battery bank | BY4: Inverter | CA4: AVR | CB4: Solar
AV5: Total | AW5: Copper | AX5: 2km | AY5: 3km | AZ5: 10km | BA5: 20km | BB5: 40km | BC5: 60km | BD5: 80km | BE5: Copper | BF5: 2km | BG5: 10km | BH5: 20km | BI5: 40km | BJ5: 60km | BK5: 80km | BL5: 100km | BM5: 120km | BN5: 2km | BO5: 10km | BP5: 80km | BQ5: 100km | BR5: 120km | BS5: 20km | BV5: battery Containment | BW5: 100AH | BX5: 200AH | BY5: 5KVA | BZ5: 3KVA
A6: 1 | B6: ASHANTI | C6: ECG | D6: OBUASI | E6: 6.204062 -1.677247 | F6: 2022 | G6: Indoor | H6: 1 | V6: 2 | Z6: 1 | AP6: 1 | AV6: =SUM(AW6:BS6) -> 8 | BA6: 2 | BC6: 1 | BD6: 1 | BL6: 3 | BN6: 1 | BX6: 2 | BZ6: 1
A7: 2 | B7: ASHANTI | C7: ECG | D7: KUMASI-ASANTEMAN | E7: 6.708774 -1.627550 | F7: 2020 | G7: Outdoor | N7: 1 | V7: 3 | Z7: 1 | AJ7: 1 | AO7: 1 | AV7: =SUM(AW7:BS7) -> 3 | AZ7: 1 | BD7: 1 | BG7: 1 | BV7: 1 | BX7: 4 | BY7: 1
A8: 3 | B8: ASHANTI | C8: ECG | D8: KUBEASE | E8: 6.675194 -1.380315 | F8: 2022 | G8: Indoor | H8: 1 | V8: 2 | Z8: 1 | AP8: 1 | AV8: =SUM(AW8:BS8) -> 7 | BA8: 2 | BD8: 1 | BG8: 1 | BI8: 1 | BK8: 1 | BL8: 1 | BX8: 2 | BZ8: 1
A9: 4 | B9: ASHANTI | C9: ECG | D9: KUMASI-ROMANHILL | E9: 6.696086 , -1.617477 | F9: 2020 | G9: Outdoor | N9: 1 | V9: 2 | Z9: 1 | AB9: 1 | AV9: =SUM(AW9:BS9) -> 29 | AZ9: 11 | BC9: 7 | BD9: 2 | BE9: 2 | BG9: 2 | BI9: 1 | BJ9: 1 | BK9: 2 | BL9: 1 | BV9: 1 | BX9: 4 | BY9: 1
B11: TOTAL | H11: =SUM(H6:H9) -> 2 | I11: =SUM(I6:I9) -> 0 | J11: =SUM(J6:J9) -> 0 | K11: =SUM(K6:K9) -> 0 | L11: =SUM(L6:L9) -> 0 | M11: =SUM(M6:M9) -> 0 | N11: =SUM(N6:N9) -> 2 | O11: =SUM(O6:O9) -> 0 | ... AC11: =SUM(AC6:AC9) -> 0 | AF11: =SUM(AF6:AF9) -> 0 | AH11: =SUM(AH6:AH9) -> 0 | AI11: =SUM(AI6:AI9) -> 0 | AJ11: =SUM(AJ6:AJ9) -> 1 | AK11: =SUM(AK6:AK9) -> 0 | AL11: =SUM(AL6:AL9) -> 0 | AM11: =SUM(AM6:AM9) -> 0 | AN11: =SUM(AN6:AN9) -> 0 | AO11: =SUM(AO6:AO9) -> 1 | ... AU11: =SUM(AU6:AU9) -> 0 | BT11: =SUM(BT6:BT9) -> 0 | BU11: =SUM(BU6:BU9) -> 0 | BW11: =SUM(BW6:BW9) -> 0 | BX11: =SUM(BX6:BX9) -> 12 | BY11: =SUM(BY6:BY9) -> 2 | BZ11: =SUM(BZ6:BZ9) -> 2 | CA11: =SUM(CA6:CA9) -> 0 | CB11: =SUM(CB6:CB9) -> 0
A13: 1 | B13: AHAFO | C13: NEDCO | D13: BECHEM | E13: 7.081587 -2.02320 | F13: 2023 | G13: Indoor | X13: 1 | AV13: =SUM(AW13:BS13) -> 3 | BD13: 1 | BQ13: 2
A14: 2 | B14: BRONG AHAFO | C14: NEDCO | D14: SUNYANI | E14: 7.319474, -2.317673 | F14: 2023 | G14: Indoor | Y14: 1 | AV14: =SUM(AW14:BS14) -> 8 | AZ14: 3 | BA14: 2 | BC14: 1 | BD14: 1 | BP14: 1
B16: TOTAL | H16: =SUM(H13:H14) -> 0 | I16: =SUM(I13:I14) -> 0 | J16: =SUM(J13:J14) -> 0 | K16: =SUM(K13:K14) -> 0 | L16: =SUM(L13:L14) -> 0 | M16: =SUM(M13:M14) -> 0 | N16: =SUM(N13:N14) -> 0 | O16: =SUM(O13:O14) -> 0 | ... AC16: =SUM(AC13:AC14) -> 0 | AF16: =SUM(AF13:AF14) -> 0 | AH16: =SUM(AH13:AH14) -> 0 | AI16: =SUM(AI13:AI14) -> 0 | AJ16: =SUM(AJ13:AJ14) -> 0 | AK16: =SUM(AK13:AK14) -> 0 | AL16: =SUM(AL13:AL14) -> 0 | AM16: =SUM(AM13:AM14) -> 0 | AN16: =SUM(AN13:AN14) -> 0 | AO16: =SUM(AO13:AO14) -> 0 | ... CB16: =SUM(CB13:CB14) -> 0
A18: 1 | B18: CENTRAL | C18: ECG | D18: CAPE COAST ECG OFFICE | E18: 5.117613 -1.244324 | F18: 2020 | G18: Indoor | V18: 3 | Z18: 1 | AP18: 1 | AV18: =SUM(AW18:BS18) -> 26 | AW18: 1 | AZ18: 1 | BA18: 16 | BC18: 3 | BD18: 1 | BE18: 2 | BK18: 1 | BL18: 1 | BX18: 4 | BY18: 1
A19: 2 | B19: CENTRAL | C19: ECG | D19: WINNEBA | E19: 5.379158 -0.652166 | F19: 2022 | G19: Outdoor | N19: 1 | Z19: 1 | AP19: 1 | AV19: =SUM(AW19:BS19) -> 9 | AW19: 1 | BA19: 4 | BD19: 1 | BE19: 2 | BK19: 1 | BW19: 4 | BY19: 1
A20: 4 | B20: CENTRAL | C20: ECG | D20: SWEDRU | E20: 5.535335 -0.692072 | F20: 2024 | G20: Outdoor | N20: 1 | Y20: 1 | AV20: =SUM(AW20:BS20) -> 2 | BJ20: 2
A21: 5 | B21: CENTRAL | C21: ECG | D21: MANKESSIM | E21: 5.2725239 -0.993339 | F21: 2023 | G21: Outdoor | AD21: 1 | AV21: =SUM(AW21:BS21) -> 3 | BA21: 1 | BJ21: 1 | BK21: 1
A22: 6 | B22: CENTRAL | C22: ECG | D22: ASSIN FOSU | E22: 5.690891 -1.2767645 | F22: 2024 | G22: Indoor | AD22: 1 | AV22: =SUM(AW22:BS22) -> 0
B24: TOTAL | H24: =SUM(H18:H21) -> 0 | I24: =SUM(I18:I21) -> 0 | J24: =SUM(J18:J21) -> 0 | K24: =SUM(K18:K21) -> 0 | L24: =SUM(L18:L21) -> 0 | M24: =SUM(M18:M21) -> 0 | N24: =SUM(N18:N21) -> 2 | O24: =SUM(O18:O21) -> 0 | ... AD24: =SUM(AD18:AD21) -> 1 | AF24: =SUM(AF18:AF21) -> 0 | AH24: =SUM(AH18:AH21) -> 0 | AI24: =SUM(AI18:AI21) -> 0 | AJ24: =SUM(AJ18:AJ21) -> 0 | AK24: =SUM(AK18:AK21) -> 0 | AL24: =SUM(AL18:AL21) -> 0 | AM24: =SUM(AM18:AM21) -> 0 | AN24: =SUM(AN18:AN21) -> 0 | AO24: =SUM(AO18:AO21) -> 0 | ... CB24: =SUM(CB18:CB21) -> 0
A26: 1 | B26: EASTERN | C26: ECG | D26: ABURI | E26: 5.873167 -0.157818 | F26: 2021 | G26: Outdoor | N26: 1 | V26: 2 | Z26: 1 | AB26: 1 | AG26: 1 | AV26: =SUM(AW26:BS26) -> 19 | BA26: 10 | BB26: 3 | BC26: 2 | BD26: 2 | BF26: 2 | BW26: 4 | BY26: 1
A27: 2 | B27: EASTERN | C27: ECG | D27: NKAWKAW | E27: 6.538083 -0.758909 | F27: 2022 | G27: Outdoor | N27: 1 | V27: 2 | Z27: 1 | AK27: 1 | AV27: =SUM(AW27:BS27) -> 11 | AW27: 1 | BA27: 2 | BC27: 1 | BD27: 2 | BF27: 2 | BJ27: 1 | BL27: 2 | BW27: 4 | BY27: 1
A28: 3 | B28: EASTERN | C28: ECG | D28: BUNSO | E28: 6.293186, -0.472517 | F28: 2023 | G28: Indoor | V28: 2 | Y28: 1 | AV28: =SUM(AW28:BS28) -> 4 | BK28: 2 | BL28: 2 | BX28: 2 | BZ28: 1
A29: 4 | B29: EASTERN | C29: ECG | D29: ASAMANKESE | E29: 5.857256 -0.661452 | F29: 2024 | G29: Outdoor | N29: 1 | AD29: 1 | AV29: =SUM(AW29:BS29) -> 2 | BJ29: 2
A30: 5 | B30: EASTERN | C30: ECG | D30: AKIM ODA | E30: 5.93694 -0.972932 | F30: 2024 | G30: Indoor | AD30: 1 | AV30: =SUM(AW30:BS30) -> 4 | AZ30: 1 | BA30: 1 | BK30: 2
A31: 6 | B31: EASTERN | C31: ECG | D31: SUHUM | E31: 6.027995 , -0.449935 | F31: 2022 | G31: Outdoor | N31: 1 | V31: 1 | Z31: 1 | AV31: =SUM(AW31:BS31) -> 7 | AW31: 1 | BA31: 1 | BD31: 1 | BJ31: 1 | BK31: 2 | BL31: 1 | BW31: 4 | BY31: 1
A32: 7 | B32: EASTERN | C32: ECG | D32: KOFORIDUA | E32: 6.091218 -0.258441 | F32: 2020 | G32: Outdoor | N32: 1 | V32: 2 | Y32: 1 | AN32: 1 | AV32: =SUM(AW32:BS32) -> 11 | AZ32: 1 | BA32: 3 | BD32: 7 | BW32: 4 | BY32: 1
A33: 8 | B33: EASTERN | C33: ECG | D33: KONONGO | E33: 6.624025 -1.2180472 | F33: 2024 | G33: Outdoor | N33: 1 | Z33: 1 | AV33: =SUM(AW33:BS33) -> 2 | BJ33: 1 | BK33: 1 | BU33: 1 | BW33: 4 | BZ33: 1 | CA33: 1
A34: 9 | B34: EASTERN | C34: ECG | D34: AKUSE | E34: 6.097085 0.064292 | F34: 2021 | G34: Outdoor | N34: 1 | V34: 2 | Z34: 1 | AP34: 1 | AV34: =SUM(AW34:BS34) -> 12 | BA34: 1 | BB34: 2 | BD34: 5 | BG34: 2 | BJ34: 1 | BK34: 1 | BV34: 1
B36: TOTAL | H36: =SUM(H26:H34) -> 0 | I36: =SUM(I26:I34) -> 0 | J36: =SUM(J26:J34) -> 0 | K36: =SUM(K26:K34) -> 0 | L36: =SUM(L26:L34) -> 0 | M36: =SUM(M26:M34) -> 0 | N36: =SUM(N26:N34) -> 7 | O36: =SUM(O26:O34) -> 0 | ... AD36: =SUM(AD26:AD34) -> 2 | AF36: =SUM(AF26:AF34) -> 0 | AG36: =SUM(AG26:AG34) -> 1 | AH36: =SUM(AH26:AH34) -> 0 | AI36: =SUM(AI26:AI34) -> 0 | AJ36: =SUM(AJ26:AJ34) -> 0 | AK36: =SUM(AK26:AK34) -> 1 | AL36: =SUM(AL26:AL34) -> 0 | AM36: =SUM(AM26:AM34) -> 0 | ... DJ36: =SUM(DJ26:DJ34) -> 0
A38: 1 | B38: GREATER ACCRA | C38: ECG | D38: CANTONMENT | E38: 5.584144 -0.164072 | F38: 2020 | G38: Indoor | R38: 2 | V38: 5 | Y38: 1 | Z38: 1 | AJ38: 1 | AK38: 1 | AL38: 1 | AM38: 2 | AP38: 1 | AR38: 1 | AS38: 1 | AT38: 2 | AU38: 1 | AV38: =SUM(AW38:BS38) -> 84 | AW38: 6 | BA38: 14 | BB38: 2 | BC38: 3 | BD38: 1 | BE38: 8 | BF38: 2 | BG38: 3 | BI38: 8 | BJ38: 9 | BK38: 1 | BS38: 27 | BX38: 8 | BY38: 1
A39: 2 | B39: GREATER ACCRA | C39: ECG | D39: MADINA | E39: 5.677437 -0.167211 | F39: 2020 | G39: Outdoor | N39: 1 | V39: 2 | Z39: 1 | AJ39: 1 | AO39: 1 | AV39: =SUM(AW39:BS39) -> 33 | AX39: 1 | BA39: 6 | BD39: 5 | BI39: 4 | BJ39: 7 | BS39: 10 | BX39: 4 | BY39: 1
A40: 3 | B40: GREATER ACCRA | C40: ECG | D40: RACK AFRICA DC | E40: 5.571390 -0.209692 | F40: 2020 | G40: Indoor | K40: 1 | V40: 3 | Z40: 1 | AK40: 1 | AP40: 1 | AV40: =SUM(AW40:BS40) -> 52 | AW40: 2 | AY40: 1 | AZ40: 3 | BA40: 21 | BC40: 2 | BD40: 3 | BE40: 2 | BF40: 1 | BG40: 10 | BH40: 1 | BI40: 2 | BJ40: 4
A41: 4 | B41: GREATER ACCRA | C41: ECG | D41: McCARTHY | E41: 5.563084 -0.299930 | F41: 2020 | G41: Outdoor | N41: 1 | V41: 2 | Z41: 1 | AJ41: 1 | AP41: 1 | AV41: =SUM(AW41:BS41) -> 43 | BA41: 10 | BB41: 2 | BC41: 3 | BD41: 3 | BE41: 2 | BJ41: 5 | BK41: 2 | BS41: 16 | BW41: 4 | BY41: 1
A42: 5 | B42: GREATER ACCRA | C42: ECG | D42: APOLONIA | E42: 5.804244 -0.091288 | F42: 2023 | G42: Indoor | AQ42: 1 | AV42: =SUM(AW42:BS42) -> 4 | AY42: 3 | BJ42: 1
A43: 6 | B43: GREATER ACCRA | C43: ECG | D43: GIL CITY CAMPUS | E43: 5.622542 -0.186943 | F43: 2022 | G43: Outdoor | N43: 1 | V43: 2 | Z43: 1 | AB43: 1 | AJ43: 1 | AV43: =SUM(AW43:BS43) -> 23 | AY43: 5 | BA43: 5 | BE43: 2 | BG43: 2 | BI43: 2 | BJ43: 2 | BS43: 5 | BW43: 4 | BY43: 1
A44: 7 | B44: GREATER ACCRA | C44: ECG | D44: TEMA FREEZONES | E44: 5.693232 0.006872 | F44: 2020 | G44: Indoor | R44: 1 | V44: 3 | Z44: 1 | AJ44: 1 | AP44: 1 | AV44: =SUM(AW44:BS44) -> 44 | AW44: 2 | AY44: 1 | BA44: 13 | BB44: 3 | BC44: 1 | BE44: 4 | BI44: 2 | BJ44: 6 | BS44: 12 | BX44: 4 | BY44: 1
A45: 8 | B45: GREATER ACCRA | C45: ECG | D45: ETIX(ONIX DC) | E45: 5.766104 -0.110246 | F45: 2021 | G45: Indoor | R45: 1 | V45: 1 | Z45: 1 | AI45: 1 | AN45: 1 | AV45: =SUM(AW45:BS45) -> 32 | AZ45: 1 | BA45: 5 | BB45: 2 | BD45: 8 | BE45: 2 | BG45: 2 | BI45: 3 | BJ45: 2 | BK45: 1 | BS45: 6
A46: 9 | B46: GREATER ACCRA | C46: ECG | D46: GIJ DZORWULU | E46: 5.622542 -0.186943 | F46: 2021 | G46: Indoor | L46: 1 | T46: 1 | Z46: 1 | AH46: 1 | AV46: =SUM(AW46:BS46) -> 14 | AY46: 1 | BA46: 2 | BE46: 2 | BJ46: 3 | BS46: 6 | BW46: 4 | BY46: 1
A47: 10 | B47: GREATER ACCRA | C47: ECG | D47: NUNGUA | E47: 5.614282 -0.089064 | F47: 2020 | G47: Outdoor | N47: 1 | V47: 1 | Z47: 1 | AC47: 1 | AJ47: 1 | AV47: =SUM(AW47:BS47) -> 23 | BA47: 6 | BC47: 2 | BG47: 4 | BH47: 1 | BI47: 2 | BJ47: 1 | BS47: 7 | BW47: 4 | BY47: 1
A48: 11 | B48: GREATER ACCRA | C48: ECG | D48: AMASAMAN | E48: 5.704165 , -0.300260 | F48: 2021 | G48: Outdoor | N48: 1 | V48: 1 | Z48: 1 | AN48: 1 | AV48: =SUM(AW48:BS48) -> 26 | BA48: 18 | BB48: 1 | BD48: 2 | BE48: 2 | BJ48: 3 | BV48: 1 | BW48: 4 | BY48: 1
A49: 12 | B49: GREATER ACCRA | C49: ECG | D49: DAWHENYA | E49: 5.757568 0.083992 | F49: 2021 | G49: Indoor | O49: 1 | V49: 1 | Z49: 1 | AB49: 1 | AF49: 1 | AG49: 1 | AV49: =SUM(AW49:BS49) -> 22 | BA49: 17 | BB49: 1 | BC49: 1 | BI49: 1 | BN49: 2 | BU49: 1 | BV49: 1 | BX49: 4 | BY49: 1
A50: 13 | B50: GREATER ACCRA | C50: ECG | D50: DAWA | E50: 5.869013 0.263467 | F50: 2020 | G50: Indoor | V50: 1 | Z50: 1 | AK50: 1 | AV50: =SUM(AW50:BS50) -> 14 | BA50: 3 | BB50: 2 | BD50: 4 | BJ50: 3 | BK50: 2
A51: 14 | B51: GREATER ACCRA | C51: ECG | D51: AQUA SAFARI (ADA 1) | E51: 5.824832 0.619369 | F51: 2021 | G51: Outdoor | V51: 1 | AF51: 1 | AN51: 1 | AV51: =SUM(AW51:BS51) -> 12 | AW51: 2 | AZ51: 2 | BA51: 5 | BB51: 1 | BC51: 1 | BD51: 1
A52: 15 | B52: GREATER ACCRA | C52: ECG | D52: ADA 2 | E52: 5.893987 0.503603 | F52: 2022 | G52: Outdoor | N52: 1 | V52: 1 | AV52: =SUM(AW52:BS52) -> 0 | BW52: 4 | BX52: 4 | BY52: 1
B54: TOTAL | H54: =SUM(H38:H52) -> 0 | I54: =SUM(I38:I52) -> 0 | J54: =SUM(J38:J52) -> 0 | K54: =SUM(K38:K52) -> 1 | L54: =SUM(L38:L52) -> 1 | M54: =SUM(M38:M52) -> 0 | N54: =SUM(N38:N52) -> 6 | O54: =SUM(O38:O52) -> 1 | ... AC54: =SUM(AC38:AC52) -> 1 | AF54: =SUM(AF38:AF52) -> 2 | AG54: =SUM(AG38:AG52) -> 1 | AH54: =SUM(AH38:AH52) -> 1 | AI54: =SUM(AI38:AI52) -> 1 | AJ54: =SUM(AJ38:AJ52) -> 6 | AK54: =SUM(AK38:AK52) -> 3 | AL54: =SUM(AL38:AL52) -> 1 | AM54: =SUM(AM38:AM52) -> 2 | ... AV54: =SUM(AV38:AV52) -> 426 | BT54: =SUM(BT38:BT52) -> 0 | BU54: =SUM(BU38:BU52) -> 1 | BW54: =SUM(BW38:BW52) -> 24 | BX54: =SUM(BX38:BX52) -> 24 | BY54: =SUM(BY38:BY52) -> 10 | BZ54: =SUM(BZ38:BZ52) -> 0 | CA54: =SUM(CA38:CA52) -> 0 | CB54: =SUM(CB38:CB52) -> 0
A56: 1 | B56: SAVANNAH | C56: NEDCO | D56: TINGA | E56: 8.592593 -2.230888 | F56: 2024 | G56: Outdoor | N56: 1 | BX56: 4 | BY56: 1
B58: TOTAL | H58: =SUM(H56:H57) -> 0 | I58: =SUM(I56:I57) -> 0 | J58: =SUM(J56:J57) -> 0 | K58: =SUM(K56:K57) -> 0 | L58: =SUM(L56:L57) -> 0 | M58: =SUM(M56:M57) -> 0 | N58: =SUM(N56:N57) -> 1 | O58: =SUM(O56:O57) -> 0 | ... AD58: =SUM(AD56:AD57) -> 0 | AF58: =SUM(AF56:AF57) -> 0 | AG58: =SUM(AG56:AG57) -> 0 | AH58: =SUM(AH56:AH57) -> 0 | AI58: =SUM(AI56:AI57) -> 0 | AJ58: =SUM(AJ56:AJ57) -> 0 | AK58: =SUM(AK56:AK57) -> 0 | AL58: =SUM(AL56:AL57) -> 0 | AM58: =SUM(AM56:AM57) -> 0 | ... CB58: =SUM(CB56:CB57) -> 0
A60: 1 | B60: NORTHERN | C60: NEDCO | D60: DIARI | E60: 9.865745, -0.870686 | F60: 2024 | G60: Outdoor | N60: 1 | X60: 1 | AV60: =SUM(AW60:BU60) -> 4 | BD60: 2 | BK60: 2 | BX60: 4 | BY60: 1
A61: 2 | B61: NORTH EAST | C61: NEDCO | D61: WALEWALE | E61: 10.35291 -0.7975752 | F61: 2024 | G61: Outdoor | N61: 1 | X61: 1 | AV61: =SUM(AW61:BU61) -> 4 | BD61: 2 | BK61: 2 | BX61: 4 | BY61: 1
A62: 3 | B62: UPPER EAST | C62: NEDCO | D62: BOLGA | E62: 10.773969 -0.855456 | F62: 2024 | G62: Outdoor | N62: 1 | Y62: 1 | AV62: =SUM(AW62:BU62) -> 4 | BA62: 3 | BK62: 1 | BX62: 4 | BY62: 1
A63: 5 | B63: NORTHERN | C63: NEDCO | D63: TAMALE | E63: 9.417364, -0.860597 | F63: 2023 | G63: Outdoor | N63: 1 | Z63: 1 | AB63: 1 | AV63: =SUM(AW63:BU63) -> 15 | AY63: 2 | AZ63: 3 | BA63: 2 | BD63: 6 | BG63: 1 | BK63: 1 | BX63: 4 | BY63: 1
B65: TOTAL | H65: =SUM(H63) -> 0 | I65: =SUM(I63) -> 0 | J65: =SUM(J63) -> 0 | K65: =SUM(K63) -> 0 | L65: =SUM(L63) -> 0 | M65: =SUM(M63) -> 0 | N65: =SUM(N63) -> 1 | O65: =SUM(O63) -> 0 | ... W65: =SUM(W63) -> 0 | X65: =SUM(X59:X64) -> 2 | Y65: =SUM(Y59:Y64) -> 1 | Z65: =SUM(Z59:Z64) -> 1 | AA65: =SUM(AA59:AA64) -> 0 | AB65: =SUM(AB59:AB64) -> 1 | AC65: =SUM(AC59:AC64) -> 0 | AD65: =SUM(AD59:AD64) -> 0 | AE65: =SUM(AE59:AE64) -> 0 | ... AR65: =SUM(AR59:AR64) -> 0 | AS65: =SUM(AS63) -> 0 | AT65: =SUM(AT63) -> 0 | AU65: =SUM(AU63) -> 0 | AV65: =SUM(AV60:AV63) -> 27 | AW65: =SUM(AW63) -> 0 | AX65: =SUM(AX63) -> 0 | AY65: =SUM(AY63) -> 2 | AZ65: =SUM(AZ63) -> 3 | BA65: =SUM(BA63) -> 2 | BB65: =SUM(BB63) -> 0 | BC65: =SUM(BC63) -> 0 | BD65: =SUM(BD63) -> 6 | BT65: =SUM(BT41:BT59) -> 0 | BU65: =SUM(BU41:BU59) -> 2 | BW65: =SUM(BW41:BW59) -> 48 | BX65: =SUM(BX41:BX59) -> 44 | BY65: =SUM(BY41:BY59) -> 20 | BZ65: =SUM(BZ41:BZ59) -> 0 | CA65: =SUM(CA41:CA59) -> 0 | CB65: =SUM(CB41:CB59) -> 0
A67: 1 | B67: VOLTA | C67: ECG | D67: SOGAKOPE | E67: 5.997086 0.595473 | F67: 2021 | G67: Indoor | V67: 1 | AD67: 1 | AV67: =SUM(AW67:BS67) -> 4 | BC67: 1 | BI67: 1 | BJ67: 1 | BK67: 1
A68: 2 | B68: VOLTA | C68: ECG | D68: AFLAO | E68: 6.117796 1.190115 | F68: 2021 | G68: Indoor | V68: 2 | Z68: 1 | AV68: =SUM(AW68:BS68) -> 5 | BE68: 1 | BH68: 1 | BJ68: 1 | BL68: 2
A69: 3 | B69: VOLTA | C69: ECG | D69: ZIOPE | E69: 6.425261, 0.732761 | F69: 2023 | G69: Indoor | I69: 1 | V69: 1 | X69: 1 | AV69: =SUM(AW69:BS69) -> 2 | BL69: 2 | BX69: 4 | BY69: 1
A70: 4 | B70: VOLTA | C70: ECG | D70: HO | E70: 6.582267, 0.480364 | F70: 2023 | G70: Indoor | I70: 1 | W70: 1 | Z70: 1 | AV70: =SUM(AW70:BS70) -> 4 | BA70: 2 | BL70: 1 | BR70: 1 | BX70: 4 | BY70: 1
A71: 5 | B71: VOLTA | C71: ECG | D71: JUAPONG | E71: 6.248250, 0.138992 | F71: 2023 | G71: Outdoor | N71: 1 | X71: 1 | AV71: =SUM(AW71:BS71) -> 3 | BB71: 1 | BP71: 2 | BX71: 4 | BY71: 1
A72: 6 | B72: VOLTA | C72: ECG | D72: KPANDO | E72: 6.992942, 0.291481 | F72: 2023 | G72: Indoor | AC72: 1 | AV72: =SUM(AW72:BS72) -> 2 | BJ72: 1 | BQ72: 1
A73: 7 | B73: VOLTA | C73: ECG | D73: HOHOE | E73: 7.143814, 0.476975 | F73: 2023 | G73: Indoor | I73: 1 | V73: 1 | AC73: 1 | AV73: =SUM(AW73:BS73) -> 3 | AY73: 1 | BB73: 1 | BJ73: 1 | BX73: 4 | BY73: 1
A74: 8 | B74: VOLTA | C74: ECG | D74: AKATSI | E74: 6.127324 0.802253 | F74: 2022 | G74: Indoor | V74: 2 | AE74: 1 | AV74: =SUM(AW74:BS74) -> 2 | BI74: 1 | BL74: 1
B76: TOTAL | H76: =SUM(H67:H74) -> 0 | I76: =SUM(I67:I74) -> 3 | J76: =SUM(J67:J74) -> 0 | K76: =SUM(K67:K74) -> 0 | L76: =SUM(L67:L74) -> 0 | M76: =SUM(M67:M74) -> 0 | N76: =SUM(N67:N74) -> 1 | O76: =SUM(O67:O74) -> 0 | ... AF76: =SUM(AF67:AF74) -> 0 | AH76: =SUM(AH67:AH74) -> 0 | AI76: =SUM(AI67:AI74) -> 0 | AJ76: =SUM(AJ67:AJ74) -> 0 | AK76: =SUM(AK67:AK74) -> 0 | AL76: =SUM(AL67:AL74) -> 0 | AM76: =SUM(AM67:AM74) -> 0 | AN76: =SUM(AN67:AN74) -> 0 | AO76: =SUM(AO67:AO74) -> 0 | ... AV76: =SUM(AV67:AV74) -> 25 | BT76: =SUM(BT67:BT74) -> 0 | BU76: =SUM(BU67:BU74) -> 0 | BW76: =SUM(BW67:BW74) -> 0 | BX76: =SUM(BX67:BX74) -> 16 | BY76: =SUM(BY67:BY74) -> 4 | BZ76: =SUM(BZ67:BZ74) -> 0 | CA76: =SUM(CA67:CA74) -> 0 | CB76: =SUM(CB67:CB74) -> 0
A78: 1 | B78: WESTERN | C78: ECG | D78: TAKORADI TTI | E78: 4.917494 -1.768088 | F78: 2020 | G78: Outdoor | N78: 1 | V78: 3 | Z78: 1 | AG78: 1 | AN78: 1 | AP78: 1 | AV78: =SUM(AW78:BS78) -> 44 | AZ78: 2 | BA78: =13+11 -> 24 | BB78: 1 | BC78: 3 | BD78: 8 | BE78: 2 | BL78: 2 | BO78: 2 | BU78: 1 | BV78: 1 | BW78: 2 | BX78: 4 | BY78: 1 | CA78: 1
A79: 3 | B79: WESTERN | C79: ECG | D79: BEPOSO | E79: 5.124906, -1.611958 | F79: 2023 | G79: Outdoor | AD79: 1 | AV79: =SUM(AW79:BS79) -> 3 | BA79: 1 | BK79: 1 | BL79: 1
A80: 2 | B80: WESTERN | C80: ECG | D80: NSUAEM | E80: 5.004219 -2.027541 | F80: 2022 | G80: Indoor | H80: 1 | V80: 1 | AC80: 1 | AV80: =SUM(AW80:BS80) -> 5 | BA80: 3 | BL80: 2 | BX80: 2 | BZ80: 1
A81: 3 | B81: WESTERN | C81: ECG | D81: DUNKWA | E81: 5.967208, -1.795603 | F81: 2024 | G81: Outdoor | N81: 1 | AD81: 1 | AV81: =SUM(AW81:BS81) -> 2 | BJ81: 1 | BL81: 1 | BU81: 1 | BV81: 1 | BW81: 4 | BZ81: 1 | CA81: 1
A82: 4 | B82: WESTERN | C82: ECG | D82: TARKWA | E82: 5.311207 -1.992372 | F82: 2022 | G82: Indoor | H82: 1 | V82: 2 | Z82: 1 | AF82: 1 | AQ82: 1 | AV82: =SUM(AW82:BS82) -> 11 | BA82: 6 | BC82: 1 | BL82: 2 | BN82: 2 | BX82: 4 | BY82: 1
A83: 5 | B83: WESTERN | C83: ECG | D83: WASA AKROPONG | E83: 5.776620 -2.093827 | F83: 2022 | G83: Indoor | H83: 1 | V83: 2 | AD83: 1 | AV83: =SUM(AW83:BS83) -> 2 | BL83: 2 | BX83: 4 | BY83: 1
B85: TOTAL | H85: =SUM(H78:H83) -> 3 | I85: =SUM(I78:I83) -> 0 | J85: =SUM(J78:J83) -> 0 | K85: =SUM(K78:K83) -> 0 | L85: =SUM(L78:L83) -> 0 | M85: =SUM(M78:M83) -> 0 | N85: =SUM(N78:N83) -> 2 | O85: =SUM(O78:O83) -> 0 | ... AD85: =SUM(AD78:AD83) -> 3 | AF85: =SUM(AF78:AF83) -> 1 | AG85: =SUM(AG78:AG83) -> 1 | AH85: =SUM(AH78:AH83) -> 0 | AI85: =SUM(AI78:AI83) -> 0 | AJ85: =SUM(AJ78:AJ83) -> 0 | AK85: =SUM(AK78:AK83) -> 0 | AL85: =SUM(AL78:AL83) -> 0 | AM85: =SUM(AM78:AM83) -> 0 | ... AV85: =SUM(AV78:AV83) -> 67 | BT85: =SUM(BT78:BT83) -> 0 | BU85: =SUM(BU78:BU83) -> 2 | BW85: =SUM(BW78:BW83) -> 6 | BX85: =SUM(BX78:BX83) -> 14 | BY85: =SUM(BY78:BY83) -> 3 | BZ85: =SUM(BZ78:BZ83) -> 2 | CA85: =SUM(CA78:CA83) -> 2 | CB85: =SUM(CB78:CB83) -> 0
B88: GRAND TOTAL | H88: =SUM(H85,H76,H54,H36,H24,H11) -> 5 | I88: =SUM(I85,I76,I54,I36,I24,I11) -> 3 | J88: =SUM(J85,J76,J54,J36,J24,J11) -> 0 | K88: =SUM(K85,K76,K54,K36,K24,K11) -> 1 | L88: =SUM(L85,L76,L54,L36,L24,L11) -> 1 | M88: =SUM(M85,M76,M54,M36,M24,M11) -> 0 | N88: =SUM(N85,N76,N54,N36,N24,N11) -> 20 | O88: =SUM(O85,O76,O54,O36,O24,O11) -> 1 | ... V88: =SUM(V85,V76,V54,V36,V24,V11) -> 62 | W88: =SUM(W85,W76,W54,W36,W24,W11,W16,W65) -> 1 | X88: =SUM(X85,X76,X54,X36,X24,X11,X16,X65) -> 5 | Y88: =SUM(Y85,Y76,Y54,Y36,Y24,Y11,Y16,Y65) -> 6 | Z88: =SUM(Z85,Z76,Z54,Z36,Z24,Z11,Z16,Z65) -> 28 | AA88: =SUM(AA85,AA76,AA54,AA36,AA24,AA11,AA16,AA65) -> 0 | AB88: =SUM(AB85,AB76,AB54,AB36,AB24,AB11,AB16,AB65) -> 5 | AC88: =SUM(AC85,AC76,AC54,AC36,AC24,AC11,AC16,AC65) -> 4 | AD88: =SUM(AD85,AD76,AD54,AD36,AD24,AD11,AD16,AD65) -> 7 | ... AF88: =SUM(AF85,AF76,AF54,AF36,AF24,AF11,AF16,AF65) -> 3 | AG88: =SUM(AG85,AG76,AG54,AG36,AG24,AG11) -> 3 | AH88: =SUM(AH85,AH76,AH54,AH36,AH24,AH11) -> 1 | AI88: =SUM(AI85,AI76,AI54,AI36,AI24,AI11) -> 1 | AJ88: =SUM(AJ85,AJ76,AJ54,AJ36,AJ24,AJ11) -> 7 | AK88: =SUM(AK85,AK76,AK54,AK36,AK24,AK11) -> 4 | AL88: =SUM(AL85,AL76,AL54,AL36,AL24,AL11) -> 1 | AM88: =SUM(AM85,AM76,AM54,AM36,AM24,AM11) -> 2 | AN88: =SUM(AN85,AN76,AN54,AN36,AN24,AN11) -> 5 | ... AV88: =SUM(AV85,AV76,AV54,AV36,AV24,AV11) -> 630 | BT88: =SUM(BT85,BT76,BT54,BT36,BT24,BT11) -> 0 | BU88: =SUM(BU85,BU76,BU54,BU36,BU24,BU11) -> 4 | BW88: =SUM(BW85,BW76,BW54,BW36,BW24,BW11) -> 54 | BX88: =SUM(BX85,BX76,BX54,BX36,BX24,BX11) -> 72 | BY88: =SUM(BY85,BY76,BY54,BY36,BY24,BY11) -> 25 | BZ88: =SUM(BZ85,BZ76,BZ54,BZ36,BZ24,BZ11) -> 6 | CA88: =SUM(CA85,CA76,CA54,CA36,CA24,CA11) -> 3 | CB88: =SUM(CB85,CB76,CB54,CB36,CB24,CB11) -> 0

Sheet MASTER-BACKHAUL
B1: Region | C1: TERRITORY | D1: Name of Line | E1: Coordinates A-End | F1: Coordinates B-End | G1: Fiber Count | H1: Distance (m) | I1: SFP(10gig) Distance(km) | J1: OPGW / UGFOC /ADSS Status | K1: Age | L1: Cost/Value | M1: Comment | N1: Status | O1: Passed Commisioning Tests | P1: Total New Poles | Q1: New 9m Poles | R1: New 11m Poles | S1: Coordinates 1 | T1: Coordinates 2 | U1: Coordinates 3 | V1: Coordinates 4 | W1: Coordinates 5 | X1: Coordinates 6 | Y1: Coordinates 7 | Z1: Coordinates 8 | AA1: Coordinates 9 | AB1: Coordinates 10 | AC1: Coordinates 11 | AD1: Coordinates 12 | AE1: Coordinates 13 | AF1: Coordinates 14 | AG1: Coordinates 15 | AH1: Coordinates 16 | AI1: Coordinates 17 | AJ1: Coordinates 18 | AK1: Coordinates 19 | AL1: Coordinates 20 | AM1: Coordinates 21 | AN1: Coordinates 22 | AO1: Coordinates 23 | AP1: Coordinates 24 | AQ1: Coordinates 25 | AR1: Coordinates 26 | AS1: Coordinates 27 | AT1: Coordinates 28 | AU1: Coordinates 29 | AV1: Coordinates 30 | AW1: Coordinates 31 | AX1: Coordinates 32 | AY1: Coordinates 33 | AZ1: Coordinates 34 | BA1: Coordinates 35 | BB1: Coordinates 36 | BC1: Coordinates 37 | BD1: Coordinates 38 | BE1: Coordinates 39 | BF1: Coordinates 40 | BG1: Coordinates 41 | BH1: Coordinates 42 | BI1: Coordinates 43 | BJ1: Coordinates 44 | BK1: Coordinates 45 | BL1: Coordinates 46 | BM1: Coordinates 47 | BN1: Coordinates 48 | BO1: Coordinates 49 | BP1: Coordinates 50 | BQ1: Coordinates 51 | BR1: Coordinates 52 | BS1: Coordinates 53 | BT1: Coordinates 54 | BU1: Coordinates 55 | BV1: Coordinates 56 | BW1: Coordinates 57 | BX1: Coordinates 58 | BY1: Coordinates 59 | BZ1: Coordinates 60 | CA1: Coordinates 61 | CB1: Coordinates 62 | CC1: Coordinates 63 | CD1: Coordinates 64 | CE1: Coordinates 65 | CF1: Coordinates 66 | CG1: Coordinates 67 | CH1: Coordinates 68 | CI1: Coordinates 69 | CJ1: Coordinates 70 | CK1: Coordinates 71 | CL1: Coordinates 72 | CM1: Coordinates 73 | CN1: Coordinates 74 | CO1: Coordinates 75
A2: 1 | B2: GREATER ACCRA | C2: ECG | D2: Tema - Dawa | E2: 5.693232, 0.006872 | F2: 5.869013, 0.263467 | G2: 48 | H2: 44000 | I2: 60 | J2: ADSS | K2: 2017 | N2: Active
A3: 2 | B3: GREATER ACCRA | C3: ECG | D3: Dawa - Ada | E3: 5.869013, 0.263467 | F3: 5.893987, 0.503603 | G3: 48 | H3: 53300 | I3: 80 | J3: ADSS | K3: 2017 | N3: Active
A4: 3 | B4: VOLTA | C4: ECG | D4: Ada - Sogakope | E4: 5.893987 0.503603 | F4: 5.997086 0.595473 | G4: 48 | H4: 27000 | I4: 60 | J4: ADSS | K4: 2017 | N4: Active
A5: 4 | B5: EASTERN | C5: ECG | D5: Akuse-Tema | E5: 6.097085, 0.064292 | F5: 5.693232, 0.006872 | G5: 48 | H5: 54400 | I5: 60 | J5: ADSS | K5: 2018 | N5: Active | O5: Yes
A6: 5 | B6: GREATER ACCRA | C6: ECG | D6: RackAfrica - Cantoment (Sec) | E6: 5.571440, -0.209714 | F6: 5.584144, -0.164072 | G6: 48 | H6: 18500 | I6: 40 | J6: ADSS | K6: 2019 | N6: Active
A7: 6 | B7: GREATER ACCRA | C7: ECG | D7: Cantoment - Tema | E7: 5.584144, -0.164072 | F7: 5.693232, 0.006872 | G7: 48 | H7: 43000 | I7: 60 | J7: ADSS | K7: 2019 | N7: Active
A8: 7 | B8: GREATER ACCRA | C8: ECG | D8: Nungua - Cantoment | E8: 5.614282 -0.089064 | F8: 5.584144, -0.164072 | G8: 48 | H8: 2800 | I8: 40 | J8: ADSS | K8: 2019 | N8: Active
A9: 8 | B9: ASHANTI | C9: ECG | D9: Asanteman - Roman Hill (Sofoline Leg) | E9: 5.704165, -0.300260 | F9: 6.696086, -1.617477 | G9: 48 | H9: 17000 | I9: 60 | J9: ADSS | K9: 2020 | N9: Active | O9: Yes
A10: 9 | B10: ASHANTI | C10: ECG | D10: Asanteman - Roman Hill (Serwaa Nyarko Leg) | E10: 5.704165, -0.300260 | F10: 6.696086, -1.617477 | G10: 48 | H10: 15500 | I10: 60 | J10: ADSS | K10: 2020 | N10: Active | O10: Yes
A11: 10 | B11: EASTERN | C11: ECG | D11: Akosombo- Akuse | E11: 6.297273, 0.055737 | F11: 6.097085, 0.064292 | G11: 48 | H11: 26000 | J11: ADSS | K11: 2020 | N11: Active
A12: 11 | B12: GREATER ACCRA | C12: ECG | D12: Tema - Prampram | E12: 5.693232, 0.006872 | F12: 5.757568, 0.083992 | G12: 48 | H12: 4400 | I12: 40 | J12: ADSS | K12: 2020 | N12: Active
A13: 12 | B13: GREATER ACCRA | C13: ECG | D13: Etix - Madina | E13: 5.766104 -0.110246 | F13: 5.677437 -0.167211 | G13: 48 | H13: 21000 | I13: 40 | J13: ADSS | K13: 2020 | N13: Active
A14: 13 | B14: GREATER ACCRA | C14: ECG | D14: Madina - GIJ | E14: 5.677437 -0.167211 | F14: 5.622542 -0.186943 | G14: 48 | H14: 26000 | I14: 60 | J14: ADSS | K14: 2020 | N14: Active
A15: 14 | B15: GREATER ACCRA | C15: ECG | D15: Madina-Cantoment | E15: 5.677437 -0.167211 | F15: 5.584144, -0.164072 | G15: 48 | H15: 26000 | I15: 60 | J15: ADSS | K15: 2020 | N15: Active
A16: 15 | B16: GREATER ACCRA | C16: ECG | D16: Madina - RackAfrica | E16: 5.677437 -0.167211 | F16: 5.571440 -0.209714 | G16: 48 | H16: 0 | I16: 60 | J16: ADSS | K16: 2020 | N16: Active
A17: 16 | B17: GREATER ACCRA | C17: ECG | D17: GIJ - Cantoment | E17: 5.622542 -0.186943 | F17: 5.584144, -0.164072 | G17: 48 | H17: 8100 | I17: 60 | J17: ADSS | K17: 2020 | N17: Active
A18: 17 | B18: ASHANTI | C18: ECG | D18: Kubease(Konongo)-Roman Hill | E18: 6.675194, -1.380315 | F18: 6.708774, -1.627550 | G18: 48 | H18: 50000 | I18: 80 | J18: ADSS | K18: 2021 | N18: Active
A19: 18 | B19: ASHANTI | C19: ECG | D19: Asanteman - BroadSpectrum | E19: 5.704165, -0.300260 | F19: 4.960283, -1.736001 | G19: 48 | H19: 3500 | I19: 20 | J19: ADSS | K19: 2021 | N19: Active | O19: Yes
A20: 19 | B20: CENTRAL | C20: ECG | D20: Winneba - McCarthy | E20: 5.379158, -0.652166 | F20: 5.563084, -0.299930 | G20: 48 | H20: 61000 | I20: 80 | J20: ADSS | K20: 2021 | N20: Active | O20: Yes
A21: 20 | B21: EASTERN | C21: ECG | D21: Amasaman- Suhum | E21: 5.704165,-0.300260 | F21: 6.027995, -0.449935 | G21: 48 | H21: 6000 | I21: 60 | J21: ADSS | K21: 2021 | N21: Active
A22: 21 | B22: EASTERN | C22: ECG | D22: Suhum- Nkawkaw | E22: 6.027995 -0.449935 | F22: 6.538083 -0.758909 | G22: 48 | H22: 96000 | I22: 80 | J22: ADSS | K22: 2021 | N22: Active
A23: 22 | B23: EASTERN | C23: ECG | D23: Nkawkaw - Kubease(Konongo) | E23: 6.538083, -0.758909 | F23: 6.675194, -1.380315 | G23: 48 | H23: 87000 | I23: 100 | J23: ADSS | K23: 2021 | N23: Active
A24: 23 | B24: EASTERN | C24: ECG | D24: Akuse - Etix | E24: 6.097085, 0.064292 | F24: 5.766104, -0.110246 | G24: 48 | H24: 75000 | I24: 80 | J24: ADSS | K24: 2021 | N24: Active
A25: 24 | B25: EASTERN | C25: ECG | D25: Madina - Aburi | E25: 5.677437, -0.167211 | F25: 5.873167, -0.157818 | G25: 48 | H25: 35000 | I25: 60 | J25: ADSS | K25: 2021 | N25: Active | O25: Yes
A26: 25 | B26: GREATER ACCRA | C26: ECG | D26: McCarthy - RackAfrica | E26: 5.563084, -0.299930 | F26: 5.571440, -0.209714 | G26: 48 | H26: 20000 | I26: 60 | J26: ADSS | K26: 2021 | N26: Active
A27: 26 | B27: GREATER ACCRA | C27: ECG | D27: RackAfrica - Cantoment (Prim) | E27: 5.571440, -0.209714 | F27: 5.584144, -0.164072 | G27: 48 | H27: 4500 | I27: 40 | J27: ADSS | K27: 2021 | N27: Active
A28: 27 | B28: GREATER ACCRA | C28: ECG | D28: Etix - Tema | E28: 5.766104, -0.110246 | F28: 5.693232, 0.006872 | G28: 48 | H28: 28000 | I28: 60 | J28: ADSS | K28: 2021 | N28: Active
A29: 28 | B29: GREATER ACCRA | C29: ECG | D29: Madina - Amasaman | E29: 5.677437 -0.167211 | F29: 5.704159 -0.300296 | G29: 48 | H29: 12700 | I29: 60 | J29: ADSS | K29: 2021 | N29: Active
A30: 29 | B30: GREATER ACCRA | C30: ECG | D30: Cantoment - MCcarthy | E30: 5.584144, -0.164072 | F30: 5.563084 -0.299930 | G30: 48 | H30: 26500 | I30: 80 | J30: ADSS | K30: 2021 | N30: Active
A31: 30 | B31: GREATER ACCRA | C31: ECG | D31: McCarthy - Madina | E31: 5.563084, -0.299930 | F31: 5.677437 -0.167211 | G31: 48 | H31: 22000 | I31: 60 | J31: ADSS | K31: 2021 | N31: Active
A32: 31 | B32: VOLTA | C32: ECG | D32: Ho-Juapong | E32: 6.571861 0.406850 | F32: 6.250124 0.137610 | G32: 48 | H32: 72529.8 | J32: ADSS | K32: 2021 | N32: Active
A33: 32 | B33: ASHANTI | C33: ECG | D33: Roman Hill - Obuasi | E33: 6.696086, -1.617477 | F33: 6.204062, -1.677247 | G33: 48 | H33: 76000 | I33: 80 | J33: ADSS | K33: 2022 | N33: Active
A34: 33 | B34: CENTRAL | C34: ECG | D34: CapeCoast-Winneba | E34: 5.117613, -1.244324 | F34: 5.379158, -0.652166 | G34: 48 | H34: 89000 | I34: 80 | J34: ADSS | K34: 2022 | N34: Active | O34: Yes
A35: 34 | B35: GREATER ACCRA | C35: ECG | D35: McCarthy - Amasaman | E35: 5.563084, -0.299930 | F35: 5.704165, -0.300260 | G35: 48 | H35: 59000 | I35: 60 | J35: ADSS | K35: 2022 | N35: Active | O35: Yes
A36: 35 | B36: GREATER ACCRA | C36: ECG | D36: Cantonment-GIL | E36: 5.584144, -0.164072 | F36: 5.622542 -0.186943 | G36: 48 | H36: 17000 | I36: 60 | J36: ADSS | K36: 2022 | N36: Active
A37: 36 | B37: GREATER ACCRA | C37: ECG | D37: Nungua - Tema | E37: 5.614282 -0.089064 | F37: 5.693232 0.006872 | G37: 48 | H37: 3000 | I37: 60 | J37: ADSS | K37: 2022 | N37: Active
A38: 37 | B38: VOLTA | C38: ECG | D38: Sogakope-Akatsi | E38: 5.997086 0.595473 | F38: 6.127324 0.802253 | G38: 48 | H38: 30000 | I38: 60 | J38: ADSS | K38: 2022 | N38: Active
A39: 38 | B39: VOLTA | C39: ECG | D39: Akatsi-Aflao | E39: 6.127324 0.802253 | F39: 6.117796 1.190115 | G39: 48 | H39: 55000 | I39: 80 | J39: ADSS | K39: 2022 | N39: Active
A40: 39 | B40: WESTERN | C40: ECG | D40: Obuasi - Wasa Akropong | E40: 6.204062 -1.677247 | F40: 5.311207 -1.992372 | G40: 48 | H40: 82000 | I40: 120 | J40: ADSS | K40: 2022 | N40: Active
A41: 40 | B41: WESTERN | C41: ECG | D41: Wasa Akropong - Tarkwa | E41: 5.311207 -1.992372 | F41: 5.311207 -1.992372 | G41: 48 | H41: 69000 | I41: 100 | J41: ADSS | K41: 2022 | N41: Active
A42: 41 | B42: WESTERN | C42: ECG | D42: Tarkwa - Nsuaem | E42: 5.311207 -1.992372 | F42: 5.004219 -2.027541 | G42: 48 | H42: 70000 | I42: 100 | J42: ADSS | K42: 2022 | N42: Active
A43: 42 | B43: WESTERN | C43: ECG | D43: Nsuaem - Takoradi | E43: 5.004219 -2.027541 | F43: 4.917494 -1.768088 | G43: 48 | H43: 50000 | I43: 120 | J43: ADSS | K43: 2022 | N43: Active
A44: 43 | B44: WESTERN | C44: ECG | D44: Takoradi - Cape Coast | E44: 4.917494 -1.768088 | F44: 5.117613 -1.244324 | G44: 48 | H44: 85000 | I44: 100 | J44: ADSS | K44: 2022 | N44: Active
A45: 44 | B45: ASHANTI | C45: ECG | D45: Asanteman - Bechem (Mankranso) | E45: 5.704165, -0.300260 | F45: 6.824089, -1.860989 | G45: 48 | H45: 35000 | J45: ADSS | K45: 2023 | N45: Active
A46: 45 | B46: AHAFO | C46: NEDCO | D46: Asanteman (Mankranso) - Bechem | E46: 6.824089, -1.860989 | F46: 7.081364, -2.023164 | G46: 48 | H46: 40000 | J46: ADSS | K46: 2023 | N46: Active
A47: 46 | B47: ASHANTI | C47: ECG | D47: Abofour - Kumasi ECG | E47: 7.162217, -1.741411 | F47: 6.745728, -1.640628 | G47: 48 | H47: 67000 | J47: ADSS | K47: 2023 | N47: Active
A48: 47 | B48: BONO EAST | C48: NEDCO | D48: Abofour - Techiman | E48: 7.162217, -1.741411 | F48: 7.589136, -1.919447 | G48: 48 | H48: 77000 | J48: ADSS | K48: 2023 | N48: Active
A49: 48 | B49: ASHANTI | C49: ECG | D49: Kumasi - Nkawie | E49: 6.700425, -1.715144 | F49: 6.660014, -1.815706 | G49: 48 | H49: 15000 | J49: ADSS | K49: 2023 | N49: Active
A50: 49 | B50: ASHANTI | C50: ECG | D50: Nkawie - Bibiani | E50: 6.660014, -1.815706 | F50: 6.460197, -2.318631 | G50: 48 | H50: 73000 | J50: ADSS | K50: 2023 | N50: Active
A51: 50 | B51: CENTRAL | C51: ECG | D51: CapeCoast-Assin Fosu | E51: 5.117613, -1.244324 | F51: 5.690664, -1.276250 | G51: 48 | H51: 87000 | I51: 80 | J51: ADSS | K51: 2023 | N51: Active
A52: 51 | B52: CENTRAL | C52: ECG | D52: Assin Fosu-Akim Oda | E52: 5.690664, -1.276250 | F52: 5.926261, -0.982933 | G52: 48 | H52: 71000 | I52: 80 | J52: ADSS | K52: 2023 | N52: Active
A53: 52 | B53: CENTRAL | C53: ECG | D53: Akim Oda-Swedru | E53: 5.926261, -0.982933 | F53: 5.526178, -0.701050 | G53: 48 | H53: 72000 | I53: 80 | J53: ADSS | K53: 2023 | N53: Active
A54: 53 | B54: CENTRAL | C54: ECG | D54: Swedru-Winneba | E54: 5.526178, -0.701050 | F54: 5.379158, -0.652166 | G54: 48 | H54: 25000 | I54: 40 | J54: ADSS | K54: 2023 | N54: Active
A55: 54 | B55: CENTRAL | C55: ECG | D55: Swedru-Asamankese | E55: 5.526178, -0.701050 | F55: 5.863620, -0.664097 | G55: 48 | H55: 74000 | I55: 80 | J55: ADSS | K55: 2023 | N55: Active
A56: 55 | B56: CENTRAL | C56: ECG | D56: Asamankese-Suhum | E56: 5.863620, -0.664097 | F56: 6.049108, -0.459814 | G56: 48 | H56: 41000 | I56: 80 | J56: ADSS | K56: 2023 | N56: Active
A57: 56 | B57: GREATER ACCRA | C57: ECG | D57: GIL-RackAfrica | E57: 5.622542 -0.186943 | F57: 5.571440 -0.209714 | G57: 48 | H57: 4000 | I57: 60 | J57: ADSS | K57: 2023 | N57: Active
A58: 57 | B58: VOLTA | C58: ECG | D58: Aflao - Ziope | E58: 6.117796 1.190115 | F58: 6.425261, 0.732761 | G58: 48 | H58: 71000 | I58: 100 | J58: ADSS | K58: 2023 | N58: Active
A59: 58 | B59: VOLTA | C59: ECG | D59: Ziope - Ho | E59: 6.425261, 0.732761 | F59: 6.571861 0.406850 | G59: 48 | H59: 44406 | I59: 80 | J59: ADSS | K59: 2023 | N59: Active
A60: 59 | B60: WESTERN NORTH | C60: ECG | D60: Bibiani - Wiawso | E60: 6.460197, -2.318631 | F60: 6.200100, -2.478589 | G60: 48 | H60: 71000 | J60: ADSS | K60: 2023 | N60: Active
A61: 60 | B61: WESTERN NORTH | C61: ECG | D61: Wiawso - Juaboso | E61: 6.200100, -2.478589 | F61: 6.342219, -2.821111 | G61: 48 | H61: 76000 | J61: ADSS | K61: 2023 | N61: Active
A62: 61 | B62: WESTERN | C62: ECG | D62: Elubo - Awiebo | E62: 5.289556, -2.772500 | F62: 5.035003, -2.440497 | G62: 48 | H62: 55000 | J62: ADSS | K62: 2023 | N62: Active
A63: 62 | B63: WESTERN | C63: ECG | D63: Awiebo - AximJn | E63: 5.035003, -2.440497 | F63: 4.932997, -1.977419 | G63: 48 | H63: 72000 | J63: ADSS | K63: 2023 | N63: Active
A64: 63 | B64: BRONG AHAFO | C64: NEDCO | D64: Bechem- Sunyani | E64: 7.081364, -2.023164 | F64: 7.316661, -2.302783 | G64: 48 | H64: 69000 | J64: ADSS | K64: 2023 | N64: Active
A65: 64 | B65: BRONG AHAFO | C65: NEDCO | D65: Sunyani - Wenchi | E65: 7.316661, -2.302783 | F65: 7.745303, -2.100225 | G65: 48 | H65: 80000 | J65: ADSS | K65: 2023 | N65: Active
A66: 65 | B66: BRONG AHAFO | C66: NEDCO | D66: Wenchi - Bamboi | E66: 7.745303, -2.100225 | F66: 8.164119, -2.033883 | G66: 48 | H66: 58000 | J66: ADSS | K66: 2023 | N66: Active
A67: 66 | B67: NORTHERN | C67: NEDCO | D67: Tamale - Diari | E67: 9.417364, -0.860597 | F67: 9.865044, -0.870639 | G67: 48 | H67: 61000 | I67: 80 | J67: ADSS | K67: 2023 | N67: Active
A68: 67 | B68: NORTH EAST | C68: NEDCO | D68: Diari - Walewale | E68: 9.865044, -0.870639 | F68: 10.337358, -0.799333 | G68: 48 | H68: 63000 | I68: 80 | J68: ADSS | K68: 2023 | N68: Active
A69: 68 | B69: NORTH EAST | C69: NEDCO | D69: Walewale - Bolgatanga | E69: 10.337358, -0.799333 | F69: 10.791053, -0.857317 | G69: 48 | H69: 63000 | I69: 80 | J69: ADSS | K69: 2023 | N69: Active
A70: 69 | B70: NORTHERN | C70: NEDCO | D70: Bolgatanga - Nakong | E70: 10.791053, -0.857317 | F70: 10.820389, -1.416281 | G70: 48 | H70: 79000 | J70: ADSS | K70: 2023 | N70: Active
A71: 70 | B71: EASTERN | C71: ECG | D71: Akosombo-Koforidua | G71: 48 | H71: 86000 | I71: 80 | J71: ADSS | K71: 2023 | N71: Active
A72: 71 | B72: EASTERN | C72: ECG | D72: Koforidua-Aburi | G72: 48 | H72: 56000 | I72: 80 | J72: ADSS | K72: 2023 | N72: Active
A73: 72 | B73: SAVANNAH | C73: NEDCO | D73: Bamboi-Tinga | G73: 48 | H73: 58000 | J73: ADSS | K73: 2023 | N73: Active
A74: 73 | B74: SAVANNAH | C74: NEDCO | D74: Tinga-Bole | G74: 48 | H74: 63000 | J74: ADSS | K74: 2023 | N74: Active
A75: 74 | B75: SAVANNAH | C75: NEDCO | D75: Bole-Sawla | G75: 48 | H75: 34000 | J75: ADSS | K75: 2023 | N75: Active
A76: 75 | B76: SAVANNAH | C76: NEDCO | D76: Sawla-Kumasa | G76: 48 | H76: 62000 | J76: ADSS | K76: 2023 | N76: Active
A77: 76 | B77: UPPER WEST | C77: NEDCO | D77: Kumasa-Wa | G77: 48 | H77: 51000 | J77: ADSS | K77: 2023 | N77: Active
A78: 77 | B78: UPPER WEST | C78: NEDCO | D78: Wa-Han | G78: 48 | H78: 81000 | J78: ADSS | K78: 2023 | N78: Active
A79: 78 | B79: UPPER WEST | C79: NEDCO | D79: Han-Tumu | G79: 48 | H79: 68000 | J79: ADSS | K79: 2023 | N79: Active
A80: 79 | B80: UPPER WEST | C80: NEDCO | D80: Tumu-Nakong | G80: 48 | H80: 79000 | J80: ADSS | K80: 2023 | N80: Active
A81: 80 | B81: UPPER EAST | C81: NEDCO | D81: Nakong-Bolga | G81: 48 | H81: 79000 | J81: ADSS | K81: 2023 | N81: Active
A82: 81 | B82: BRONG AHAFO | C82: NEDCO | D82: Sunyani-Berekum | G82: 48 | H82: 43000 | J82: ADSS | K82: 2023 | N82: Active
A83: 82 | B83: BONO EAST | C83: NEDCO | D83: Abofour - Kumasi NEDCO | E83: 7.162217, -1.741412 | F83: 6.745728, -1.640629 | G83: 48 | H83: 5000 | J83: ADSS | K83: 2024 | N83: Active
A84: 83 | B84: WESTERN NORTH | C84: ECG | D84: Elubo - Enchi | G84: 48 | H84: 87000 | J84: ADSS | K84: 2024 | N84: Active
A85: 84 | B85: UPPER EAST | C85: NEDCO | D85: Bolgatanga - Bawku | G85: 48 | H85: 93000 | J85: ADSS | K85: 2024 | N85: Active
A86: 85 | B86: ASHANTI | C86: ECG | D86: Tanoso - Kwanfinfin | G86: 48 | H86: 38400 | K86: 2025 | N86: Active
A87: 86 | B87: ASHANTI | C87: ECG | D87: Kwanfinfin - Bibiano | G87: 48 | H87: 55400 | K87: 2025 | N87: Active
A88: 87 | B88: BRONG AHAFO | C88: NEDCO | D88: Berekum - Dormaa Ahenkro | G88: 48 | H88: 55470 | K88: 2025 | N88: Active
A89: 88 | B89: BRONG AHAFO | C89: NEDCO | D89: Dorma Ahenkro - Goaso | G89: 48 | H89: 90131 | K89: 2025 | N89: Active
A90: 89 | B90: VOLTA | C90: ECG | D90: Ho - Peki | G90: 48 | H90: 75600 | K90: 2025 | N90: Active | P90: 59 | Q90: 59 | R90: 0 | S90: 7.127453841 0.460639464 | T90: 7.11892027 0.457614612 | U90: 7.117936565 0.457327167 | V90: 7.116745216 0.397182516 | W90: 7.12328244 0.383894176 | X90: 7.120654849 0.377286797 | Y90: 7.119892429 0.369125367 | Z90: 7.118337966 0.349855828 | AA90: 7.10565377 0.352257886 | AB90: 7.098720143 0.352496167 | AC90: 7.078010938 0.350948814 | AD90: 7.028946165 0.327710888 | AE90: 7.0213348 0.321522636 | AF90: 7.009451182 0.315408656 | AG90: 6.99768156 0.300073337 | AH90: 6.929069475 0.284538597 | AI90: 6.928427223 0.284439682 | AJ90: 6.829180827 0.327001558 | AK90: 6.816312001 0.332140085 | AL90: 6.787985943 0.344667657 | AM90: 6.707923704 0.333549962 | AN90: 6.692233332 0.334132866 | AO90: 6.646309267 0.299103734 | AP90: 6.639624446 0.298710795 | AQ90: 6.630709987 0.310475287 | AR90: 6.628624338 0.31180485 | AS90: 6.536888287 0.232185238 | AT90: 6.529608394 0.226444305 | AU90: 6.49446821 0.202173238 | AV90: 6.4922789 0.201166522 | AW90: 6.490782482 0.200499385 | AX90: 6.484025046 0.197252163 | AY90: 6.415000647 0.172556982 | AZ90: 6.434579169 0.170683932 | BA90: 6.467696726 0.187373723 | BB90: 6.468908428 0.188127796 | BC90: 6.469490654 0.188481645 | BD90: 6.470792589 0.189317306 | BE90: 6.472280769 0.190275183 | BF90: 6.473261371 0.190813624 | BG90: 6.473671511 0.19105651 | BH90: 6.476968939 0.193172288 | BI90: 6.478386233 0.193943558 | BJ90: 6.479669761 0.194819003 | BK90: 6.481064792 0.195725596 | BL90: 6.482380948 0.196421226 | BM90: 6.483236925 0.196850992 | BN90: 6.485167087 0.197865138 | BO90: 6.485869199 0.198200633 | BP90: 6.487830764 0.199078058 | BQ90: 6.48892094 0.199638229 | BR90: 6.490325825 0.200293193 | BS90: 7.118424, 0.361965 | BT90: 7.119843, 0.369127 | BU90: 7.120701, 0.377258 | BV90: 7.123268, 0.383892 | BW90: 7.118310, 0.349901 | BX90: 6.528107, 0.225380 | BY90: 6.528488, 0.225678
A91: 90 | B91: VOLTA | C91: ECG | D91: Peki - Kpando | G91: 48 | H91: 77350 | K91: 2025 | N91: Active
A92: 91 | B92: VOLTA | C92: ECG | D92: Kpando - Hohoe | G92: 48 | H92: 43750 | K92: 2025 | N92: Active
A93: 92 | B93: VOLTA | C93: ECG | D93: Akosombo - Ho | G93: 48 | H93: 1500 | K93: 2025 | N93: Active
A94: 93 | B94: VOLTA | C94: ECG | D94: Hohoe - Kedjebi | G94: 48 | H94: 55000 | K94: 2025 | N94: Inactive
A95: 94 | B95: VOLTA | C95: ECG | D95: Kedjebi - Nkwanta | G95: 48 | H95: 95000 | K95: 2025 | N95: Inactive
A96: 95 | B96: VOLTA | C96: ECG | D96: Nkwanta - Kpassa | G96: 48 | H96: 43000 | K96: 2025 | N96: Inactive
A97: 96 | B97: NORTHERN | C97: NEDCO | D97: Yendi - Gushegu | G97: 48 | H97: 70000 | K97: 2025 | N97: Active
A98: 97 | B98: GREATER ACCRA | C98: ECG | D98: Master Power - DTRT | G98: 48 | H98: 1000 | K98: 2025 | N98: Active | S98: 5.661152,-0.015456 | T98: 5.65845,-0.012037 | U98: 5.660142,-0.014942 | V98: 5.659233,-0.009982 | W98: 5.659578,-0.009647 | X98: 5.66124,-0.015975 | Y98: 5.645064, -0.096683
A99: 98 | B99: NORTHERN | C99: NEDCO | D99: Kpassa - Bimbilla | G99: 48 | H99: 65000 | K99: 2026
A100: 99 | B100: NORTHERN | C100: NEDCO | D100: Bimbilla - Yendi | G100: 48 | H100: 75000 | K100: 2026
...

Sheet MASTER-ACCESSORIES - BACKHAUL
A1: S/N | B1: Region | C1: Territory | D1: Name of Line | E1: Distance (m) | F1: Pole Brackets (pcs) | G1: Tension Clamps (pcs) | H1: Suspensions (pcs) | I1: Buckles (pcs) | J1: Steel Band (m) | K1: Closures (pcs) | L1: Status
A2: 1 | B2: ASHANTI | C2: ECG | D2: Kubease(Konongo)-Roman Hill | E2: 50000 | F2: =(((E2/70)+1)*0.4) -> 286.11429 | G2: =2*F2 -> 572.22857 | H2: =(((E2/70)+1)*0.6) -> 429.17143 | I2: =H2+F2 -> 715.28571 | J2: =I2 -> 715.28571 | K2: =(E2/4000)+1 -> 13.5 | L2: Active
A3: 2 | B3: ASHANTI | C3: ECG | D3: Asanteman - Roman Hill (Sofoline Leg) | E3: 17000 | F3: =(((E3/70)+1)*0.4) -> 97.542857 | G3: =2*F3 -> 195.08571 | H3: =(((E3/70)+1)*0.6) -> 146.31429 | I3: =H3+F3 -> 243.85714 | J3: =I3 -> 243.85714 | K3: =(E3/4000)+1 -> 5.25 | L3: Active
A4: 3 | B4: ASHANTI | C4: ECG | D4: Asanteman - Roman Hill (Serwaa Nyarko Leg) | E4: 15500 | F4: =(((E4/70)+1)*0.4) -> 88.971429 | G4: =2*F4 -> 177.94286 | H4: =(((E4/70)+1)*0.6) -> 133.45714 | I4: =H4+F4 -> 222.42857 | J4: =I4 -> 222.42857 | K4: =(E4/4000)+1 -> 4.875 | L4: Active
A5: 4 | B5: ASHANTI | C5: ECG | D5: Asanteman - BroadSpectrum | E5: 3500 | F5: =(((E5/70)+1)*0.4) -> 20.4 | G5: =2*F5 -> 40.8 | H5: =(((E5/70)+1)*0.6) -> 30.6 | I5: =H5+F5 -> 51 | J5: =I5 -> 51 | K5: =(E5/4000)+1 -> 1.875 | L5: Active
A6: 5 | B6: ASHANTI | C6: ECG | D6: Roman Hill - Obuasi | E6: 76000 | F6: =(((E6/70)+1)*0.4) -> 434.68571 | G6: =2*F6 -> 869.37143 | H6: =(((E6/70)+1)*0.6) -> 652.02857 | I6: =H6+F6 -> 1086.7143 | J6: =I6 -> 1086.7143 | K6: =(E6/4000)+1 -> 20 | L6: Active
A7: 6 | B7: ASHANTI | C7: ECG | D7: Asanteman - Bechem (Mankranso) | E7: 35000 | F7: =(((E7/70)+1)*0.4) -> 200.4 | G7: =2*F7 -> 400.8 | H7: =(((E7/70)+1)*0.6) -> 300.6 | I7: =H7+F7 -> 501 | J7: =I7 -> 501 | K7: =(E7/4000)+1 -> 9.75 | L7: Active
A8: 7 | B8: AHAFO | C8: NEDCO | D8: Asanteman (Mankranso) - Bechem | E8: 40000 | F8: =(((E8/70)+1)*0.4) -> 228.97143 | G8: =2*F8 -> 457.94286 | H8: =(((E8/70)+1)*0.6) -> 343.45714 | I8: =H8+F8 -> 572.42857 | J8: =I8 -> 572.42857 | K8: =(E8/4000)+1 -> 11 | L8: Active
A9: 8 | B9: ASHANTI | C9: ECG | D9: Abofour - Kumasi ECG | E9: 67000 | F9: =(((E9/70)+1)*0.4) -> 383.25714 | G9: =2*F9 -> 766.51429 | H9: =(((E9/70)+1)*0.6) -> 574.88571 | I9: =H9+F9 -> 958.14286 | J9: =I9 -> 958.14286 | K9: =(E9/4000)+1 -> 17.75 | L9: Active
A10: 9 | B10: BONO EAST | C10: NEDCO | D10: Abofour - Kumasi NEDCO | E10: 5000 | F10: =(((E10/70)+1)*0.4) -> 28.971429 | G10: =2*F10 -> 57.942857 | H10: =(((E10/70)+1)*0.6) -> 43.457143 | I10: =H10+F10 -> 72.428571 | J10: =I10 -> 72.428571 | K10: =(E10/4000)+1 -> 2.25 | L10: Active
A11: 10 | B11: BONO EAST | C11: NEDCO | D11: Abofour - Techiman | E11: 77000 | F11: =(((E11/70)+1)*0.4) -> 440.4 | G11: =2*F11 -> 880.8 | H11: =(((E11/70)+1)*0.6) -> 660.6 | I11: =H11+F11 -> 1101 | J11: =I11 -> 1101 | K11: =(E11/4000)+1 -> 20.25 | L11: Active
A12: 11 | B12: ASHANTI | C12: ECG | D12: Kumasi - Nkawie | E12: 15000 | F12: =(((E12/70)+1)*0.4) -> 86.114286 | G12: =2*F12 -> 172.22857 | H12: =(((E12/70)+1)*0.6) -> 129.17143 | I12: =H12+F12 -> 215.28571 | J12: =I12 -> 215.28571 | K12: =(E12/4000)+1 -> 4.75 | L12: Active
A13: 12 | B13: ASHANTI | C13: ECG | D13: Nkawie - Bibiani | E13: 73000 | F13: =(((E13/70)+1)*0.4) -> 417.54286 | G13: =2*F13 -> 835.08571 | H13: =(((E13/70)+1)*0.6) -> 626.31429 | I13: =H13+F13 -> 1043.8571 | J13: =I13 -> 1043.8571 | K13: =(E13/4000)+1 -> 19.25 | L13: Active
... A102: 101 | B102: NORTHERN | C102: NEDCO | D102: Bimbilla - Yendi | E102: 75000 | F102: =(((E102/70)+1)*0.4) -> 428.97143 | G102: =2*F102 -> 857.94286 | H102: =(((E102/70)+1)*0.6) -> 643.45714 | I102: =H102+F102 -> 1072.4286 | J102: =I102 -> 1072.4286 | K102: =(E102/4000)+1 -> 19.75 | L102: Active
D112: TOTAL | E112: =SUM(E2:E102) -> 5127736.8 | F112: =SUM(F2:F102) -> 29341.753 | G112: =SUM(G2:G102) -> 58683.506 | H112: =SUM(H2:H102) -> 44012.63 | I112: =SUM(I2:I102) -> 73354.383 | J112: =SUM(J2:J102) -> 73354.383 | K112: =SUM(K2:K102) -> 1382.9342
D138: LEGEND:
D140: ODF:- Optical Distribution Frames
D142: ADSS FOC:- All Dielectric Self Supporting Fibre Optic Cable

Sheet MASTER-METRO
B1: REGION | C1: TERRITOY | D1: NAME OF LINE | E1: COORDINATES A-END | F1: COORDINATES B-END | G1: FIBER COUNT | H1: LOCATION | I1: Drop Cable Distance (M) | J1: ADSS DISTANCE (M) | K1: 1G SFP DISTANCE(KM) | L1: 10G SFP DISTANCE(KM) | M1: CPE | N1: OPGW / UGFOC /ADSS STATUS | O1: AGE | P1: DATE | Q1: MONTH | R1: COST/VALUE | S1: STATUS | T1: Passed Commisioning Tests | U1: Total New Poles | V1: 9m Poles | W1: 11m Poles | X1: Coordinate 1 | Y1: Coordinate 2 | Z1: Coordinate 3 | AA1: Coordinate 4 | AB1: Coordinate 5 | AC1: Coordinate 6 | AD1: Coordinate 7 | AE1: Coordinate 8 | AF1: Coordinate 9 | AG1: Coordinate 10 | AH1: Coordinate 11 | AI1: Coordinate 12 | AJ1: Coordinate 13 | AK1: Coordinate 14 | AL1: Coordinate 15 | AM1: Coordinate 16 | AN1: Coordinate 17 | AO1: Coordinate 18 | AP1: Coordinate 19 | AQ1: Coordinate 20 | AR1: Coordinate 21 | AS1: Coordinate 22 | AT1: Coordinate 23 | AU1: Coordinate 24 | AV1: Coordinate 25 | AW1: Coordinate 26 | AX1: Coordinate 27 | AY1: Coordinate 28 | AZ1: Coordinate 29 | BA1: Coordinate 30 | BB1: Coordinate 31 | BC1: Coordinate 32 | BD1: Coordinate 33 | BE1: Coordinate 34 | BF1: Coordinate 35 | BG1: Coordinate 36 | BH1: Coordinate 37 | BI1: Coordinate 38 | BJ1: Coordinate 39 | BK1: Coordinate 40 | BL1: Coordinate 41 | BM1: Coordinate 42 | BN1: Coordinate 43 | BO1: Coordinate 44 | BP1: Coordinate 45 | BQ1: Coordinate 46 | BR1: Coordinate 47 | BS1: Coordinate 48 | BT1: Coordinate 49 | BU1: Coordinate 50 | BV1: Coordinate 51 | BW1: Coordinate 52 | BX1: Coordinate 53 | BY1: Coordinate 54 | BZ1: Coordinate 55 | CA1: Coordinate 56 | CB1: Coordinate 57 | CC1: Coordinate 58 | CD1: Coordinate 59 | CE1: Coordinate 60 | CF1: Coordinate 61 | CG1: Coordinate 62 | CH1: Coordinate 63 | CI1: Coordinate 64 | CJ1: Coordinate 65 | CK1: Coordinate 66 | CL1: Coordinate 67 | CM1: Coordinate 68
A2: {=_xlfn.SEQUENCE(COUNTA(D$2:D$1048576))} -> 1 | B2: ASHANTI | C2: ECG | D2: MANHYIA PALACE | E2: 6.703436,-1.614345 | F2: 6.708775, -1.627550 | G2: {=_xlfn.IFS(J2<301,2,J2>300,48)} -> 48 | H2: KUMASI | I2: 0 | J2: 2100 | K2: =IF(M2="ONT",20,IF(M2="N/A","N/A",IF(M2="MIKROTIK",IF(J2<3000,10,IF(3000<J2>10000,20,IF(10000<J2>20000,40,IF(20000<J2>40000,60,IF(J2>40000,80,IF(J2<300,3,))))))))) -> FALSE | M2: Furukawa | N2: ADSS | O2: 2021 | S2: ACTIVE | T2: Yes
A3: 2 | B3: ASHANTI | C3: ECG | D3: PRINCE OF PEACE GIRLS | E3: 6.69596,-1.64277 | F3: 6.708775, -1.627550 | G3: {=_xlfn.IFS(J3<301,2,J3>300,48)} -> 48 | H3: KUMASI | I3: 0 | J3: 2200 | K3: =IF(M3="ONT",20,IF(M3="N/A","N/A",IF(M3="MIKROTIK",IF(J3<3000,10,IF(3000<J3>10000,20,IF(10000<J3>20000,40,IF(20000<J3>40000,60,IF(J3>40000,80,IF(J3<300,3,))))))))) -> N/A | M3: N/A | N3: ADSS | O3: 2020 | S3: INACTIVE | T3: Yes
A4: 3 | B4: ASHANTI | C4: ECG | D4: ST. LOUIS SENIOR HIGH, KUMASI | E4: 6.695041,-1.545178 | F4: 6.708775, -1.627550 | G4: {=_xlfn.IFS(J4<301,2,J4>300,48)} -> 48 | H4: KUMASI | I4: 0 | J4: 1500 | K4: =IF(M4="ONT",20,IF(M4="N/A","N/A",IF(M4="MIKROTIK",IF(J4<3000,10,IF(3000<J4>10000,20,IF(10000<J4>20000,40,IF(20000<J4>40000,60,IF(J4>40000,80,IF(J4<300,3,))))))))) -> FALSE | M4: Furukawa | N4: ADSS | O4: 2020 | S4: ACTIVE | T4: Yes
A5: 4 | B5: ASHANTI | C5: ECG | D5: ADVENTIST SENIOR HIGH, KUMASI | E5: 6.70934,-1.632254 | F5: 6.708775, -1.627550 | G5: {=_xlfn.IFS(J5<301,2,J5>300,48)} -> 2 | H5: KUMASI | I5: 150 | J5: 0 | K5: =IF(M5="ONT",20,IF(M5="N/A","N/A",IF(M5="MIKROTIK",IF(J5<3000,10,IF(3000<J5>10000,20,IF(10000<J5>20000,40,IF(20000<J5>40000,60,IF(J5>40000,80,IF(J5<300,3,))))))))) -> FALSE | M5: Furukawa | N5: ADSS | O5: 2020 | S5: ACTIVE | T5: Yes
A6: 5 | B6: ASHANTI | C6: ECG | D6: AGRIC NZEMA SENIOR HIGH, KUMASI | E6: 6.67339,-1.67716 | F6: 6.696086°, -1.617477° | G6: {=_xlfn.IFS(J6<301,2,J6>300,48)} -> 48 | H6: KUMASI | I6: 0 | J6: 3575 | K6: =IF(M6="ONT",20,IF(M6="N/A","N/A",IF(M6="MIKROTIK",IF(J6<3000,10,IF(3000<J6>10000,20,IF(10000<J6>20000,40,IF(20000<J6>40000,60,IF(J6>40000,80,IF(J6<300,3,))))))))) -> FALSE | M6: Furukawa | N6: ADSS | O6: 2020 | S6: ACTIVE | T6: Yes
A7: 6 | B7: ASHANTI | C7: ECG | D7: AL-AZARIYA ISLAMIC SNR. HIGH, KUMASI | E7: 6.73497,-1.608583 | F7: 6.708775, -1.627550 | G7: {=_xlfn.IFS(J7<301,2,J7>300,48)} -> 48 | H7: KUMASI | I7: 0 | J7: 800 | K7: =IF(M7="ONT",20,IF(M7="N/A","N/A",IF(M7="MIKROTIK",IF(J7<3000,10,IF(3000<J7>10000,20,IF(10000<J7>20000,40,IF(20000<J7>40000,60,IF(J7>40000,80,IF(J7<300,3,))))))))) -> FALSE | M7: Furukawa | N7: ADSS | O7: 2020 | S7: ACTIVE | T7: Yes
A8: 7 | B8: ASHANTI | C8: ECG | D8: ANGLICAN SENIOR HIGH, KUMASI | E8: 6.692,-1.60927 | F8: 6.696086°, -1.617477° | G8: {=_xlfn.IFS(J8<301,2,J8>300,48)} -> 48 | H8: KUMASI | I8: 0 | J8: 400 | K8: =IF(M8="ONT",20,IF(M8="N/A","N/A",IF(M8="MIKROTIK",IF(J8<3000,10,IF(3000<J8>10000,20,IF(10000<J8>20000,40,IF(20000<J8>40000,60,IF(J8>40000,80,IF(J8<300,3,))))))))) -> FALSE | M8: Furukawa | N8: ADSS | O8: 2020 | S8: ACTIVE | T8: Yes
A9: 8 | B9: ASHANTI | C9: ECG | D9: ARMED FORCES SENIOR HIGH/TECH, KUMASI | E9: 6.691597,-1.629728 | F9: 6.696086°, -1.617477° | G9: {=_xlfn.IFS(J9<301,2,J9>300,48)} -> 48 | H9: KUMASI | I9: 0 | J9: 1200 | K9: =IF(M9="ONT",20,IF(M9="N/A","N/A",IF(M9="MIKROTIK",IF(J9<3000,10,IF(3000<J9>10000,20,IF(10000<J9>20000,40,IF(20000<J9>40000,60,IF(J9>40000,80,IF(J9<300,3,))))))))) -> FALSE | M9: Furukawa | N9: ADSS | O9: 2020 | S9: ACTIVE | T9: Yes
A10: 9 | B10: ASHANTI | C10: ECG | D10: ASANTEMAN SENIOR HIGH | E10: 6.708825,-1.627581 | F10: 6.708775, -1.627550 | G10: {=_xlfn.IFS(J10<301,2,J10>300,48)} -> 48 | H10: KUMASI | I10: 0 | J10: 500 | K10: =IF(M10="ONT",20,IF(M10="N/A","N/A",IF(M10="MIKROTIK",IF(J10<3000,10,IF(3000<J10>10000,20,IF(10000<J10>20000,40,IF(20000<J10>40000,60,IF(J10>40000,80,IF(J10<300,3,))))))))) -> FALSE | M10: Furukawa | N10: ADSS | O10: 2020 | S10: ACTIVE | T10: Yes
A11: 10 | B11: ASHANTI | C11: ECG | D11: ASOKORE MAMPONG MUNICIPAL | E11: 6.7175,-1.56237 | F11: 6.696086°, -1.617477° | G11: {=_xlfn.IFS(J11<301,2,J11>300,48)} -> 48 | H11: ASOKORE | I11: 0 | J11: 426 | K11: =IF(M11="ONT",20,IF(M11="N/A","N/A",IF(M11="MIKROTIK",IF(J11<3000,10,IF(3000<J11>10000,20,IF(10000<J11>20000,40,IF(20000<J11>40000,60,IF(J11>40000,80,IF(J11<300,3,))))))))) -> FALSE | M11: Furukawa | N11: ADSS | O11: 2020 | S11: ACTIVE | T11: Yes
A12: 11 | B12: ASHANTI | C12: ECG | D12: EJISUMAN SENIOR HIGH | E12: 6.728703,-1.475162 | F12: 6.696086°, -1.617477° | G12: {=_xlfn.IFS(J12<301,2,J12>300,48)} -> 48 | H12: EJISU | I12: 0 | J12: 2500 | K12: =IF(M12="ONT",20,IF(M12="N/A","N/A",IF(M12="MIKROTIK",IF(J12<3000,10,IF(3000<J12>10000,20,IF(10000<J12>20000,40,IF(20000<J12>40000,60,IF(J12>40000,80,IF(J12<300,3,))))))))) -> N/A | M12: N/A | N12: ADSS | O12: 2020 | S12: ACTIVE | T12: Yes
A13: 12 | B13: ASHANTI | C13: ECG | D13: ISLAMIC SENIOR HIGH, AMPABAME | E13: 6.712857,-1.641135 | F13: 6.708775, -1.627550 | G13: {=_xlfn.IFS(J13<301,2,J13>300,48)} -> 48 | H13: KUMASI | I13: 0 | J13: 1100 | K13: =IF(M13="ONT",20,IF(M13="N/A","N/A",IF(M13="MIKROTIK",IF(J13<3000,10,IF(3000<J13>10000,20,IF(10000<J13>20000,40,IF(20000<J13>40000,60,IF(J13>40000,80,IF(J13<300,3,))))))))) -> FALSE | M13: Furukawa | N13: ADSS | O13: 2020 | S13: ACTIVE | T13: Yes
A14: 13 | B14: ASHANTI | C14: ECG | D14: KNUST SENIOR HIGH | E14: 6.689783,-1.54805 | F14: 6.696086°, -1.617477° | G14: {=_xlfn.IFS(J14<301,2,J14>300,48)} -> 48 | H14: KUMASI | I14: 0 | J14: 629 | K14: =IF(M14="ONT",20,IF(M14="N/A","N/A",IF(M14="MIKROTIK",IF(J14<3000,10,IF(3000<J14>10000,20,IF(10000<J14>20000,40,IF(20000<J14>40000,60,IF(J14>40000,80,IF(J14<300,3,))))))))) -> FALSE | M14: Furukawa | N14: ADSS | O14: 2020 | S14: ACTIVE | T14: Yes
... A54: 53 | B54: ASHANTI | C54: ECG | D54: EFANEST KESSBEN CEO RESIDENCE KUMASI | E54: 6.683168, -1.632282 | F54: 6.696086°, -1.617477° | G54: {=_xlfn.IFS(J54<301,2,J54>300,48)} -> 48 | H54: KUMASI | I54: 0 | J54: 1700 | K54: =IF(M54="ONT",20,IF(M54="N/A","N/A",IF(M54="MIKROTIK",IF(J54<3000,10,IF(3000<J54>10000,20,IF(10000<J54>20000,40,IF(20000<J54>40000,60,IF(J54>40000,80,IF(J54<300,3,))))))))) -> 20 | M54: ONT | N54: ADSS | O54: 2021 | S54: ACTIVE | T54: Yes
A55: 54 | B55: ASHANTI | C55: ECG | D55: ODENEHO KUMASI | E55: 6.672321, -1.651491 | F55: 6.696086°, -1.617477° | G55: {=_xlfn.IFS(J55<301,2,J55>300,48)} -> 48 | H55: KUMASI | I55: 0 | J55: 1800 | K55: =IF(M55="ONT",20,IF(M55="N/A","N/A",IF(M55="MIKROTIK",IF(J55<3000,10,IF(3000<J55>10000,20,IF(10000<J55>20000,40,IF(20000<J55>40000,60,IF(J55>40000,80,IF(J55<300,3,))))))))) -> 20 | M55: ONT | N55: ADSS | O55: 2021 | P55: 44400 | Q55: July | S55: ACTIVE | T55: Yes
A56: 55 | B56: ASHANTI | C56: ECG | D56: LONGFORD ROYAL HOTEL | E56: 6.727498, -1.581914 | F56: 6.696086°, -1.617477° | G56: {=_xlfn.IFS(J56<301,2,J56>300,48)} -> 48 | H56: KUMASI | I56: 0 | J56: 1800 | K56: =IF(M56="ONT",20,IF(M56="N/A","N/A",IF(M56="MIKROTIK",IF(J56<3000,10,IF(3000<J56>10000,20,IF(10000<J56>20000,40,IF(20000<J56>40000,60,IF(J56>40000,80,IF(J56<300,3,))))))))) -> 10 | M56: MIKROTIK | N56: ADSS | O56: 2021 | P56: 44400 | Q56: July | S56: ACTIVE | T56: Yes
A57: 56 | B57: ASHANTI | C57: ECG | D57: ODENEHO TSE ADDO MAYFAIR | E57: 5.610061, -0.141144 | F57: 5.584144, -0.164072 | G57: {=_xlfn.IFS(J57<301,2,J57>300,48)} -> 48 | H57: TSE ADDO | I57: 0 | J57: 2500 | K57: =IF(M57="ONT",20,IF(M57="N/A","N/A",IF(M57="MIKROTIK",IF(J57<3000,10,IF(3000<J57>10000,20,IF(10000<J57>20000,40,IF(20000<J57>40000,60,IF(J57>40000,80,IF(J57<300,3,))))))))) -> 20 | M57: ONT | N57: ADSS | O57: 2021 | P57: 44383 | Q57: July | S57: ACTIVE | T57: Yes
A58: 57 | B58: ASHANTI | C58: ECG | D58: ABSA ASAFO BRANCH | E58: 6.684504, -1.614025 | F58: 5.584144, -0.164072 | G58: {=_xlfn.IFS(J58<301,2,J58>300,48)} -> 48 | H58: KUMASI | I58: 0 | J58: 1500 | K58: =IF(M58="ONT",20,IF(M58="N/A","N/A",IF(M58="MIKROTIK",IF(J58<3000,10,IF(3000<J58>10000,20,IF(10000<J58>20000,40,IF(20000<J58>40000,60,IF(J58>40000,80,IF(J58<300,3,))))))))) -> 20 | M58: ONT | N58: ADSS | O58: 2022 | P58: 44568 | Q58: January | S58: ACTIVE | T58: Yes
A59: 58 | B59: ASHANTI | C59: ECG | D59: ABSA KROFROM | E59: 6.713413,-1.615592 | F59: 6.696086°, -1.617477° | G59: {=_xlfn.IFS(J59<301,2,J59>300,48)} -> 48 | H59: Krofrom | I59: 0 | J59: 400 | K59: =IF(M59="ONT",20,IF(M59="N/A","N/A",IF(M59="MIKROTIK",IF(J59<3000,10,IF(3000<J59>10000,20,IF(10000<J59>20000,40,IF(20000<J59>40000,60,IF(J59>40000,80,IF(J59<300,3,))))))))) -> 20 | M59: ONT | N59: ADSS | O59: 2021 | S59: ACTIVE | T59: Yes
A60: 59 | B60: ASHANTI | C60: ECG | D60: ABSA KUMASI KPST MAIN AND PLC /PREMPEH | E60: 6.689871,-1.622878 | F60: 6.696086°, -1.617477° | G60: {=_xlfn.IFS(J60<301,2,J60>300,48)} -> 48 | H60: KUMASI | I60: 0 | J60: 800 | K60: =IF(M60="ONT",20,IF(M60="N/A","N/A",IF(M60="MIKROTIK",IF(J60<3000,10,IF(3000<J60>10000,20,IF(10000<J60>20000,40,IF(20000<J60>40000,60,IF(J60>40000,80,IF(J60<300,3,))))))))) -> 20 | M60: ONT | N60: ADSS | O60: 2021 | S60: ACTIVE | T60: Yes
A61: 60 | B61: ASHANTI | C61: ECG | D61: ABSA SUAME MAGAZINE/ OLD SUAME | E61: 6.728684,-1.63248 | F61: 6.696086°, -1.617477° | G61: {=_xlfn.IFS(J61<301,2,J61>300,48)} -> 48 | H61: SUAME | I61: 0 | J61: 400 | K61: =IF(M61="ONT",20,IF(M61="N/A","N/A",IF(M61="MIKROTIK",IF(J61<3000,10,IF(3000<J61>10000,20,IF(10000<J61>20000,40,IF(20000<J61>40000,60,IF(J61>40000,80,IF(J61<300,3,))))))))) -> 20 | M61: ONT | N61: ADSS | O61: 2021 | S61: ACTIVE | T61: Yes
A62: 61 | B62: ASHANTI | C62: ECG | D62: ABSA TAFO | E62: 6.739561,-1.611229 | F62: 6.708775, -1.627550 | G62: {=_xlfn.IFS(J62<301,2,J62>300,48)} -> 48 | H62: TAFO | I62: 0 | J62: 400 | K62: =IF(M62="ONT",20,IF(M62="N/A","N/A",IF(M62="MIKROTIK",IF(J62<3000,10,IF(3000<J62>10000,20,IF(10000<J62>20000,40,IF(20000<J62>40000,60,IF(J62>40000,80,IF(J62<300,3,))))))))) -> 20 | M62: ONT | N62: ADSS | O62: 2021 | S62: ACTIVE | T62: Yes
A63: 62 | B63: ASHANTI | C63: ECG | D63: ABSA TANOSO | E63: 6.696178,-1.68193 | F63: 6.708775, -1.627550 | G63: {=_xlfn.IFS(J63<301,2,J63>300,48)} -> 2 | H63: TANOSO | I63: 0 | J63: 300 | K63: =IF(M63="ONT",20,IF(M63="N/A","N/A",IF(M63="MIKROTIK",IF(J63<3000,10,IF(3000<J63>10000,20,IF(10000<J63>20000,40,IF(20000<J63>40000,60,IF(J63>40000,80,IF(J63<300,3,))))))))) -> 20 | M63: ONT | N63: ADSS | O63: 2021 | S63: ACTIVE | T63: Yes
A64: 63 | B64: ASHANTI | C64: ECG | D64: ABSA BANTAMA | E64: 642'23.50"N 138'10.85"W | F64: 6.708775, -1.627550 | G64: {=_xlfn.IFS(J64<301,2,J64>300,48)} -> 48 | H64: BANTAMA | I64: 0 | J64: 350 | K64: =IF(M64="ONT",20,IF(M64="N/A","N/A",IF(M64="MIKROTIK",IF(J64<3000,10,IF(3000<J64>10000,20,IF(10000<J64>20000,40,IF(20000<J64>40000,60,IF(J64>40000,80,IF(J64<300,3,))))))))) -> 20 | M64: ONT | N64: ADSS | O64: 2021 | S64: ACTIVE | T64: Yes
A65: 64 | B65: ASHANTI | C65: ECG | D65: SAN_ERNEST CHEMIST_KUM_SANTASE | E65: 640'15.41"N 138'16.08"W | F65: 6.708775, -1.627550 | G65: {=_xlfn.IFS(J65<301,2,J65>300,48)} -> 48 | H65: SANTASI | I65: 0 | J65: 700 | K65: =IF(M65="ONT",20,IF(M65="N/A","N/A",IF(M65="MIKROTIK",IF(J65<3000,10,IF(3000<J65>10000,20,IF(10000<J65>20000,40,IF(20000<J65>40000,60,IF(J65>40000,80,IF(J65<300,3,))))))))) -> 20 | M65: ONT | N65: ADSS | O65: 2021 | P65: 44534 | Q65: December | S65: ACTIVE | T65: Yes
A66: 65 | B66: ASHANTI | C66: ECG | D66: SPORT BETTING GROUP KUMASI | E66: 6.687589 -1.607350 | F66: 6.708775, -1.627550 | G66: {=_xlfn.IFS(J66<301,2,J66>300,48)} -> 48 | H66: KUMASI | I66: 0 | J66: 700 | K66: =IF(M66="ONT",20,IF(M66="N/A","N/A",IF(M66="MIKROTIK",IF(J66<3000,10,IF(3000<J66>10000,20,IF(10000<J66>20000,40,IF(20000<J66>40000,60,IF(J66>40000,80,IF(J66<300,3,))))))))) -> 20 | M66: ONT | N66: ADSS | O66: 2021 | S66: ACTIVE | T66: Yes
A67: 66 | B67: ASHANTI | C67: ECG | D67: ASANTEMAN - BROADSPECTRUM | E67: 6.678250, -1.616044 | F67: 6.708775, -1.627550 | G67: {=_xlfn.IFS(J67<301,2,J67>300,48)} -> 48 | H67: KUMASI | I67: 0 | J67: 3500 | K67: =IF(M67="ONT",20,IF(M67="N/A","N/A",IF(M67="MIKROTIK",IF(J67<3000,10,IF(3000<J67>10000,20,IF(10000<J67>20000,40,IF(20000<J67>40000,60,IF(J67>40000,80,IF(J67<300,3,))))))))) -> 20 | M67: MIKROTIK | N67: ADSS | O67: 2021 | S67: ACTIVE | T67: Yes
A68: 67 | B68: ASHANTI | C68: ECG | D68: ASAFO BRANCH | E68: 6.684504,-1.614025 | F68: 6.708775, -1.627550 | G68: {=_xlfn.IFS(J68<301,2,J68>300,48)} -> 48 | H68: KUMASI | I68: 0 | J68: 1129.8 | K68: =IF(M68="ONT",20,IF(M68="N/A","N/A",IF(M68="MIKROTIK",IF(J68<3000,10,IF(3000<J68>10000,20,IF(10000<J68>20000,40,IF(20000<J68>40000,60,IF(J68>40000,80,IF(J68<300,3,))))))))) -> FALSE | M68: VSOL 1RD | N68: ADSS | O68: 2021 | S68: ACTIVE | T68: Yes
A69: 68 | B69: ASHANTI | C69: ECG | D69: ODEHENO | E69: 6.672321,-1.651491 | F69: 6.708775, -1.627550 | G69: {=_xlfn.IFS(J69<301,2,J69>300,48)} -> 48 | H69: KUMASI | I69: 0 | J69: 577.5 | K69: =IF(M69="ONT",20,IF(M69="N/A","N/A",IF(M69="MIKROTIK",IF(J69<3000,10,IF(3000<J69>10000,20,IF(10000<J69>20000,40,IF(20000<J69>40000,60,IF(J69>40000,80,IF(J69<300,3,))))))))) -> 10 | M69: MIKROTIK | N69: ADSS | O69: 2021 | S69: ACTIVE | T69: Yes
A70: 69 | B70: ASHANTI | C70: ECG | D70: LANGFORD HOTEL | E70: 6.727498, -1.581914 | F70: 6.708775, -1.627550 | G70: {=_xlfn.IFS(J70<301,2,J70>300,48)} -> 48 | H70: KUMASI | I70: 0 | J70: 3715.95 | K70: =IF(M70="ONT",20,IF(M70="N/A","N/A",IF(M70="MIKROTIK",IF(J70<3000,10,IF(3000<J70>10000,20,IF(10000<J70>20000,40,IF(20000<J70>40000,60,IF(J70>40000,80,IF(J70<300,3,))))))))) -> 20 | M70: MIKROTIK | N70: ADSS | O70: 2021 | S70: ACTIVE | T70: Yes
A71: 70 | B71: ASHANTI | C71: ECG | D71: BOADI F TO KNUST | E71: 6.686874, -1.545754 | F71: 6°41'12.91"N 1°32'44.65"W | G71: 24 | H71: KUMASI | I71: 0 | J71: 4048.8 | K71: =IF(M71="ONT",20,IF(M71="N/A","N/A",IF(M71="MIKROTIK",IF(J71<3000,10,IF(3000<J71>10000,20,IF(10000<J71>20000,40,IF(20000<J71>40000,60,IF(J71>40000,80,IF(J71<300,3,))))))))) -> N/A | M71: N/A | N71: ADSS | O71: 2022 | S71: ACTIVE | T71: Yes
A72: 71 | B72: ASHANTI | C72: ECG | D72: CROP RESEARCH INSTITUTE | E72: 6.710169,-1.527967 | F72: 6.696086°, -1.617477° | G72: {=_xlfn.IFS(J72<301,2,J72>300,48)} -> 48 | H72: KUMASI | I72: 0 | J72: 567 | K72: =IF(M72="ONT",20,IF(M72="N/A","N/A",IF(M72="MIKROTIK",IF(J72<3000,10,IF(3000<J72>10000,20,IF(10000<J72>20000,40,IF(20000<J72>40000,60,IF(J72>40000,80,IF(J72<300,3,))))))))) -> 10 | M72: MIKROTIK | N72: ADSS | O72: 2020 | S72: ACTIVE | T72: Yes
A73: 72 | B73: ASHANTI | C73: ECG | D73: GOLDEN TULIP KUMASI | E73: 6.682457, -1.625554 | F73: 6.696086°, -1.617477° | G73: {=_xlfn.IFS(J73<301,2,J73>300,48)} -> 48 | H73: KUMASI | I73: 0 | J73: 315 | K73: =IF(M73="ONT",20,IF(M73="N/A","N/A",IF(M73="MIKROTIK",IF(J73<3000,10,IF(3000<J73>10000,20,IF(10000<J73>20000,40,IF(20000<J73>40000,60,IF(J73>40000,80,IF(J73<300,3,))))))))) -> N/A | M73: N/A | N73: ADSS | O73: 2021 | S73: ACTIVE | T73: Yes
A74: 73 | B74: ASHANTI | C74: ECG | D74: INTERNATIONAL COMMUNITY SCHOOL, AJAMESU | E74: 6.537139,-1.668662 | F74: 6.696086°, -1.617477° | G74: {=_xlfn.IFS(J74<301,2,J74>300,48)} -> 48 | H74: KUMASI | I74: 0 | J74: 400 | K74: =IF(M74="ONT",20,IF(M74="N/A","N/A",IF(M74="MIKROTIK",IF(J74<3000,10,IF(3000<J74>10000,20,IF(10000<J74>20000,40,IF(20000<J74>40000,60,IF(J74>40000,80,IF(J74<300,3,))))))))) -> 10 | M74: MIKROTIK | N74: ADSS | O74: 2021 | S74: ACTIVE | T74: Yes
A75: 74 | B75: ASHANTI | C75: ECG | D75: JACKSON COMPLEX 2 | E75: 6.6891,-1.6352 | F75: 6.708775, -1.627550 | G75: {=_xlfn.IFS(J75<301,2,J75>300,48)} -> 48 | H75: KUMASI | I75: 0 | J75: 3963.75 | K75: =IF(M75="ONT",20,IF(M75="N/A","N/A",IF(M75="MIKROTIK",IF(J75<3000,10,IF(3000<J75>10000,20,IF(10000<J75>20000,40,IF(20000<J75>40000,60,IF(J75>40000,80,IF(J75<300,3,))))))))) -> 20 | M75: MIKROTIK | N75: ADSS | O75: 2020 | S75: ACTIVE | T75: Yes
A76: 75 | B76: ASHANTI | C76: ECG | D76: JACKSON EDUCATIONAL COMPLEX | E76: 6.673182,-1.553365 | F76: 6.708775, -1.627550 | G76: {=_xlfn.IFS(J76<301,2,J76>300,48)} -> 48 | H76: KUMASI | I76: 0 | J76: 1000 | K76: =IF(M76="ONT",20,IF(M76="N/A","N/A",IF(M76="MIKROTIK",IF(J76<3000,10,IF(3000<J76>10000,20,IF(10000<J76>20000,40,IF(20000<J76>40000,60,IF(J76>40000,80,IF(J76<300,3,))))))))) -> 10 | M76: MIKROTIK | N76: ADSS | O76: 2020 | S76: ACTIVE | T76: Yes
A77: 76 | B77: ASHANTI | C77: ECG | D77: OFORIKROM MUNICIPAL | E77: 6.688106,-1.594238 | F77: 6.696086°, -1.617477° | G77: {=_xlfn.IFS(J77<301,2,J77>300,48)} -> 48 | H77: OFORIKROM | I77: 0 | J77: 315 | K77: =IF(M77="ONT",20,IF(M77="N/A","N/A",IF(M77="MIKROTIK",IF(J77<3000,10,IF(3000<J77>10000,20,IF(10000<J77>20000,40,IF(20000<J77>40000,60,IF(J77>40000,80,IF(J77<300,3,))))))))) -> 20 | M77: ONT | N77: ADSS | O77: 2020 | S77: ACTIVE | T77: Yes
A78: 77 | B78: ASHANTI | C78: ECG | D78: OSEI TUTU SENIOR HIGH, AKROPONG | E78: 6.738295,-1.722737 | F78: 6.708775, -1.627550 | G78: {=_xlfn.IFS(J78<301,2,J78>300,48)} -> 48 | H78: KUMASI | I78: 0 | J78: 8373.75 | K78: =IF(M78="ONT",20,IF(M78="N/A","N/A",IF(M78="MIKROTIK",IF(J78<3000,10,IF(3000<J78>10000,20,IF(10000<J78>20000,40,IF(20000<J78>40000,60,IF(J78>40000,80,IF(J78<300,3,))))))))) -> N/A | M78: N/A | N78: ADSS | O78: 2021 | S78: ACTIVE | T78: Yes
A79: 78 | B79: ASHANTI | C79: ECG | D79: ST. LOUIS COLLEGE OF EDUCATION,�KUMASI | E79: 6.706729,-1.626197 | F79: 6.708775, -1.627550 | G79: {=_xlfn.IFS(J79<301,2,J79>300,48)} -> 48 | H79: KUMASI | I79: 0 | J79: 394.8 | K79: =IF(M79="ONT",20,IF(M79="N/A","N/A",IF(M79="MIKROTIK",IF(J79<3000,10,IF(3000<J79>10000,20,IF(10000<J79>20000,40,IF(20000<J79>40000,60,IF(J79>40000,80,IF(J79<300,3,))))))))) -> 20 | M79: ONT | N79: ADSS | O79: 2021 | S79: ACTIVE | T79: Yes
A80: 79 | B80: ASHANTI | C80: ECG | D80: YAA ASANTEWA - ABSA MERGE | E80: 6.697507, -1.699824 | F80: 6.696086°, -1.617477° | G80: {=_xlfn.IFS(J80<301,2,J80>300,48)} -> 48 | H80: KUMASI | I80: 0 | J80: 2206.05 | K80: =IF(M80="ONT",20,IF(M80="N/A","N/A",IF(M80="MIKROTIK",IF(J80<3000,10,IF(3000<J80>10000,20,IF(10000<J80>20000,40,IF(20000<J80>40000,60,IF(J80>40000,80,IF(J80<300,3,))))))))) -> N/A | M80: N/A | N80: ADSS | O80: 2021 | S80: ACTIVE | T80: Yes
A81: 80 | B81: ASHANTI | C81: ECG | D81: NPRA (KUMASI) | E81: 6.676436, -1.598133 | F81: 6.696086°, -1.617477° | G81: {=_xlfn.IFS(J81<301,2,J81>300,48)} -> 48 | H81: KUMASI | I81: 0 | J81: 700 | K81: =IF(M81="ONT",20,IF(M81="N/A","N/A",IF(M81="MIKROTIK",IF(J81<3000,10,IF(3000<J81>10000,20,IF(10000<J81>20000,40,IF(20000<J81>40000,60,IF(J81>40000,80,IF(J81<300,3,))))))))) -> 10 | M81: MIKROTIK | N81: ADSS | O81: 2023 | S81: ACTIVE | T81: Yes
A82: 81 | B82: ASHANTI | C82: ECG | D82: FAB MANHYIA | E82: 6.702893 -1.614202 | F82: 6.696086°, -1.617477° | G82: {=_xlfn.IFS(J82<301,2,J82>300,48)} -> 48 | H82: KUMASI | I82: 0 | J82: 500 | K82: =IF(M82="ONT",20,IF(M82="N/A","N/A",IF(M82="MIKROTIK",IF(J82<3000,10,IF(3000<J82>10000,20,IF(10000<J82>20000,40,IF(20000<J82>40000,60,IF(J82>40000,80,IF(J82<300,3,))))))))) -> 20 | M82: ONT | N82: ADSS | O82: 2022 | S82: ACTIVE | T82: Yes
A83: 82 | B83: ASHANTI | C83: ECG | D83: KUMARK | E83: 6.705527 -1.624199 | F83: 6.708775, -1.627550 | G83: {=_xlfn.IFS(J83<301,2,J83>300,48)} -> 48 | H83: KUMASI | I83: 0 | J83: 400 | K83: =IF(M83="ONT",20,IF(M83="N/A","N/A",IF(M83="MIKROTIK",IF(J83<3000,10,IF(3000<J83>10000,20,IF(10000<J83>20000,40,IF(20000<J83>40000,60,IF(J83>40000,80,IF(J83<300,3,))))))))) -> 20 | M83: ONT | N83: ADSS | O83: 2020 | S83: ACTIVE | T83: Yes
... A105: 104 | B105: CENTRAL | C105: ECG | D105: UNIVERSITY OF EDUCATION, WINNEBA LAST MILE | E105: 5.360979, -0.633509 | F105: 5.117614, -1.244325 | G105: {=_xlfn.IFS(J105<301,2,J105>300,48)} -> 48 | H105: WINNEBA | I105: 0 | J105: 4000 | K105: =IF(M105="ONT",20,IF(M105="N/A","N/A",IF(M105="MIKROTIK",IF(J105<3000,10,IF(3000<J105>10000,20,IF(10000<J105>20000,40,IF(20000<J105>40000,60,IF(J105>40000,80,IF(J105<300,3,))))))))) -> N/A | M105: N/A | N105: ADSS | O105: 2021 | S105: ACTIVE | T105: Yes
A106: 105 | B106: CENTRAL | C106: ECG | D106: KASOA NORTH | E106: 5.535266, -0.412451 | F106: 5.117614, -1.244325 | G106: 24 | H106: KASOA | I106: 0 | J106: 7500 | K106: =IF(M106="ONT",20,IF(M106="N/A","N/A",IF(M106="MIKROTIK",IF(J106<3000,10,IF(3000<J106>10000,20,IF(10000<J106>20000,40,IF(20000<J106>40000,60,IF(J106>40000,80,IF(J106<300,3,))))))))) -> N/A | M106: N/A | N106: ADSS | O106: 2021 | S106: ACTIVE | T106: Yes
A107: 106 | B107: CENTRAL | C107: ECG | D107: KASOA SOUTH | E107: 5.533481, -0.425442 | F107: 5.117614, -1.244325 | G107: {=_xlfn.IFS(J107<301,2,J107>300,48)} -> 48 | H107: KASOA | I107: 0 | J107: 3600 | K107: =IF(M107="ONT",20,IF(M107="N/A","N/A",IF(M107="MIKROTIK",IF(J107<3000,10,IF(3000<J107>10000,20,IF(10000<J107>20000,40,IF(20000<J107>40000,60,IF(J107>40000,80,IF(J107<300,3,))))))))) -> N/A | M107: N/A | N107: ADSS | O107: 2021 | S107: ACTIVE | T107: Yes
A108: 107 | B108: WESTERN | C108: ECG | D108: HOLY CHILD COLLEGE OF EDUCATION, SEKONDI -TAKORADI | E108: 4.935736,-1.74672 | F108: 5.117614, -1.244325 | G108: {=_xlfn.IFS(J108<301,2,J108>300,48)} -> 48 | H108: TAKORADI | I108: 0 | J108: 1500 | K108: =IF(M108="ONT",20,IF(M108="N/A","N/A",IF(M108="MIKROTIK",IF(J108<3000,10,IF(3000<J108>10000,20,IF(10000<J108>20000,40,IF(20000<J108>40000,60,IF(J108>40000,80,IF(J108<300,3,))))))))) -> 10 | M108: MIKROTIK | N108: ADSS | O108: 2021 | S108: ACTIVE | T108: Yes
A109: 108 | B109: CENTRAL | C109: ECG | D109: ABSA CAPE COAST | E109: 5 6'21.66"N 114'28.13"W | F109: 5.117614, -1.244325 | G109: {=_xlfn.IFS(J109<301,2,J109>300,48)} -> 48 | H109: CAPECOAST | I109: 0 | J109: 1400 | K109: =IF(M109="ONT",20,IF(M109="N/A","N/A",IF(M109="MIKROTIK",IF(J109<3000,10,IF(3000<J109>10000,20,IF(10000<J109>20000,40,IF(20000<J109>40000,60,IF(J109>40000,80,IF(J109<300,3,))))))))) -> 10 | M109: MIKROTIK | N109: ADSS | O109: 2021 | S109: ACTIVE | T109: Yes
A110: 109 | B110: GREATER ACCRA | C110: ECG | D110: KASOA 1 SOCCABET | E110: 5.535443, -0.420973 | F110: 5.117614, -1.244325 | G110: {=_xlfn.IFS(J110<301,2,J110>300,48)} -> 48 | H110: KASOA | I110: 0 | J110: 2000 | K110: =IF(M110="ONT",20,IF(M110="N/A","N/A",IF(M110="MIKROTIK",IF(J110<3000,10,IF(3000<J110>10000,20,IF(10000<J110>20000,40,IF(20000<J110>40000,60,IF(J110>40000,80,IF(J110<300,3,))))))))) -> 10 | M110: MIKROTIK | N110: ADSS | O110: 2021 | S110: ACTIVE | T110: Yes
A111: 110 | B111: GREATER ACCRA | C111: ECG | D111: B5 PLUS KASOA | E111: 5.535496,-0.408833 | F111: 5.117614, -1.244325 | G111: {=_xlfn.IFS(J111<301,2,J111>300,48)} -> 48 | H111: KASOA | I111: 0 | J111: 800 | K111: =IF(M111="ONT",20,IF(M111="N/A","N/A",IF(M111="MIKROTIK",IF(J111<3000,10,IF(3000<J111>10000,20,IF(10000<J111>20000,40,IF(20000<J111>40000,60,IF(J111>40000,80,IF(J111<300,3,))))))))) -> 10 | M111: MIKROTIK | N111: ADSS | O111: 2021 | S111: ACTIVE | T111: Yes
A112: 111 | B112: CENTRAL | C112: ECG | D112: WINNEBA SUBSTATION TO UEW | E112: 5.361383, -0.631297 | F112: 5.388139, -0.645250 | G112: 24 | H112: WINNEBA | I112: 0 | J112: 4024.65 | K112: =IF(M112="ONT",20,IF(M112="N/A","N/A",IF(M112="MIKROTIK",IF(J112<3000,10,IF(3000<J112>10000,20,IF(10000<J112>20000,40,IF(20000<J112>40000,60,IF(J112>40000,80,IF(J112<300,3,))))))))) -> N/A | M112: N/A | N112: ADSS | O112: 2021 | S112: ACTIVE | T112: Yes
A113: 112 | B113: CENTRAL | C113: ECG | D113: TEE POINT - WINNEBA DISTRICT | E113: 5.377854, -0.642034 | F113: 5.117614, -1.244325 | G113: {=_xlfn.IFS(J113<301,2,J113>300,48)} -> 48 | H113: WINNEBA | I113: 0 | J113: 315 | K113: =IF(M113="ONT",20,IF(M113="N/A","N/A",IF(M113="MIKROTIK",IF(J113<3000,10,IF(3000<J113>10000,20,IF(10000<J113>20000,40,IF(20000<J113>40000,60,IF(J113>40000,80,IF(J113<300,3,))))))))) -> N/A | M113: N/A | N113: ADSS | O113: 2021 | S113: ACTIVE | T113: Yes
A114: 113 | B114: CENTRAL | C114: ECG | D114: CAPE COAST EDUCATION OFFICE | E114: 5.107689, -1.247608 | F114: 5.117614, -1.244325 | G114: {=_xlfn.IFS(J114<301,2,J114>300,48)} -> 48 | H114: CAPECOAST | I114: 0 | J114: 2118.9 | K114: =IF(M114="ONT",20,IF(M114="N/A","N/A",IF(M114="MIKROTIK",IF(J114<3000,10,IF(3000<J114>10000,20,IF(10000<J114>20000,40,IF(20000<J114>40000,60,IF(J114>40000,80,IF(J114<300,3,))))))))) -> FALSE | M114: D-LINK | N114: ADSS | O114: 2021 | S114: ACTIVE | T114: Yes
A115: 114 | B115: CENTRAL | C115: ECG | D115: CCTU CLINIC | E115: 5.153468,-1.278349 | F115: 5.117614, -1.244325 | G115: {=_xlfn.IFS(J115<301,2,J115>300,48)} -> 48 | H115: CAPECOAST | I115: 0 | J115: 315 | K115: =IF(M115="ONT",20,IF(M115="N/A","N/A",IF(M115="MIKROTIK",IF(J115<3000,10,IF(3000<J115>10000,20,IF(10000<J115>20000,40,IF(20000<J115>40000,60,IF(J115>40000,80,IF(J115<300,3,))))))))) -> FALSE | M115: D-LINK | N115: ADSS | O115: 2021 | S115: ACTIVE | T115: Yes
A116: 115 | B116: CENTRAL | C116: ECG | D116: CCTU NEW BLOCK | E116: 5.153473,-1.279471 | F116: 5.117614, -1.244325 | G116: {=_xlfn.IFS(J116<301,2,J116>300,48)} -> 48 | H116: CAPECOAST | I116: 0 | J116: 315 | K116: =IF(M116="ONT",20,IF(M116="N/A","N/A",IF(M116="MIKROTIK",IF(J116<3000,10,IF(3000<J116>10000,20,IF(10000<J116>20000,40,IF(20000<J116>40000,60,IF(J116>40000,80,IF(J116<300,3,))))))))) -> FALSE | M116: CISCO/D-LINK | N116: ADSS | O116: 2021 | S116: ACTIVE | T116: Yes
A117: 116 | B117: CENTRAL | C117: ECG | D117: CIVIL AND BUILDING DEPT | E117: 5.154683,-1.279184 | F117: 5.117614, -1.244325 | G117: {=_xlfn.IFS(J117<301,2,J117>300,48)} -> 48 | H117: CAPECOAST | I117: 0 | J117: 315 | K117: =IF(M117="ONT",20,IF(M117="N/A","N/A",IF(M117="MIKROTIK",IF(J117<3000,10,IF(3000<J117>10000,20,IF(10000<J117>20000,40,IF(20000<J117>40000,60,IF(J117>40000,80,IF(J117<300,3,))))))))) -> FALSE | M117: D-LINK | N117: ADSS | O117: 2021 | S117: ACTIVE | T117: Yes
A118: 117 | B118: CENTRAL | C118: ECG | D118: CCTU - ELEC DEPARTMENT | E118: 5.154585, -1.278709 | F118: 5.117614, -1.244325 | G118: {=_xlfn.IFS(J118<301,2,J118>300,48)} -> 48 | H118: CAPECOAST | I118: 0 | J118: 315 | K118: =IF(M118="ONT",20,IF(M118="N/A","N/A",IF(M118="MIKROTIK",IF(J118<3000,10,IF(3000<J118>10000,20,IF(10000<J118>20000,40,IF(20000<J118>40000,60,IF(J118>40000,80,IF(J118<300,3,))))))))) -> FALSE | M118: D-LINK | N118: ADSS | O118: 2021 | S118: ACTIVE | T118: Yes
A119: 118 | B119: CENTRAL | C119: ECG | D119: ECG SUBSTATION - CAPECOAST | E119: 5.117852, -1.244636 | F119: 5.117614, -1.244325 | G119: {=_xlfn.IFS(J119<301,2,J119>300,48)} -> 48 | H119: CAPECOAST | I119: 0 | J119: 315 | K119: =IF(M119="ONT",20,IF(M119="N/A","N/A",IF(M119="MIKROTIK",IF(J119<3000,10,IF(3000<J119>10000,20,IF(10000<J119>20000,40,IF(20000<J119>40000,60,IF(J119>40000,80,IF(J119<300,3,))))))))) -> N/A | M119: N/A | N119: ADSS | O119: 2021 | S119: ACTIVE | T119: Yes
A120: 119 | B120: CENTRAL | C120: ECG | D120: EFFUTU SENIOR HIGH/TECH | E120: 5.203687,-1.323434 | F120: 5.117614, -1.244325 | G120: {=_xlfn.IFS(J120<301,2,J120>300,48)} -> 48 | H120: EFFUTU | I120: 0 | J120: 9251.55 | K120: =IF(M120="ONT",20,IF(M120="N/A","N/A",IF(M120="MIKROTIK",IF(J120<3000,10,IF(3000<J120>10000,20,IF(10000<J120>20000,40,IF(20000<J120>40000,60,IF(J120>40000,80,IF(J120<300,3,))))))))) -> 20 | M120: MIKROTIK | N120: ADSS | O120: 2021 | S120: ACTIVE | T120: Yes
A121: 120 | B121: CENTRAL | C121: ECG | D121: HOLY CHILD | E121: 5.121464, -1.233710 | F121: 5.117614, -1.244325 | G121: {=_xlfn.IFS(J121<301,2,J121>300,48)} -> 48 | H121: CAPECOAST | I121: 0 | J121: 2160.9 | K121: =IF(M121="ONT",20,IF(M121="N/A","N/A",IF(M121="MIKROTIK",IF(J121<3000,10,IF(3000<J121>10000,20,IF(10000<J121>20000,40,IF(20000<J121>40000,60,IF(J121>40000,80,IF(J121<300,3,))))))))) -> 10 | M121: MIKROTIK | N121: ADSS | O121: 2021 | S121: ACTIVE | T121: Yes
A122: 121 | B122: CENTRAL | C122: ECG | D122: KASOA SOUTH FROM KASOA SS | E122: 5.533472, -0.425508 | F122: 5.117614, -1.244325 | G122: {=_xlfn.IFS(J122<301,2,J122>300,48)} -> 48 | H122: KASOA | I122: 0 | J122: 3195.15 | K122: =IF(M122="ONT",20,IF(M122="N/A","N/A",IF(M122="MIKROTIK",IF(J122<3000,10,IF(3000<J122>10000,20,IF(10000<J122>20000,40,IF(20000<J122>40000,60,IF(J122>40000,80,IF(J122<300,3,))))))))) -> N/A | M122: N/A | N122: ADSS | O122: 2021 | S122: ACTIVE | T122: Yes
A123: 122 | B123: CENTRAL | C123: ECG | D123: MAIN ADMIN | E123: 5.152822,-1.279142 | F123: 5.117614, -1.244325 | G123: {=_xlfn.IFS(J123<301,2,J123>300,48)} -> 48 | H123: CAPECOAST | I123: 0 | J123: 315 | K123: =IF(M123="ONT",20,IF(M123="N/A","N/A",IF(M123="MIKROTIK",IF(J123<3000,10,IF(3000<J123>10000,20,IF(10000<J123>20000,40,IF(20000<J123>40000,60,IF(J123>40000,80,IF(J123<300,3,))))))))) -> FALSE | M123: CISCO/D-LINK | N123: ADSS | O123: 2021 | S123: ACTIVE | T123: Yes
A124: 123 | B124: CENTRAL | C124: ECG | D124: NEW AUDITORIUM | E124: 5.152524,-1.278184 | F124: 5.117614, -1.244325 | G124: {=_xlfn.IFS(J124<301,2,J124>300,48)} -> 48 | H124: CAPECOAST | I124: 0 | J124: 315 | K124: =IF(M124="ONT",20,IF(M124="N/A","N/A",IF(M124="MIKROTIK",IF(J124<3000,10,IF(3000<J124>10000,20,IF(10000<J124>20000,40,IF(20000<J124>40000,60,IF(J124>40000,80,IF(J124<300,3,))))))))) -> N/A | M124: N/A | N124: ADSS | O124: 2021 | S124: ACTIVE | T124: Yes
... A126: 125 | B126: CENTRAL | C126: ECG | D126: SALTPOND SUBSTATION TO SALTPOND DIST OFF | E126: 5.201730, -1.066392 | F126: 5.117614, -1.244325 | G126: {=_xlfn.IFS(J126<301,2,J126>300,48)} -> 48 | H126: SALTPOND | I126: 0 | J126: 3232.95 | K126: =IF(M126="ONT",20,IF(M126="N/A","N/A",IF(M126="MIKROTIK",IF(J126<3000,10,IF(3000<J126>10000,20,IF(10000<J126>20000,40,IF(20000<J126>40000,60,IF(J126>40000,80,IF(J126<300,3,))))))))) -> N/A | M126: N/A | N126: ADSS | O126: 2022 | S126: ACTIVE | T126: Yes
A127: 126 | B127: CENTRAL | C127: ECG | D127: UCC LASTMILE | E127: 5.122527, -1.294850 | F127: 5.117614, -1.244325 | G127: 24 | H127: CAPECOAST | I127: 0 | J127: 12000 | K127: =IF(M127="ONT",20,IF(M127="N/A","N/A",IF(M127="MIKROTIK",IF(J127<3000,10,IF(3000<J127>10000,20,IF(10000<J127>20000,40,IF(20000<J127>40000,60,IF(J127>40000,80,IF(J127<300,3,))))))))) -> N/A | M127: N/A | N127: ADSS | O127: 2021 | S127: ACTIVE | T127: Yes
A128: 127 | B128: CENTRAL | C128: ECG | D128: UCC OLD DATA CENTER | E128: 5.115815,-1.293491 | F128: 5.117614, -1.244325 | G128: {=_xlfn.IFS(J128<301,2,J128>300,48)} -> 48 | H128: CAPECOAST | I128: 0 | J128: 315 | K128: =IF(M128="ONT",20,IF(M128="N/A","N/A",IF(M128="MIKROTIK",IF(J128<3000,10,IF(3000<J128>10000,20,IF(10000<J128>20000,40,IF(20000<J128>40000,60,IF(J128>40000,80,IF(J128<300,3,))))))))) -> N/A | M128: N/A | N128: ADSS | O128: 2021 | S128: ACTIVE | T128: Yes
A129: 128 | B129: CENTRAL | C129: ECG | D129: UCC OLD SITE | E129: 5.105474,-1.284439 | F129: 5.117614, -1.244325 | G129: {=_xlfn.IFS(J129<301,2,J129>300,48)} -> 48 | H129: CAPECOAST | I129: 0 | J129: 1577.1 | K129: =IF(M129="ONT",20,IF(M129="N/A","N/A",IF(M129="MIKROTIK",IF(J129<3000,10,IF(3000<J129>10000,20,IF(10000<J129>20000,40,IF(20000<J129>40000,60,IF(J129>40000,80,IF(J129<300,3,))))))))) -> N/A | M129: N/A | N129: ADSS | O129: 2021 | S129: ACTIVE | T129: Yes
A130: 129 | B130: CENTRAL | C130: ECG | D130: CCTU LIBRARY/NOC | E130: 5.154429,-1.277909 | F130: 5.117614, -1.244325 | G130: {=_xlfn.IFS(J130<301,2,J130>300,48)} -> 48 | H130: CAPECOAST | I130: 0 | J130: 315 | K130: =IF(M130="ONT",20,IF(M130="N/A","N/A",IF(M130="MIKROTIK",IF(J130<3000,10,IF(3000<J130>10000,20,IF(10000<J130>20000,40,IF(20000<J130>40000,60,IF(J130>40000,80,IF(J130<300,3,))))))))) -> 10 | M130: MIKROTIK | N130: ADSS | O130: 2020 | S130: ACTIVE | T130: Yes
A131: 130 | B131: CENTRAL | C131: ECG | D131: CCTU MECHANICAL DEPT | E131: 5.154615,-1.279678 | F131: 5.117614, -1.244325 | G131: {=_xlfn.IFS(J131<301,2,J131>300,48)} -> 48 | H131: CAPECOAST | I131: 0 | J131: 315 | K131: =IF(M131="ONT",20,IF(M131="N/A","N/A",IF(M131="MIKROTIK",IF(J131<3000,10,IF(3000<J131>10000,20,IF(10000<J131>20000,40,IF(20000<J131>40000,60,IF(J131>40000,80,IF(J131<300,3,))))))))) -> 10 | M131: MIKROTIK | N131: ADSS | O131: 2020 | S131: ACTIVE | T131: Yes
A132: 131 | B132: CENTRAL | C132: ECG | D132: CCTU STORES | E132: 5.154903,-1.279538 | F132: 5.117614, -1.244325 | G132: {=_xlfn.IFS(J132<301,2,J132>300,48)} -> 48 | H132: CAPECOAST | I132: 0 | J132: 315 | K132: =IF(M132="ONT",20,IF(M132="N/A","N/A",IF(M132="MIKROTIK",IF(J132<3000,10,IF(3000<J132>10000,20,IF(10000<J132>20000,40,IF(20000<J132>40000,60,IF(J132>40000,80,IF(J132<300,3,))))))))) -> 10 | M132: MIKROTIK | N132: ADSS | O132: 2020 | S132: ACTIVE | T132: Yes
A133: 132 | B133: CENTRAL | C133: ECG | D133: 1XBET-CAPECOAST | E133: 5.132246,-1.275613 | F133: 5.117614, -1.244325 | G133: {=_xlfn.IFS(J133<301,2,J133>300,48)} -> 48 | H133: CAPECOAST | I133: 0 | J133: 520 | K133: =IF(M133="ONT",20,IF(M133="N/A","N/A",IF(M133="MIKROTIK",IF(J133<3000,10,IF(3000<J133>10000,20,IF(10000<J133>20000,40,IF(20000<J133>40000,60,IF(J133>40000,80,IF(J133<300,3,))))))))) -> 10 | M133: MIKROTIK | N133: ADSS | O133: 2022 | S133: ACTIVE | T133: Yes
A134: 133 | B134: CENTRAL | C134: ECG | D134: CCTU HOSTEL | E134: 5.152661,-1.277477 | F134: 5.117614, -1.244325 | G134: {=_xlfn.IFS(J134<301,2,J134>300,48)} -> 48 | H134: CAPECOAST | I134: 0 | J134: 3200 | K134: =IF(M134="ONT",20,IF(M134="N/A","N/A",IF(M134="MIKROTIK",IF(J134<3000,10,IF(3000<J134>10000,20,IF(10000<J134>20000,40,IF(20000<J134>40000,60,IF(J134>40000,80,IF(J134<300,3,))))))))) -> FALSE | M134: CISCO SW | N134: ADSS | O134: 2020 | S134: ACTIVE | T134: Yes
A135: 134 | B135: CENTRAL | C135: ECG | D135: FAB SALTPOND | E135: 5.221992 -1.048042 | F135: 5.117614, -1.244325 | G135: {=_xlfn.IFS(J135<301,2,J135>300,48)} -> 48 | H135: SALTPOND | I135: 0 | J135: 600 | K135: =IF(M135="ONT",20,IF(M135="N/A","N/A",IF(M135="MIKROTIK",IF(J135<3000,10,IF(3000<J135>10000,20,IF(10000<J135>20000,40,IF(20000<J135>40000,60,IF(J135>40000,80,IF(J135<300,3,))))))))) -> 10 | M135: MIKROTIK | N135: ADSS | O135: 2023 | S135: ACTIVE | T135: Yes
A136: 135 | B136: EASTERN | C136: ECG | D136: CONTRACTA APPARTMENT ROUTE | E136: 6.070693, -0.016422 | F136: 6.097086, 0.064292 | G136: {=_xlfn.IFS(J136<301,2,J136>300,48)} -> 48 | H136: SOMANYA | I136: 0 | J136: 315 | K136: =IF(M136="ONT",20,IF(M136="N/A","N/A",IF(M136="MIKROTIK",IF(J136<3000,10,IF(3000<J136>10000,20,IF(10000<J136>20000,40,IF(20000<J136>40000,60,IF(J136>40000,80,IF(J136<300,3,))))))))) -> 10 | M136: MIKROTIK | N136: ADSS | O136: 2021 | S136: ACTIVE | T136: Yes
A137: 136 | B137: EASTERN | C137: ECG | D137: NEW JUABEN NORTH MUNICIPAL | E137: 6.109793,-0.26847 | F137: 6.091217, -0.258442 | G137: {=_xlfn.IFS(J137<301,2,J137>300,48)} -> 48 | H137: JUABEN | I137: 0 | J137: 3000 | K137: =IF(M137="ONT",20,IF(M137="N/A","N/A",IF(M137="MIKROTIK",IF(J137<3000,10,IF(3000<J137>10000,20,IF(10000<J137>20000,40,IF(20000<J137>40000,60,IF(J137>40000,80,IF(J137<300,3,))))))))) -> 20 | M137: MIKROTIK | N137: ADSS | O137: 2021 | S137: ACTIVE | T137: Yes
A138: 137 | B138: EASTERN | C138: ECG | D138: NEW JUABEN SOUTH MUNICIPAL | E138: 6.091217,-0.258581 | F138: 6.091217, -0.258442 | G138: {=_xlfn.IFS(J138<301,2,J138>300,48)} -> 2 | H138: JUABEN | I138: 0 | J138: 300 | K138: =IF(M138="ONT",20,IF(M138="N/A","N/A",IF(M138="MIKROTIK",IF(J138<3000,10,IF(3000<J138>10000,20,IF(10000<J138>20000,40,IF(20000<J138>40000,60,IF(J138>40000,80,IF(J138<300,3,))))))))) -> 10 | M138: MIKROTIK | N138: ADSS | O138: 2021 | S138: ACTIVE | T138: Yes
A139: 138 | B139: EASTERN | C139: ECG | D139: MT MARY COLLEGE OF EDUCATION SOMANYA | E139: 6.115379, -0.016027 | F139: 6.097086, 0.064292 | G139: {=_xlfn.IFS(J139<301,2,J139>300,48)} -> 48 | H139: SOMANYA | I139: 0 | J139: 2800 | K139: =IF(M139="ONT",20,IF(M139="N/A","N/A",IF(M139="MIKROTIK",IF(J139<3000,10,IF(3000<J139>10000,20,IF(10000<J139>20000,40,IF(20000<J139>40000,60,IF(J139>40000,80,IF(J139<300,3,))))))))) -> 10 | M139: MIKROTIK | N139: ADSS | O139: 2021 | S139: ACTIVE | T139: Yes
... A156: 155 | B156: EASTERN | C156: ECG | D156: AKUSE DATACENTER(48F)(VRA) | E156: 6.093553, 0.114530 | F156: 6.097086, 0.064292 | G156: {=_xlfn.IFS(J156<301,2,J156>300,48)} -> 48 | H156: AKUSE | I156: 0 | J156: 9372.3 | K156: =IF(M156="ONT",20,IF(M156="N/A","N/A",IF(M156="MIKROTIK",IF(J156<3000,10,IF(3000<J156>10000,20,IF(10000<J156>20000,40,IF(20000<J156>40000,60,IF(J156>40000,80,IF(J156<300,3,))))))))) -> N/A | M156: N/A | N156: ADSS | O156: 2021 | S156: ACTIVE | T156: Yes
A157: 156 | B157: EASTERN | C157: ECG | D157: BUNSO TO KIBI DIST OFFICE | E157: 6.158153, -0.559129 | F157: 6.158225, -0.559117 | G157: 24 | H157: BONSU | I157: 0 | J157: 19684.35 | K157: =IF(M157="ONT",20,IF(M157="N/A","N/A",IF(M157="MIKROTIK",IF(J157<3000,10,IF(3000<J157>10000,20,IF(10000<J157>20000,40,IF(20000<J157>40000,60,IF(J157>40000,80,IF(J157<300,3,))))))))) -> N/A | M157: N/A | N157: ADSS | O157: 2021 | S157: ACTIVE | T157: Yes
A158: 157 | B158: EASTERN | C158: ECG | D158: MOUNT MARY COLLEGE OF EDUCATION | E158: 6.115379,-0.016027 | F158: 6.097086, 0.064292 | G158: {=_xlfn.IFS(J158<301,2,J158>300,48)} -> 48 | H158: SOMANYA | I158: 0 | J158: 2303.7 | K158: =IF(M158="ONT",20,IF(M158="N/A","N/A",IF(M158="MIKROTIK",IF(J158<3000,10,IF(3000<J158>10000,20,IF(10000<J158>20000,40,IF(20000<J158>40000,60,IF(J158>40000,80,IF(J158<300,3,))))))))) -> 10 | M158: MIKROTIK | N158: ADSS | O158: 2021 | S158: ACTIVE | T158: Yes
A159: 158 | B159: EASTERN | C159: ECG | D159: SUHUM SUBSTATION TO SUHUM DIST OFF | E159: 6.040994, -0.442475 | F159: 6.027995°, -0.449935° | G159: 24 | H159: SUHUM | I159: 0 | J159: 2796.15 | K159: =IF(M159="ONT",20,IF(M159="N/A","N/A",IF(M159="MIKROTIK",IF(J159<3000,10,IF(3000<J159>10000,20,IF(10000<J159>20000,40,IF(20000<J159>40000,60,IF(J159>40000,80,IF(J159<300,3,))))))))) -> 10 | M159: MIKROTIK | N159: ADSS | O159: 2021 | S159: ACTIVE | T159: Yes
A160: 159 | B160: EASTERN | C160: ECG | D160: NKAWKAW DIST OFF TO NKAWKAW SUBSTATION | E160: 6.556525, -0.780061 | F160: 6.560261, -0.775392 | G160: 24 | H160: NKAWKAW | I160: 0 | J160: 824.25 | K160: =IF(M160="ONT",20,IF(M160="N/A","N/A",IF(M160="MIKROTIK",IF(J160<3000,10,IF(3000<J160>10000,20,IF(10000<J160>20000,40,IF(20000<J160>40000,60,IF(J160>40000,80,IF(J160<300,3,))))))))) -> 10 | M160: MIKROTIK | N160: ADSS | O160: 2021 | S160: ACTIVE | T160: Yes
A161: 160 | B161: EASTERN | C161: ECG | D161: ELECSET NETWORK | E161: 5.98725,-0.087634 | F161: 5.873167, -0.157817 | G161: {=_xlfn.IFS(J161<301,2,J161>300,48)} -> 48 | H161: AKWAPIM | I161: 0 | J161: 11636.1 | K161: =IF(M161="ONT",20,IF(M161="N/A","N/A",IF(M161="MIKROTIK",IF(J161<3000,10,IF(3000<J161>10000,20,IF(10000<J161>20000,40,IF(20000<J161>40000,60,IF(J161>40000,80,IF(J161<300,3,))))))))) -> 20 | M161: MIKROTIK | N161: ADSS | O161: 2023 | S161: ACTIVE | T161: Yes
A162: 161 | B162: EASTERN | C162: ECG | D162: VOLTIC GHANA LIMITED (ADIESO ROAD) | E162: 5.820236,-0.378149 | F162: 5.704165°, -0.300260° | G162: {=_xlfn.IFS(J162<301,2,J162>300,48)} -> 48 | H162: ADISEO | I162: 0 | J162: 2500 | K162: =IF(M162="ONT",20,IF(M162="N/A","N/A",IF(M162="MIKROTIK",IF(J162<3000,10,IF(3000<J162>10000,20,IF(10000<J162>20000,40,IF(20000<J162>40000,60,IF(J162>40000,80,IF(J162<300,3,))))))))) -> 10 | M162: MIKROTIK | N162: ADSS | O162: 2022 | S162: ACTIVE | T162: Yes
A163: 162 | B163: EASTERN | C163: ECG | D163: NPRA (KOFORIDUA) | E163: 6.078536, -0.269683 | F163: 6.091217, -0.258442 | G163: {=_xlfn.IFS(J163<301,2,J163>300,48)} -> 48 | H163: KOFORIDUA | I163: 0 | J163: 2600 | K163: =IF(M163="ONT",20,IF(M163="N/A","N/A",IF(M163="MIKROTIK",IF(J163<3000,10,IF(3000<J163>10000,20,IF(10000<J163>20000,40,IF(20000<J163>40000,60,IF(J163>40000,80,IF(J163<300,3,))))))))) -> 10 | M163: MIKROTIK | N163: ADSS | O163: 2023 | S163: ACTIVE | T163: Yes
A164: 163 | B164: EASTERN | C164: ECG | D164: ABSA NEW ABRIEM | E164: 6.343878, -0.997808 | F164: 6.538083, -0.758908 | G164: {=_xlfn.IFS(J164<301,2,J164>300,48)} -> 2 | H164: NEW ABREM | I164: 0 | J164: 250 | K164: =IF(M164="ONT",20,IF(M164="N/A","N/A",IF(M164="MIKROTIK",IF(J164<3000,10,IF(3000<J164>10000,20,IF(10000<J164>20000,40,IF(20000<J164>40000,60,IF(J164>40000,80,IF(J164<300,3,))))))))) -> 10 | M164: MIKROTIK | N164: ADSS | O164: 2023 | S164: ACTIVE | T164: Yes
A165: 164 | B165: EASTERN | C165: ECG | D165: AKROPONG KWAYISIBEA HOTEL | E165: 5.949549 -0.102871 | F165: 5.873167, -0.157817 | G165: {=_xlfn.IFS(J165<301,2,J165>300,48)} -> 48 | H165: AKROPONG | I165: 0 | J165: 12000 | K165: =IF(M165="ONT",20,IF(M165="N/A","N/A",IF(M165="MIKROTIK",IF(J165<3000,10,IF(3000<J165>10000,20,IF(10000<J165>20000,40,IF(20000<J165>40000,60,IF(J165>40000,80,IF(J165<300,3,))))))))) -> 20 | M165: MIKROTIK | N165: ADSS | O165: 2023 | S165: ACTIVE | T165: Yes
A166: 165 | B166: EASTERN | C166: ECG | D166: FREEDOTEL | E166: 5.9006934,-0.1499885 | F166: 5.873167, -0.157817 | G166: {=_xlfn.IFS(J166<301,2,J166>300,48)} -> 48 | H166: ABURI | I166: 0 | J166: 3100 | K166: =IF(M166="ONT",20,IF(M166="N/A","N/A",IF(M166="MIKROTIK",IF(J166<3000,10,IF(3000<J166>10000,20,IF(10000<J166>20000,40,IF(20000<J166>40000,60,IF(J166>40000,80,IF(J166<300,3,))))))))) -> 20 | M166: MIKROTIK | N166: ADSS | O166: 2023 | S166: ACTIVE | T166: Yes
A167: 166 | B167: EASTERN | C167: ECG | D167: HENRY AMANKWAH | E167: 5.823353 -0.185328 | F167: 5.873167, -0.157817 | G167: {=_xlfn.IFS(J167<301,2,J167>300,48)} -> 2 | H167: ABURI | I167: 0 | J167: 300 | K167: =IF(M167="ONT",20,IF(M167="N/A","N/A",IF(M167="MIKROTIK",IF(J167<3000,10,IF(3000<J167>10000,20,IF(10000<J167>20000,40,IF(20000<J167>40000,60,IF(J167>40000,80,IF(J167<300,3,))))))))) -> 10 | M167: MIKROTIK | N167: ADSS | O167: 2023 | S167: ACTIVE | T167: Yes
A168: 167 | B168: EASTERN | C168: ECG | D168: Koforidua Senior High/Tech | E168: 6.076758, -0.259322 | F168: 6.091217, -0.258442 | G168: {=_xlfn.IFS(J168<301,2,J168>300,48)} -> 48 | H168: KOFORIDUA | I168: 0 | J168: 3500 | K168: =IF(M168="ONT",20,IF(M168="N/A","N/A",IF(M168="MIKROTIK",IF(J168<3000,10,IF(3000<J168>10000,20,IF(10000<J168>20000,40,IF(20000<J168>40000,60,IF(J168>40000,80,IF(J168<300,3,))))))))) -> 20 | M168: MIKROTIK | N168: ADSS | O168: 2020 | S168: ACTIVE | T168: Yes
A169: 168 | B169: EASTERN | C169: ECG | D169: AKUSE ROYAL LODGE | E169: 6.219519 0.089220 | F169: 6.097086, 0.064292 | G169: {=_xlfn.IFS(J169<301,2,J169>300,48)} -> 2 | H169: AKUSE | I169: 0 | J169: 150 | K169: =IF(M169="ONT",20,IF(M169="N/A","N/A",IF(M169="MIKROTIK",IF(J169<3000,10,IF(3000<J169>10000,20,IF(10000<J169>20000,40,IF(20000<J169>40000,60,IF(J169>40000,80,IF(J169<300,3,))))))))) -> 10 | M169: MIKROTIK | N169: ADSS | O169: 2020 | S169: ACTIVE | T169: Yes
A170: 169 | B170: GREATER ACCRA | C170: ECG | D170: ST. MARGARET MARY SNR.HIGH/TECH | E170: 5.560057, -0.269484 | F170: 5.117614, -1.244325 | G170: {=_xlfn.IFS(J170<301,2,J170>300,48)} -> 48 | H170: DANSOMAN | I170: 0 | J170: 1728.3 | K170: =IF(M170="ONT",20,IF(M170="N/A","N/A",IF(M170="MIKROTIK",IF(J170<3000,10,IF(3000<J170>10000,20,IF(10000<J170>20000,40,IF(20000<J170>40000,60,IF(J170>40000,80,IF(J170<300,3,))))))))) -> 20 | M170: ONT | N170: ADSS | O170: 2021 | S170: ACTIVE | T170: Yes
A171: 170 | B171: GREATER ACCRA | C171: ECG | D171: ABLEKUMA CENTRAL MUNICIPAL | E171: 5.553431,-0.240433 | F171: 5.584144, -0.164072 | G171: {=_xlfn.IFS(J171<301,2,J171>300,48)} -> 2 | H171: ABLEKUMA | I171: 0 | J171: 100 | K171: =IF(M171="ONT",20,IF(M171="N/A","N/A",IF(M171="MIKROTIK",IF(J171<3000,10,IF(3000<J171>10000,20,IF(10000<J171>20000,40,IF(20000<J171>40000,60,IF(J171>40000,80,IF(J171<300,3,))))))))) -> 20 | M171: ONT | N171: ADSS | O171: 2020 | S171: ACTIVE | T171: Yes
A172: 171 | B172: GREATER ACCRA | C172: ECG | D172: ABLEKUMA NORTH MUNICIPAL | E172: 5.58389,-0.2575 | F172: 5.563083, -0.299931 | G172: {=_xlfn.IFS(J172<301,2,J172>300,48)} -> 48 | H172: ABLEKUMA | I172: 0 | J172: 2200 | K172: =IF(M172="ONT",20,IF(M172="N/A","N/A",IF(M172="MIKROTIK",IF(J172<3000,10,IF(3000<J172>10000,20,IF(10000<J172>20000,40,IF(20000<J172>40000,60,IF(J172>40000,80,IF(J172<300,3,))))))))) -> 10 | M172: MIKROTIK | N172: ADSS | O172: 2020 | S172: ACTIVE | T172: Yes
... A310: 309 | B310: GREATER ACCRA | C310: ECG | D310: PRESBY BOYS SENIOR HIGH, LEGON | E310: 5.662462,-0.176124 | F310: 5.677436, -0.167211 | G310: {=_xlfn.IFS(J310<301,2,J310>300,48)} -> 48 | H310: LEGON | I310: 0 | J310: 700 | K310: =IF(M310="ONT",20,IF(M310="N/A","N/A",IF(M310="MIKROTIK",IF(J310<3000,10,IF(3000<J310>10000,20,IF(10000<J310>20000,40,IF(20000<J310>40000,60,IF(J310>40000,80,IF(J310<300,3,))))))))) -> 20 | M310: ONT | N310: ADSS | O310: 2021 | S310: ACTIVE | T310: Yes
A311: 310 | B311: GREATER ACCRA | C311: ECG | D311: UNIVERSITY OF GHANA, LEGON (UG) | E311: 5.650370, -0.186080 | F311: 5.677436, -0.167211 | G311: 24 | H311: LEGON | I311: 0 | J311: 4000 | K311: =IF(M311="ONT",20,IF(M311="N/A","N/A",IF(M311="MIKROTIK",IF(J311<3000,10,IF(3000<J311>10000,20,IF(10000<J311>20000,40,IF(20000<J311>40000,60,IF(J311>40000,80,IF(J311<300,3,))))))))) -> N/A | M311: N/A | N311: ADSS | O311: 2021 | S311: ACTIVE | T311: Yes
A312: 311 | B312: GREATER ACCRA | C312: ECG | D312: UNIVERSITY OF PROFESSIONAL STUDIES ACCRA (UPSA) | E312: 5.661872, -0.165458 | F312: 5.677436, -0.167211 | G312: 24 | H312: LEGON | I312: 0 | J312: 2000 | K312: =IF(M312="ONT",20,IF(M312="N/A","N/A",IF(M312="MIKROTIK",IF(J312<3000,10,IF(3000<J312>10000,20,IF(10000<J312>20000,40,IF(20000<J312>40000,60,IF(J312>40000,80,IF(J312<300,3,))))))))) -> N/A | M312: N/A | N312: ADSS | O312: 2021 | S312: ACTIVE | T312: Yes
A313: 312 | B313: GREATER ACCRA | C313: ECG | D313: PRESBY SENIOR HIGH, OSU | E313: 5.555478,-0.18611 | F313: 5.677436, -0.167211 | G313: {=_xlfn.IFS(J313<301,2,J313>300,48)} -> 48 | H313: OSU | I313: 0 | J313: 700 | K313: =IF(M313="ONT",20,IF(M313="N/A","N/A",IF(M313="MIKROTIK",IF(J313<3000,10,IF(3000<J313>10000,20,IF(10000<J313>20000,40,IF(20000<J313>40000,60,IF(J313>40000,80,IF(J313<300,3,))))))))) -> 20 | M313: ONT | N313: ADSS | O313: 2021 | S313: ACTIVE | T313: Yes
A314: 313 | B314: GREATER ACCRA | C314: ECG | D314: REGIONAL MARITIME UNIVERSITY, ACCRA (RMU) | E314: 5.608036, -0.063383 | F314: 5.614283, -0.089064 | G314: {=_xlfn.IFS(J314<301,2,J314>300,48)} -> 48 | H314: NUNGUA | I314: 0 | J314: 1750 | K314: =IF(M314="ONT",20,IF(M314="N/A","N/A",IF(M314="MIKROTIK",IF(J314<3000,10,IF(3000<J314>10000,20,IF(10000<J314>20000,40,IF(20000<J314>40000,60,IF(J314>40000,80,IF(J314<300,3,))))))))) -> N/A | M314: N/A | N314: ADSS | O314: 2021 | S314: ACTIVE | T314: Yes
...

Sheet POLES
B2: BACKHAUL | J2: METRO
A3: SN | B3: REGION | C3: DSITANCE | D3: POLES UTILIZED | E3: New Poles | F3: EXISTING POLES | I3: SN | J3: REGION | K3: DSITANCE | L3: POLES UTILIZED | M3: New Poles | N3: EXISTING POLES
A4: 1 | B4: ='TOTALS(PASSIVE)'!B3 -> ASHANTI | C4: ='TOTALS(PASSIVE)'!J3 -> 445800 | D4: =C4/100 -> 4458 | E4: 1408 | F4: =D4-E4 -> 3050 | I4: 1 | J4: ='TOTALS(PASSIVE)'!B3 -> ASHANTI | K4: ='TOTALS(PASSIVE)'!C3 -> 210301.3 | L4: 17226 | M4: 689 | N4: =L4-M4 -> 16537
A5: 2 | B5: ='TOTALS(PASSIVE)'!B4 -> CENTRAL | C5: ='TOTALS(PASSIVE)'!J4 -> 520000 | D5: =C5/100 -> 5200 | E5: 2080 | F5: =D5-E5 -> 3120 | I5: 2 | J5: ='TOTALS(PASSIVE)'!B4 -> CENTRAL | K5: ='TOTALS(PASSIVE)'!C4 -> 119608 | L5: 1096 | M5: 438 | N5: =L5-M5 -> 658
A6: 3 | B6: ='TOTALS(PASSIVE)'!B5 -> EASTERN | C6: ='TOTALS(PASSIVE)'!J5 -> 521400 | D6: =C6/100 -> 5214 | E6: 2085 | F6: =D6-E6 -> 3129 | I6: 3 | J6: ='TOTALS(PASSIVE)'!B5 -> EASTERN | K6: ='TOTALS(PASSIVE)'!C5 -> 208681.7 | L6: 1776 | M6: 710 | N6: =L6-M6 -> 1066
A7: 4 | B7: ='TOTALS(PASSIVE)'!B6 -> GREATER ACCRA | C7: ='TOTALS(PASSIVE)'!J6 -> 444800 | D7: =C7/100 -> 4448 | E7: 1775 | F7: =D7-E7 -> 2673 | I7: 4 | J7: ='TOTALS(PASSIVE)'!B6 -> GREATER ACCRA | K7: ='TOTALS(PASSIVE)'!C6 -> 1507321.2 | L7: 13245 | M7: 529 | N7: =L7-M7 -> 12716
A8: 5 | B8: ='TOTALS(PASSIVE)'!B7 -> VOLTA | C8: 299935 | D8: 2999 | E8: 1199 | F8: =D8-E8 -> 1800 | I8: 5 | J8: ='TOTALS(PASSIVE)'!B7 -> VOLTA | K8: ='TOTALS(PASSIVE)'!C7 -> 25159 | L8: =K8/100 -> 251.59 | M8: 97 | N8: =L8-M8 -> 154.59
A9: 6 | B9: ='TOTALS(PASSIVE)'!B8 -> OTI | C9: ='TOTALS(PASSIVE)'!J8 -> 0 | D9: =C9/100 -> 0 | E9: =D9-G9 -> 0 | F9: 0 | I9: 6 | J9: ='TOTALS(PASSIVE)'!B8 -> OTI | K9: ='TOTALS(PASSIVE)'!C8 -> 0 | L9: =K9/100 -> 0 | M9: =L9/1000*4 -> 0 | N9: =L9-M9 -> 0
A10: 7 | B10: ='TOTALS(PASSIVE)'!B9 -> WESTERN | C10: ='TOTALS(PASSIVE)'!J9 -> 483000 | D10: =C10/100 -> 4830 | E10: 1932 | F10: =D10-E10 -> 2898 | I10: 7 | J10: ='TOTALS(PASSIVE)'!B9 -> WESTERN | K10: ='TOTALS(PASSIVE)'!C9 -> 191833.55 | L10: 1575 | M10: 630 | N10: =L10-M10 -> 945
A11: 8 | B11: ='TOTALS(PASSIVE)'!B10 -> WESTERN NORTH | C11: ='TOTALS(PASSIVE)'!J10 -> 234000 | D11: =C11/100 -> 2340 | E11: 936 | F11: =D11-E11 -> 1404 | I11: 8 | J11: ='TOTALS(PASSIVE)'!B10 -> WESTERN NORTH | K11: ='TOTALS(PASSIVE)'!C10 -> 0 | L11: =K11/100 -> 0 | M11: =L11/1000*4 -> 0 | N11: =L11-M11 -> 0
A12: 9 | B12: ='TOTALS(PASSIVE)'!B11 -> BONO EAST | C12: ='TOTALS(PASSIVE)'!J11 -> 82000 | D12: =C12/100 -> 820 | E12: 328 | F12: =D12-E12 -> 492 | I12: 9 | J12: ='TOTALS(PASSIVE)'!B11 -> BONO EAST | K12: ='TOTALS(PASSIVE)'!C11 -> 0 | L12: =K12/100 -> 0 | M12: =L12/1000*4 -> 0 | N12: =L12-M12 -> 0
A13: 10 | B13: ='TOTALS(PASSIVE)'!B12 -> AHAFO | C13: ='TOTALS(PASSIVE)'!J12 -> 40000 | D13: =C13/100 -> 400 | E13: 160 | F13: =D13-E13 -> 240 | I13: 10 | J13: ='TOTALS(PASSIVE)'!B12 -> AHAFO | K13: ='TOTALS(PASSIVE)'!C12 -> 0 | L13: =K13/100 -> 0 | M13: =L13/1000*4 -> 0 | N13: =L13-M13 -> 0
A14: 11 | B14: ='TOTALS(PASSIVE)'!B13 -> BRONG AHAFO | C14: ='TOTALS(PASSIVE)'!J13 -> 395601 | D14: =C14/100 -> 3956.01 | E14: 1000 | F14: =D14-E14 -> 2956.01 | I14: 11 | J14: ='TOTALS(PASSIVE)'!B13 -> BRONG AHAFO | K14: ='TOTALS(PASSIVE)'!C13 -> 1948 | L14: 55 | M14: 22 | N14: =L14-M14 -> 33
A15: 12 | B15: ='TOTALS(PASSIVE)'!B14 -> SAVANNAH | C15: ='TOTALS(PASSIVE)'!J14 -> 217000 | D15: =C15/100 -> 2170 | E15: 868 | F15: =D15-E15 -> 1302 | I15: 12 | J15: ='TOTALS(PASSIVE)'!B14 -> SAVANNAH | K15: ='TOTALS(PASSIVE)'!C14 -> 0 | L15: =K15/100 -> 0 | M15: =L15/1000*4 -> 0 | N15: =L15-M15 -> 0
A16: 13 | B16: ='TOTALS(PASSIVE)'!B15 -> NORTHERN | C16: ='TOTALS(PASSIVE)'!J15 -> 350000 | D16: =C16/100 -> 3500 | E16: 546 | F16: =D16-E16 -> 2954 | I16: 13 | J16: ='TOTALS(PASSIVE)'!B15 -> NORTHERN | K16: ='TOTALS(PASSIVE)'!C15 -> 2268 | L16: =K16/100 -> 22.68 | M16: 180 | N16: =L16-M16 -> -157.32
A17: 14 | B17: ='TOTALS(PASSIVE)'!B16 -> NORTH EAST | C17: ='TOTALS(PASSIVE)'!J16 -> 126000 | D17: =C17/100 -> 1260 | E17: 500 | F17: =D17-E17 -> 760 | I17: 14 | J17: ='TOTALS(PASSIVE)'!B16 -> NORTH EAST | K17: ='TOTALS(PASSIVE)'!C16 -> 0 | L17: =K17/100 -> 0 | M17: =L17/1000*4 -> 0 | N17: =L17-M17 -> 0
A18: 15 | B18: ='TOTALS(PASSIVE)'!B17 -> UPPER EAST | C18: ='TOTALS(PASSIVE)'!J17 -> 172000 | D18: =C18/100 -> 1720 | E18: 688 | F18: =D18-E18 -> 1032 | I18: 15 | J18: ='TOTALS(PASSIVE)'!B17 -> UPPER EAST | K18: ='TOTALS(PASSIVE)'!C17 -> 0 | L18: =K18/100 -> 0 | M18: 10 | N18: =L18-M18 -> -10
A19: 16 | B19: ='TOTALS(PASSIVE)'!B18 -> UPPER WEST | C19: ='TOTALS(PASSIVE)'!J18 -> 279000 | D19: =C19/100 -> 2790 | E19: 1116 | F19: =D19-E19 -> 1674 | I19: 16 | J19: ='TOTALS(PASSIVE)'!B18 -> UPPER WEST | K19: ='TOTALS(PASSIVE)'!C18 -> 0 | L19: =K19/100 -> 0 | M19: =L19/1000*4 -> 0 | N19: =L19-M19 -> 0
E28: =SUM(D4:D11) -> 29489 | F28: =SUM(L4:L11) -> 35169.59 | G28: =SUM(E28:F28) -> 64658.59 | H28: 0.25
E29: =SUM(F4:F11) -> 18074 | F29: =SUM(N4:N11) -> 32076.59 | G29: =SUM(E29:F29) -> 50150.59 | H29: =G29*H28 -> 12537.647
H30: =G29-H29 -> 37612.942

Sheet NEDCO - BACKHAUL
A1: SN | B1: Region | C1: TERRITORY | D1: Name of Line | E1: Coordinates A-End | F1: Coordinates B-End | G1: Fiber Count | H1: Distance (m) | I1: Age | J1: Cost/Value | K1: Comment | L1: Status
A2: 1 | B2: AHAFO | C2: NEDCO | D2: Asanteman (Mankranso) - Bechem | E2: 6.824089, -1.860989 | F2: 7.081364, -2.023164 | G2: 48 | H2: 40000 | I2: 2023 | L2: Active
A3: 2 | B3: BONO EAST | C3: NEDCO | D3: Abofour - Techiman | E3: 7.162217, -1.741411 | F3: 7.589136, -1.919447 | G3: 48 | H3: 77000 | I3: 2023 | L3: Active
A4: 3 | B4: BRONG AHAFO | C4: NEDCO | D4: Bechem- Sunyani | E4: 7.081364, -2.023164 | F4: 7.316661, -2.302783 | G4: 48 | H4: 69000 | I4: 2023 | L4: Active
A5: 4 | B5: BRONG AHAFO | C5: NEDCO | D5: Sunyani - Wenchi | E5: 7.316661, -2.302783 | F5: 7.745303, -2.100225 | G5: 48 | H5: 80000 | I5: 2023 | L5: Active
A6: 5 | B6: BRONG AHAFO | C6: NEDCO | D6: Wenchi - Bamboi | E6: 7.745303, -2.100225 | F6: 8.164119, -2.033883 | G6: 48 | H6: 58000 | I6: 2023 | L6: Active
A7: 6 | B7: NORTHERN | C7: NEDCO | D7: Tamale - Diari | E7: 9.417364, -0.860597 | F7: 9.865044, -0.870639 | G7: 48 | H7: 61000 | I7: 2023 | L7: Active
A8: 7 | B8: NORTH EAST | C8: NEDCO | D8: Diari - Walewale | E8: 9.865044, -0.870639 | F8: 10.337358, -0.799333 | G8: 48 | H8: 63000 | I8: 2023 | L8: Active
A9: 8 | B9: NORTH EAST | C9: NEDCO | D9: Walewale - Bolgatanga | E9: 10.337358, -0.799333 | F9: 10.791053, -0.857317 | G9: 48 | H9: 63000 | I9: 2023 | L9: Active
A10: 9 | B10: NORTHERN | C10: NEDCO | D10: Bolgatanga - Nakong | E10: 10.791053, -0.857317 | F10: 10.820389, -1.416281 | G10: 48 | H10: 79000 | I10: 2023 | L10: Active
A11: 10 | B11: SAVANNAH | C11: NEDCO | D11: Bamboi-Tinga | G11: 48 | H11: 58000 | I11: 2023 | L11: Active
A12: 11 | B12: SAVANNAH | C12: NEDCO | D12: Tinga-Bole | G12: 48 | H12: 63000 | I12: 2023 | L12: Active
A13: 12 | B13: SAVANNAH | C13: NEDCO | D13: Bole-Sawla | G13: 48 | H13: 34000 | I13: 2023 | L13: Active
A14: 13 | B14: SAVANNAH | C14: NEDCO | D14: Sawla-Kumasa | G14: 48 | H14: 62000 | I14: 2023 | L14: Active
A15: 14 | B15: UPPER WEST | C15: NEDCO | D15: Kumasa-Wa | G15: 48 | H15: 51000 | I15: 2023 | L15: Active
A16: 15 | B16: UPPER WEST | C16: NEDCO | D16: Wa-Han | G16: 48 | H16: 81000 | I16: 2023 | L16: Active
A17: 16 | B17: UPPER WEST | C17: NEDCO | D17: Han-Tumu | G17: 48 | H17: 68000 | I17: 2023 | L17: Active
A18: 17 | B18: UPPER WEST | C18: NEDCO | D18: Tumu-Nakong | G18: 48 | H18: 79000 | I18: 2023 | L18: Active
A19: 18 | B19: UPPER EAST | C19: NEDCO | D19: Nakong-Bolga | G19: 48 | H19: 79000 | I19: 2023 | L19: Active
A20: 19 | B20: BRONG AHAFO | C20: NEDCO | D20: Sunyani-Berekum | G20: 48 | H20: 43000 | I20: 2023 | L20: Active
A21: 20 | B21: BONO EAST | C21: NEDCO | D21: Abofour - Kumasi NEDCO | E21: 7.162217, -1.741412 | F21: 6.745728, -1.640629 | G21: 48 | H21: 5000 | I21: 2024 | L21: Active
A22: 21 | B22: UPPER EAST | C22: NEDCO | D22: Bolgatanga - Bawku | G22: 48 | H22: 93000 | I22: 2024 | L22: Active
A23: 22 | B23: BONO | C23: NEDCO | D23: Berekum - Dormaa Ahenkro | G23: 48 | H23: 55470 | I23: 2025 | L23: Inactive
A24: 23 | B24: NORTHERN | C24: NEDCO | D24: Dorma Ahenkro - Goaso | G24: 48 | H24: 90131 | I24: 2025 | L24: Inactive
A25: 24 | B25: NORTHERN | C25: NEDCO | D25: Yendi - Gushegu | G25: 48 | H25: 70000 | I25: 2025 | L25: Active
A26: 25 | B26: NORTHERN | C26: NEDCO | D26: Kpassa - Bimbilla | G26: 48 | H26: 65000 | I26: 2026 | L26: Active
A27: 26 | B27: NORTHERN | C27: NEDCO | D27: Bimbilla - Yendi | G27: 48 | H27: 76000 | I27: 2026 | L27: Active
D64: LEGEND:
D66: ODF:- Optical Distribution Frames
D68: ADSS FOC:- All Dielectric Self Supporting Fibre Optic Cable

Sheet NEDCO - METRO
B1: REGION | C1: TERRITOY | D1: NAME OF LINE | E1: LOCATION | F1: COORDINATES A-END | G1: COORDINATES B-END | H1: DROP DISTANCE (M) | I1: ADSS DISTANCE (M) | J1: 1G SFP DISTANCE(KM) | K1: 10G SFP DISTANCE(KM) | L1: CPE | M1: OPGW / UGFOC /ADSS STATUS | N1: AGE | O1: COST/VALUE | P1: STATUS | Q1: Passed Commisioning Tests
A2: 1 | B2: NORTHERN | C2: NEDCO | D2: B5 PLUS TAMALE | E2: TAMALE | F2: 9.450259° -0.845861° | G2: 9.417553° -0.860828° | H2: 0 | I2: 1400 | J2: 10 | L2: MIKROTIK | N2: 45128 | P2: ACTIVE
A3: 2 | B3: NORTHERN | C3: NEDCO | D3: TAMALE BTS | E3: TAMALE | H3: 0 | I3: 2000 | J3: 10 | L3: MIKROTIK | N3: 45308 | P3: INACTIVE
A4: 3 | B4: BRONG AHAFO | C4: NEDCO | D4: TOYOTA NEW ABIREM | E4: NEW ABREM | H4: 0 | I4: 600 | J4: 10 | L4: MIKROTIK | N4: 45443 | P4: ACTIVE
A5: 4 | B5: NORTHERN | C5: NEDCO | D5: DHL TAMALE | E5: TAMALE | H5: 0 | I5: 300 | J5: 10 | L5: MIKROTIK | N5: 45267 | P5: ACTIVE
A6: 5 | B6: UPPER EAST | C6: NEDCO | D6: NAVRONGO HEALTH RESEARCH CENTER | E6: NAVRONGO | H6: 0 | I6: 2700 | J6: 10 | L6: MIKROTIK | N6: 45237 | P6: ACTIVE
A7: 6 | B7: BRONG AHAFO | C7: NEDCO | D7: SUNYANI HIGH COURT | E7: SUNYANI | H7: 70 | I7: 0 | J7: 10 | L7: MIKROTIK | N7: 45253 | P7: ACTIVE
A8: 7 | B8: NORTHERN | C8: NEDCO | D8: RADIO SAVANNAH | E8: TAMALE | H8: 0 | I8: 300 | J8: 10 | L8: MIKROTIK | N8: 45254 | P8: ACTIVE
A9: 8 | B9: NORTHERN | C9: NEDCO | D9: ABSA GUMANI | E9: GUMANI | H9: 0 | I9: 400 | J9: 10 | L9: MIKROTIK | N9: 45069 | P9: ACTIVE
A10: 9 | B10: NORTHERN | C10: NEDCO | D10: JAPAN MOTORS TAMALE | E10: TAMALE | H10: 0 | I10: 4800 | J10: 20 | L10: MIKROTIK | N10: 45076 | P10: ACTIVE
A11: 10 | B11: NORTHERN | C11: NEDCO | D11: FAR EAST MERCANTILE - TAMALE | E11: TAMALE | H11: 0 | I11: 5600 | J11: 20 | L11: MIKROTIK | N11: 45070 | P11: ACTIVE
A12: 11 | B12: NORTHERN | C12: NEDCO | D12: TAMALE TEACHING HOSPITAL | E12: TAMALE | H12: 0 | I12: 4100 | J12: N/A | L12: N/A | N12: 45056 | P12: ACTIVE
A13: 12 | B13: NORTHERN | C13: NEDCO | D13: CARL TECH | E13: TAMALE | H13: 0 | I13: 450 | J13: 10 | L13: MIKROTIK | N13: 45107 | P13: ACTIVE
A14: 13 | B14: NORTHERN | C14: NEDCO | D14: ABSA TAMALE | E14: TAMALE | H14: 0 | I14: 900 | J14: 10 | L14: MIKROTIK | N14: 45083 | P14: ACTIVE
A15: 14 | B15: NORTHERN | C15: NEDCO | D15: STL NHIA | E15: TAMALE | H15: 0 | I15: 7500 | J15: 20 | L15: MIKROTIK | N15: 45057 | P15: ACTIVE
A16: 15 | B16: NORTHERN | C16: NEDCO | D16: TAMALE AIRPORT | E16: TAMALE | H16: 0 | I16: 13000 | J16: N/A | L16: N/A | N16: 45036 | P16: ACTIVE
A17: 16 | B17: BRONG AHAFO | C17: NEDCO | D17: DVLA SUNYANI | E17: SUNYANI | H17: 0 | I17: 500 | J17: 10 | L17: MIKROTIK | N17: 45330 | P17: ACTIVE
A18: 17 | B18: BRONG AHAFO | C18: NEDCO | D18: INFOWAY | E18: SUNYANI | H18: 0 | I18: 0 | J18: 10 | L18: MIKROTIK | N18: 45334 | P18: ACTIVE
A19: 18 | B19: BRONG AHAFO | C19: NEDCO | D19: GHANA CIVIL AVIATION AUTHORITY | E19: SUNYANI | H19: 0 | I19: 1000 | J19: 20 | L19: MIKROTIK | N19: 45406 | P19: ACTIVE
A20: 19 | B20: WESTERN | C20: ECG | D20: GRATIFIED ENGINEERING COASTAL COMMERE | E20: SUNYANI | H20: 0 | I20: 300 | J20: 20 | L20: ONT | N20: 45412 | P20: ACTIVE
A21: 20 | B21: NORTHERN | C21: NEDCO | D21: KANVILI | E21: TAMALE | H21: 0 | I21: 350 | J21: 20 | L21: MIKROTIK | N21: 45457 | P21: ACTIVE
A22: 21 | B22: NORTHERN | C22: NEDCO | D22: RATCH TAMALE | E22: TAMALE | H22: 0 | I22: 500 | J22: 20 | L22: MIKROTIK | N22: 45457 | P22: ACTIVE
A23: 22 | B23: BRONG AHAFO | C23: NEDCO | D23: INFOWAY - YAMO COLLEGE OF HEALTH | E23: SUNYANI | H23: 0 | I23: 350 | J23: 20 | L23: MIKROTIK | N23: 45415 | P23: ACTIVE
A24: 23 | B24: BRONG AHAFO | C24: NEDCO | D24: M-KOPA SUNYANI | E24: SUNYANI | H24: 0 | I24: 700 | J24: 10 | L24: MIKROTIK | N24: 45510 | P24: ACTIVE
A25: 24 | B25: NORTHERN | C25: NEDCO | D25: M-Kopa Tamale | E25: TAMALE | H25: 0 | I25: 500 | J25: 10 | L25: MIKROTIK | N25: 45524 | P25: ACTIVE
A26: 25 | B26: NORTHERN | C26: NEDCO | D26: ARD Inc (Water Aid Ghana | E26: TAMALE | H26: 0 | I26: 600 | J26: 10 | L26: MIKROTIK | N26: 45531 | P26: ACTIVE
A27: 26 | B27: BRONG AHAFO | C27: NEDCO | D27: Goil Sunyani | E27: SUNYANI | H27: 0 | I27: 700 | J27: 10 | L27: MIKROTIK | N27: 45579 | P27: ACTIVE
A28: 27 | B28: BRONG AHAFO | C28: NEDCO | D28: OmniBSIC Sunyani | E28: SUNYANI | H28: 0 | I28: 650 | J28: FALSE | L28: VSOL 1RD | N28: 45636 | P28: ACTIVE
A29: 28 | B29: NORTHERN | C29: NEDCO | D29: OmniBSIC Tamale | E29: TAMALE | H29: 0 | I29: 1170 | J29: 10 | L29: MIKROTIK | N29: 45615 | P29: ACTIVE
A30: 29 | B30: NORTHERN | C30: NEDCO | D30: Ghana Shippers Authority Tamale | E30: Tamale | H30: 0 | I30: 2000 | J30: FALSE | L30: VSOL 1RD | N30: 45629 | P30: ACTIVE
A31: 30 | B31: NORTHERN | C31: NEDCO | D31: Best Point Savings Tamale | E31: TAMALE | H31: 0 | I31: 348 | J31: 10 | L31: MIKROTIK | N31: 45622 | P31: ACTIVE
A32: 31 | B32: BRONG AHAFO | C32: NEDCO | D32: Best Point Savings Sunyani | E32: SUNYANI | H32: 0 | I32: 650 | J32: 10 | L32: MIKROTIK | N32: 45702 | P32: ACTIVE
A33: 32 | B33: NORTHERN | C33: NEDCO | D33: GOIL TAMALE | E33: TAMALE | H33: 0 | I33: 1800 | J33: 10 | L33: MIKROTIK | N33: 45744 | P33: ACTIVE
A34: 33 | B34: NORTHERN | C34: NEDCO | D34: Advans Tamale | E34: Tamale | H34: 0 | I34: 347 | J34: FALSE | L34: VSOL 1RD | N34: 45781 | P34: ACTIVE
A35: 34 | B35: NORTHERN | C35: NEDCO | D35: MECOY TAMALE | E35: Tamale | H35: 0 | I35: 120 | J35: 10 | L35: MIKROTIK | N35: 45782 | P35: ACTIVE
A36: 35 | B36: NORTHERN | C36: NEDCO | D36: Echo TAMALE OFFICE | E36: Tamale | H36: 0 | I36: 700 | J36: 10 | L36: MIKROTIK | N36: 45812.594 | P36: ACTIVE
A37: 36 | B37: BRONG AHAFO | C37: NEDCO | D37: EFFANEST-SUNYANI | E37: Sunyani | H37: 0 | I37: 220 | J37: 10 | L37: MIKROTIK | N37: 45831.559 | P37: ACTIVE
A38: 37 | B38: BRONG AHAFO | C38: NEDCO | D38: SAWTEL-2-SUNYANI-DVLA | E38: Sunyani | H38: 0 | I38: 45 | J38: 10 | L38: MIKROTIK | N38: 45834.44 | P38: ACTIVE
A39: 38 | B39: BRONG AHAFO | C39: NEDCO | D39: SAWTEL-2-WENCHI-SUB-OFFICE | E39: Wenchi | H39: 0 | I39: 485 | J39: 10 | L39: MIKROTIK | N39: 45835 | P39: ACTIVE
A40: 39 | B40: BRONG AHAFO | C40: NEDCO | D40: SAWTEL-2-WENCHI-CUSTOMS-DVLA | E40: Wenchi | H40: 0 | I40: 150 | J40: 10 | L40: MIKROTIK | N40: 45925 | P40: ACTIVE
A41: 40 | B41: BRONG AHAFO | C41: NEDCO | D41: SAWTEL-2-WENCHI TAINSO OUTPOST | E41: Wenchi | H41: 0 | I41: 0 | J41: FALSE | L41: VSOL 2DAC | N41: 45832.653 | P41: ACTIVE
A42: 41 | B42: BRONG AHAFO | C42: NEDCO | D42: SAWTEL-2-SUNYANI-AREA OFFICE | E42: Sunyani | H42: 0 | I42: 340 | J42: 10 | L42: MIKROTIK | N42: 45846 | P42: ACTIVE
A43: 42 | B43: NORTHERN | C43: NEDCO | D43: KNUST-TAMALE | E43: Tamale | H43: 0 | I43: 1000 | J43: 10 | L43: MIKROTIK | N43: 45874 | P43: ACTIVE
A44: 43 | B44: NORTHERN | C44: NEDCO | D44: MAXINET-DONEWELL-INSURANCE -TAMALE | E44: Tamale | H44: 0 | I44: 336 | J44: FALSE | L44: VSOL 1RD | N44: 45902 | P44: ACTIVE
A45: 44 | B45: UPPER WEST | C45: NEDCO | D45: NEDCO-WA AREA OFFICE | E45: Wa | H45: 50 | I45: 0 | J45: 10 | L45: MIKROTIK | N45: 45902 | P45: ACTIVE
A46: 45 | B46: NORTHERN | C46: NEDCO | D46: NEDCO-TAMALE AREA OFFICE | E46: Tamale | H46: 0 | I46: 377 | J46: 10 | L46: MIKROTIK | N46: 45910 | P46: ACTIVE
A47: 46 | B47: SAVANNA | C47: NEDCO | D47: NEDCO-SAWLA AREA OFFICE | E47: Sawla | H47: 150 | I47: 0 | J47: FALSE | L47: Media Converter | N47: 45938 | P47: ACTIVE
A48: 47 | B48: NORTHERN | C48: NEDCO | D48: DDS-AMERICAN AUTO | E48: Tamale | H48: 0 | I48: 1100 | J48: FALSE | L48: VSOL 1RD | N48: 45946 | P48: ACTIVE
A49: 48 | B49: UPPER WEST | C49: NEDCO | D49: ECHO-GIZ-WA | E49: Wa | H49: 0 | I49: 600 | J49: FALSE | L49: Media Converter | N49: 45978 | P49: ACTIVE
A50: 49 | B50: SAVANNA | C50: NEDCO | D50: SAWTEL-1-DVLA-BOLE | E50: Bole | H50: 99 | I50: 0 | J50: 3 | L50: MIKROTIK | N50: 45978 | P50: ACTIVE
A51: 50 | B51: UPPER EAST | C51: NEDCO | D51: IKLICK -MC BAUCHEMIE | E51: Adenta | H51: 502 | I51: 2241 | J51: FALSE | L51: VSOL 2DAC | N51: 45985 | P51: ACTIVE
A52: 51 | B52: NORTHERN | C52: NEDCO | D52: ECHO-BAYPORT- TAMALE | E52: Tamale | H52: 140 | I52: 1677 | J52: FALSE | L52: VSOL 1RD | N52: 46003 | P52: ACTIVE
A53: 52 | B53: NORTHERN | C53: NEDCO | D53: DDS-CFAO-TAMALE | E53: Tamale | H53: 0 | I53: 463 | J53: FALSE | L53: VSOL 1RD | N53: 46011 | P53: ACTIVE
A54: 53 | B54: BONO | C54: NEDCO | D54: ECONNECTA -NPRA-SUNYANI | E54: Sunyani | H54: 0 | I54: 1500 | J54: 20 | L54: MIKROTIK | N54: 46011 | P54: ACTIVE
A55: 54 | B55: NORTHERN | C55: NEDCO | D55: Tamale Base Station | E55: Tamale | H55: 0 | I55: 768 | J55: 20 | L55: MIKROTIK | N55: 46050 | P55: ACTIVE

Sheet MASTER-ACCESSORIES- METRO
B1: Region | C1: Territory | D1: Name of Line | E1: Dropcable distance (m) | F1: ADSS distance (m) | G1: Pole Brackets (pcs) | H1: Tension Clamps (pcs) | I1: Suspensions (pcs) | J1: Buckles (pcs) | K1: Steel Band (m) | L1: Closures (pcs) | M1: Deadends | N1: Status | O1: DATE
A2: {=_xlfn.SEQUENCE(COUNTA(D$2:D$1048576))} -> 1 | B2: ASHANTI | C2: ECG | D2: MANHYIA PALACE | E2: 0 | F2: 2100 | G2: =(((F2/70)+1)*0.4) -> 12.4 | H2: =G2*2 -> 24.8 | I2: =(((F2/70)+1)*0.6) -> 18.6 | J2: =I2+G2 -> 31 | K2: =J2 -> 31 | L2: =(F2/4000)+1 -> 1.525 | M2: =E2/60 -> 0 | N2: ACTIVE
A3: 2 | B3: ASHANTI | C3: ECG | D3: PRINCE OF PEACE GIRLS | E3: 0 | F3: 2200 | G3: =(((F3/70)+1)*0.4) -> 12.971429 | H3: =G3*2 -> 25.942857 | I3: =(((F3/70)+1)*0.6) -> 19.457143 | J3: =I3+G3 -> 32.428571 | K3: =J3 -> 32.428571 | L3: =(F3/4000)+1 -> 1.55 | M3: =E3/60 -> 0 | N3: INACTIVE
A4: 3 | B4: ASHANTI | C4: ECG | D4: ST. LOUIS SENIOR HIGH, KUMASI | E4: 0 | F4: 1500 | G4: =(((F4/70)+1)*0.4) -> 8.9714286 | H4: =G4*2 -> 17.942857 | I4: =(((F4/70)+1)*0.6) -> 13.457143 | J4: =I4+G4 -> 22.428571 | K4: =J4 -> 22.428571 | L4: =(F4/4000)+1 -> 1.375 | M4: =E4/60 -> 0 | N4: ACTIVE
A5: 4 | B5: ASHANTI | C5: ECG | D5: ADVENTIST SENIOR HIGH, KUMASI | E5: 150 | F5: 0 | G5: =(((F5/70)+1)*0.4) -> 0.4 | H5: =G5*2 -> 0.8 | I5: =(((F5/70)+1)*0.6) -> 0.6 | J5: =I5+G5 -> 1 | K5: =J5 -> 1 | L5: =(F5/4000)+1 -> 1 | M5: =E5/60 -> 2.5 | N5: ACTIVE
A6: 5 | B6: ASHANTI | C6: ECG | D6: AGRIC NZEMA SENIOR HIGH, KUMASI | E6: 0 | F6: 3575 | G6: =(((F6/70)+1)*0.4) -> 20.828571 | H6: =G6*2 -> 41.657143 | I6: =(((F6/70)+1)*0.6) -> 31.242857 | J6: =I6+G6 -> 52.071429 | K6: =J6 -> 52.071429 | L6: =(F6/4000)+1 -> 1.89375 | M6: =E6/60 -> 0 | N6: ACTIVE
A7: 6 | B7: ASHANTI | C7: ECG | D7: AL-AZARIYA ISLAMIC SNR. HIGH, KUMASI | E7: 0 | F7: 800 | G7: =(((F7/70)+1)*0.4) -> 4.9714286 | H7: =G7*2 -> 9.9428571 | I7: =(((F7/70)+1)*0.6) -> 7.4571429 | J7: =I7+G7 -> 12.428571 | K7: =J7 -> 12.428571 | L7: =(F7/4000)+1 -> 1.2 | M7: =E7/60 -> 0 | N7: ACTIVE
A8: 7 | B8: ASHANTI | C8: ECG | D8: ANGLICAN SENIOR HIGH, KUMASI | E8: 0 | F8: 400 | G8: =(((F8/70)+1)*0.4) -> 2.6857143 | H8: =G8*2 -> 5.3714286 | I8: =(((F8/70)+1)*0.6) -> 4.0285714 | J8: =I8+G8 -> 6.7142857 | K8: =J8 -> 6.7142857 | L8: =(F8/4000)+1 -> 1.1 | M8: =E8/60 -> 0 | N8: ACTIVE
A9: 8 | B9: ASHANTI | C9: ECG | D9: ARMED FORCES SENIOR HIGH/TECH, KUMASI | E9: 0 | F9: 1200 | G9: =(((F9/70)+1)*0.4) -> 7.2571429 | H9: =G9*2 -> 14.514286 | I9: =(((F9/70)+1)*0.6) -> 10.885714 | J9: =I9+G9 -> 18.142857 | K9: =J9 -> 18.142857 | L9: =(F9/4000)+1 -> 1.3 | M9: =E9/60 -> 0 | N9: ACTIVE
A10: 9 | B10: ASHANTI | C10: ECG | D10: ASANTEMAN SENIOR HIGH | E10: 0 | F10: 500 | G10: =(((F10/70)+1)*0.4) -> 3.2571429 | H10: =G10*2 -> 6.5142857 | I10: =(((F10/70)+1)*0.6) -> 4.8857143 | J10: =I10+G10 -> 8.1428571 | K10: =J10 -> 8.1428571 | L10: =(F10/4000)+1 -> 1.125 | M10: =E10/60 -> 0 | N10: ACTIVE
A11: 10 | B11: ASHANTI | C11: ECG | D11: ASOKORE MAMPONG MUNICIPAL | E11: 0 | F11: 426 | G11: =(((F11/70)+1)*0.4) -> 2.8342857 | H11: =G11*2 -> 5.6685714 | I11: =(((F11/70)+1)*0.6) -> 4.2514286 | J11: =I11+G11 -> 7.0857143 | K11: =J11 -> 7.0857143 | L11: =(F11/4000)+1 -> 1.1065 | M11: =E11/60 -> 0 | N11: ACTIVE
A12: 11 | B12: ASHANTI | C12: ECG | D12: EJISUMAN SENIOR HIGH | E12: 0 | F12: 2500 | G12: =(((F12/70)+1)*0.4) -> 14.685714 | H12: =G12*2 -> 29.371429 | I12: =(((F12/70)+1)*0.6) -> 22.028571 | J12: =I12+G12 -> 36.714286 | K12: =J12 -> 36.714286 | L12: =(F12/4000)+1 -> 1.625 | M12: =E12/60 -> 0 | N12: ACTIVE
A13: 12 | B13: ASHANTI | C13: ECG | D13: ISLAMIC SENIOR HIGH, AMPABAME | E13: 0 | F13: 1100 | G13: =(((F13/70)+1)*0.4) -> 6.6857143 | H13: =G13*2 -> 13.371429 | I13: =(((F13/70)+1)*0.6) -> 10.028571 | J13: =I13+G13 -> 16.714286 | K13: =J13 -> 16.714286 | L13: =(F13/4000)+1 -> 1.275 | M13: =E13/60 -> 0 | N13: ACTIVE
A14: 13 | B14: ASHANTI | C14: ECG | D14: KNUST SENIOR HIGH | E14: 0 | F14: 629 | G14: =(((F14/70)+1)*0.4) -> 3.9942857 | H14: =G14*2 -> 7.9885714 | I14: =(((F14/70)+1)*0.6) -> 5.9914286 | J14: =I14+G14 -> 9.9857143 | K14: =J14 -> 9.9857143 | L14: =(F14/4000)+1 -> 1.15725 | M14: =E14/60 -> 0 | N14: ACTIVE
... A1123: 1122 | B1123: GREATER ACCRA | C1123: ECG | D1123: BTS MUSTPHA DAUDA | E1123: 0 | F1123: 100 | G1123: =(((F1123/70)+1)*0.4) -> 0.97142857 | H1123: =G1123*2 -> 1.9428571 | I1123: =(((F1123/70)+1)*0.6) -> 1.4571429 | J1123: =I1123+G1123 -> 2.4285714 | K1123: =J1123 -> 2.4285714 | L1123: =(F1123/4000)+1 -> 1.025 | M1123: =E1123/60 -> 0 | N1123: ACTIVE
A1124: 1123 | B1124: GREATER ACCRA | C1124: ECG | D1124: BTS PASTOR ASARE | E1124: 0 | F1124: 150 | G1124: =(((F1124/70)+1)*0.4) -> 1.2571429 | H1124: =G1124*2 -> 2.5142857 | I1124: =(((F1124/70)+1)*0.6) -> 1.8857143 | J1124: =I1124+G1124 -> 3.1428571 | K1124: =J1124 -> 3.1428571 | L1124: =(F1124/4000)+1 -> 1.0375 | M1124: =E1124/60 -> 0 | N1124: ACTIVE | Q1124: =SUM(F2:F1123) -> 1673409.7
A1125: 1124 | B1125: GREATER ACCRA | C1125: ECG | D1125: AUXANO TECHNOLOGIES BLUE RESORT | E1125: 0 | F1125: 3500 | G1125: =(((F1125/70)+1)*0.4) -> 20.4 | H1125: =G1125*2 -> 40.8 | I1125: =(((F1125/70)+1)*0.6) -> 30.6 | J1125: =I1125+G1125 -> 51 | K1125: =J1125 -> 51 | L1125: =(F1125/4000)+1 -> 1.875 | M1125: =E1125/60 -> 0 | N1125: ACTIVE
A1126: 1125 | B1126: GREATER ACCRA | C1126: ECG | D1126: AUXANO TECHNOLOGIES ICAG | E1126: 0 | F1126: 450 | G1126: =(((F1126/70)+1)*0.4) -> 2.9714286 | H1126: =G1126*2 -> 5.9428571 | I1126: =(((F1126/70)+1)*0.6) -> 4.4571429 | J1126: =I1126+G1126 -> 7.4285714 | K1126: =J1126 -> 7.4285714 | L1126: =(F1126/4000)+1 -> 1.1125 | M1126: =E1126/60 -> 0 | N1126: ACTIVE
A1127: 1126 | B1127: GREATER ACCRA | C1127: ECG | D1127: VANNIADO | E1127: 0 | F1127: 300 | G1127: =(((F1127/70)+1)*0.4) -> 2.1142857 | H1127: =G1127*2 -> 4.2285714 | I1127: =(((F1127/70)+1)*0.6) -> 3.1714286 | J1127: =I1127+G1127 -> 5.2857143 | K1127: =J1127 -> 5.2857143 | L1127: =(F1127/4000)+1 -> 1.075 | M1127: =E1127/60 -> 0 | N1127: ACTIVE
A1128: 1127 | B1128: GREATER ACCRA | C1128: ECG | D1128: E & A BEACHFRONT | E1128: 0 | F1128: 500 | G1128: =(((F1128/70)+1)*0.4) -> 3.2571429 | H1128: =G1128*2 -> 6.5142857 | I1128: =(((F1128/70)+1)*0.6) -> 4.8857143 | J1128: =I1128+G1128 -> 8.1428571 | K1128: =J1128 -> 8.1428571 | L1128: =(F1128/4000)+1 -> 1.125 | M1128: =E1128/60 -> 0 | N1128: ACTIVE
A1129: 1128 | B1129: GREATER ACCRA | C1129: ECG | D1129: BTS TELECOM MR SAMPSON | E1129: 0 | F1129: 350 | G1129: =(((F1129/70)+1)*0.4) -> 2.4 | H1129: =G1129*2 -> 4.8 | I1129: =(((F1129/70)+1)*0.6) -> 3.6 | J1129: =I1129+G1129 -> 6 | K1129: =J1129 -> 6 | L1129: =(F1129/4000)+1 -> 1.0875 | M1129: =E1129/60 -> 0 | N1129: ACTIVE
A1130: 1129 | B1130: GREATER ACCRA | C1130: ECG | D1130: BTS TELECOM SAMUEL FUAH | E1130: 0 | F1130: 350 | G1130: =(((F1130/70)+1)*0.4) -> 2.4 | H1130: =G1130*2 -> 4.8 | I1130: =(((F1130/70)+1)*0.6) -> 3.6 | J1130: =I1130+G1130 -> 6 | K1130: =J1130 -> 6 | L1130: =(F1130/4000)+1 -> 1.0875 | M1130: =E1130/60 -> 0 | N1130: ACTIVE
A1131: 1130 | B1131: GREATER ACCRA | C1131: ECG | D1131: BTS TELECOM ISAAC D24 | E1131: 0 | F1131: 300 | G1131: =(((F1131/70)+1)*0.4) -> 2.1142857 | H1131: =G1131*2 -> 4.2285714 | I1131: =(((F1131/70)+1)*0.6) -> 3.1714286 | J1131: =I1131+G1131 -> 5.2857143 | K1131: =J1131 -> 5.2857143 | L1131: =(F1131/4000)+1 -> 1.075 | M1131: =E1131/60 -> 0 | N1131: ACTIVE
A1132: 1131 | B1132: GREATER ACCRA | C1132: ECG | D1132: BTS MR TINO | E1132: 0 | F1132: 500 | G1132: =(((F1132/70)+1)*0.4) -> 3.2571429 | H1132: =G1132*2 -> 6.5142857 | I1132: =(((F1132/70)+1)*0.6) -> 4.8857143 | J1132: =I1132+G1132 -> 8.1428571 | K1132: =J1132 -> 8.1428571 | L1132: =(F1132/4000)+1 -> 1.125 | M1132: =E1132/60 -> 0 | N1132: ACTIVE
A1133: 1132 | B1133: GREATER ACCRA | C1133: ECG | D1133: CUBECONSULT MR CHARLES | E1133: 0 | F1133: 110 | G1133: =(((F1133/70)+1)*0.4) -> 1.0285714 | H1133: =G1133*2 -> 2.0571429 | I1133: =(((F1133/70)+1)*0.6) -> 1.5428571 | J1133: =I1133+G1133 -> 2.5714286 | K1133: =J1133 -> 2.5714286 | L1133: =(F1133/4000)+1 -> 1.0275 | M1133: =E1133/60 -> 0 | N1133: ACTIVE
A1134: 1133 | B1134: GREATER ACCRA | C1134: ECG | D1134: BTS TELECOM MR OBIRI BOATENG | E1134: 0 | F1134: 350 | G1134: =(((F1134/70)+1)*0.4) -> 2.4 | H1134: =G1134*2 -> 4.8 | I1134: =(((F1134/70)+1)*0.6) -> 3.6 | J1134: =I1134+G1134 -> 6 | K1134: =J1134 -> 6 | L1134: =(F1134/4000)+1 -> 1.0875 | M1134: =E1134/60 -> 0 | N1134: ACTIVE
A1135: 1134 | B1135: GREATER ACCRA | C1135: ECG | D1135: BTS TELECOM PRINCE GYENING | E1135: 0 | F1135: 350 | G1135: =(((F1135/70)+1)*0.4) -> 2.4 | H1135: =G1135*2 -> 4.8 | I1135: =(((F1135/70)+1)*0.6) -> 3.6 | J1135: =I1135+G1135 -> 6 | K1135: =J1135 -> 6 | L1135: =(F1135/4000)+1 -> 1.0875 | M1135: =E1135/60 -> 0 | N1135: ACTIVE
A1136: 1135 | B1136: GREATER ACCRA | C1136: ECG | D1136: BTS TELECOM MILLICENT HOME | E1136: 0 | F1136: 1700 | G1136: =(((F1136/70)+1)*0.4) -> 10.114286 | H1136: =G1136*2 -> 20.228571 | I1136: =(((F1136/70)+1)*0.6) -> 15.171429 | J1136: =I1136+G1136 -> 25.285714 | K1136: =J1136 -> 25.285714 | L1136: =(F1136/4000)+1 -> 1.425 | M1136: =E1136/60 -> 0 | N1136: ACTIVE
... A1735: 1734 | B1735: GREATER ACCRA | C1735: ECG | D1735: Spectrum Internet Academic City Leg 1 | E1735: 0 | F1735: 3000 | G1735: =(((F1735/70)+1)*0.4) -> 17.542857 | H1735: =G1735*2 -> 35.085714 | I1735: =(((F1735/70)+1)*0.6) -> 26.314286 | J1735: =I1735+G1735 -> 43.857143 | K1735: =J1735 -> 43.857143 | L1735: =(F1735/4000)+1 -> 1.75 | M1735: =E1735/60 -> 0 | N1735: ACTIVE
A1736: 1735 | B1736: GREATER ACCRA | C1736: ECG | D1736: COP Pastor Frank | E1736: 76 | F1736: 0 | G1736: =(((F1736/70)+1)*0.4) -> 0.4 | H1736: =G1736*2 -> 0.8 | I1736: =(((F1736/70)+1)*0.6) -> 0.6 | J1736: =I1736+G1736 -> 1 | K1736: =J1736 -> 1 | L1736: =(F1736/4000)+1 -> 1 | M1736: =E1736/60 -> 1.2666667 | N1736: ACTIVE | O1736: 45662
A1737: 1736 | B1737: GREATER ACCRA | C1737: ECG | D1737: Geemon Solution Electroland Flat 2 | E1737: 300 | F1737: 0 | G1737: =(((F1737/70)+1)*0.4) -> 0.4 | H1737: =G1737*2 -> 0.8 | I1737: =(((F1737/70)+1)*0.6) -> 0.6 | J1737: =I1737+G1737 -> 1 | K1737: =J1737 -> 1 | L1737: =(F1737/4000)+1 -> 1 | M1737: =E1737/60 -> 5 | N1737: ACTIVE | O1737: 45659
A1738: 1737 | B1738: GREATER ACCRA | C1738: ECG | D1738: Geemon Solution Electroland Flat 4 | E1738: 300 | F1738: 0 | G1738: =(((F1738/70)+1)*0.4) -> 0.4 | H1738: =G1738*2 -> 0.8 | I1738: =(((F1738/70)+1)*0.6) -> 0.6 | J1738: =I1738+G1738 -> 1 | K1738: =J1738 -> 1 | L1738: =(F1738/4000)+1 -> 1 | M1738: =E1738/60 -> 5 | N1738: ACTIVE | O1738: 45659
A1739: 1738 | B1739: GREATER ACCRA | C1739: ECG | D1739: Geemon Solution Electroland Flat 5 | E1739: 300 | F1739: 0 | G1739: =(((F1739/70)+1)*0.4) -> 0.4 | H1739: =G1739*2 -> 0.8 | I1739: =(((F1739/70)+1)*0.6) -> 0.6 | J1739: =I1739+G1739 -> 1 | K1739: =J1739 -> 1 | L1739: =(F1739/4000)+1 -> 1 | M1739: =E1739/60 -> 5 | N1739: ACTIVE | O1739: 45661
A1740: 1739 | B1740: GREATER ACCRA | C1740: ECG | D1740: GIJ PRO VC Residence Relocation | E1740: 350 | F1740: 0 | G1740: =(((F1740/70)+1)*0.4) -> 0.4 | H1740: =G1740*2 -> 0.8 | I1740: =(((F1740/70)+1)*0.6) -> 0.6 | J1740: =I1740+G1740 -> 1 | K1740: =J1740 -> 1 | L1740: =(F1740/4000)+1 -> 1 | M1740: =E1740/60 -> 5.8333333 | N1740: ACTIVE | O1740: 45666
A1741: 1740 | B1741: GREATER ACCRA | C1741: ECG | D1741: Edify Beautiful Beginnings | E1741: 100 | F1741: 800 | G1741: =(((F1741/70)+1)*0.4) -> 4.9714286 | H1741: =G1741*2 -> 9.9428571 | I1741: =(((F1741/70)+1)*0.6) -> 7.4571429 | J1741: =I1741+G1741 -> 12.428571 | K1741: =J1741 -> 12.428571 | L1741: =(F1741/4000)+1 -> 1.2 | M1741: =E1741/60 -> 1.6666667 | N1741: ACTIVE | O1741: 45667
A1742: 1741 | B1742: GREATER ACCRA | C1742: ECG | D1742: Makot Solution Kemi Residence | E1742: 300 | F1742: 0 | G1742: =(((F1742/70)+1)*0.4) -> 0.4 | H1742: =G1742*2 -> 0.8 | I1742: =(((F1742/70)+1)*0.6) -> 0.6 | J1742: =I1742+G1742 -> 1 | K1742: =J1742 -> 1 | L1742: =(F1742/4000)+1 -> 1 | M1742: =E1742/60 -> 5 | N1742: ACTIVE | O1742: 45667
A1743: 1742 | B1743: GREATER ACCRA | C1743: ECG | D1743: Edify Flobar Academy | E1743: 200 | F1743: 550 | G1743: =(((F1743/70)+1)*0.4) -> 3.5428571 | H1743: =G1743*2 -> 7.0857143 | I1743: =(((F1743/70)+1)*0.6) -> 5.3142857 | J1743: =I1743+G1743 -> 8.8571429 | K1743: =J1743 -> 8.8571429 | L1743: =(F1743/4000)+1 -> 1.1375 | M1743: =E1743/60 -> 3.3333333 | N1743: ACTIVE | O1743: 45667
A1744: 1743 | B1744: GREATER ACCRA | C1744: ECG | D1744: Geemon Solution William | E1744: 300 | F1744: 0 | G1744: =(((F1744/70)+1)*0.4) -> 0.4 | H1744: =G1744*2 -> 0.8 | I1744: =(((F1744/70)+1)*0.6) -> 0.6 | J1744: =I1744+G1744 -> 1 | K1744: =J1744 -> 1 | L1744: =(F1744/4000)+1 -> 1 | M1744: =E1744/60 -> 5 | N1744: ACTIVE | O1744: 45667
A1745: 1744 | B1745: GREATER ACCRA | C1745: ECG | D1745: Geemon Solution Ahmed | E1745: 300 | F1745: 0 | G1745: =(((F1745/70)+1)*0.4) -> 0.4 | H1745: =G1745*2 -> 0.8 | I1745: =(((F1745/70)+1)*0.6) -> 0.6 | J1745: =I1745+G1745 -> 1 | K1745: =J1745 -> 1 | L1745: =(F1745/4000)+1 -> 1 | M1745: =E1745/60 -> 5 | N1745: ACTIVE | O1745: 45665
A1746: 1745 | B1746: GREATER ACCRA | C1746: ECG | D1746: Geemon Solution Zag | E1746: 300 | F1746: 0 | G1746: =(((F1746/70)+1)*0.4) -> 0.4 | H1746: =G1746*2 -> 0.8 | I1746: =(((F1746/70)+1)*0.6) -> 0.6 | J1746: =I1746+G1746 -> 1 | K1746: =J1746 -> 1 | L1746: =(F1746/4000)+1 -> 1 | M1746: =E1746/60 -> 5 | N1746: ACTIVE | O1746: 45665
A1747: 1746 | B1747: VOLTA | C1747: ECG | D1747: Aflao Customs Sawtel 1 | E1747: 250 | F1747: 0 | G1747: =(((F1747/70)+1)*0.4) -> 0.4 | H1747: =G1747*2 -> 0.8 | I1747: =(((F1747/70)+1)*0.6) -> 0.6 | J1747: =I1747+G1747 -> 1 | K1747: =J1747 -> 1 | L1747: =(F1747/4000)+1 -> 1 | M1747: =E1747/60 -> 4.1666667 | N1747: ACTIVE | O1747: 45665
... A2020: 2019 | B2020: GREATER ACCRA | C2020: ECG | D2020: SAWTEL-2-TEMA -TSC-1 | E2020: 0 | F2020: 0 | G2020: =(((F2020/70)+1)*0.4) -> 0.4 | H2020: =G2020*2 -> 0.8 | I2020: =(((F2020/70)+1)*0.6) -> 0.6 | J2020: =I2020+G2020 -> 1 | K2020: =J2020 -> 1 | L2020: =(F2020/4000)+1 -> 1 | M2020: =E2020/60 -> 0 | N2020: ACTIVE | O2020: 45801
A2021: 2020 | B2021: GREATER ACCRA | C2021: ECG | D2021: SAWTEL-2-GRA-NEW DC | E2021: 0 | F2021: 427.4 | G2021: =(((F2021/70)+1)*0.4) -> 2.8422857 | H2021: =G2021*2 -> 5.6845714 | I2021: =(((F2021/70)+1)*0.6) -> 4.2634286 | J2021: =I2021+G2021 -> 7.1057143 | K2021: =J2021 -> 7.1057143 | L2021: =(F2021/4000)+1 -> 1.10685 | M2021: =E2021/60 -> 0 | N2021: ACTIVE
A2022: 2021 | B2022: GREATER ACCRA | C2022: ECG | D2022: IKLICK-TS11-SAMUEL-MAINOO | E2022: 202 | F2022: 0 | G2022: =(((F2022/70)+1)*0.4) -> 0.4 | H2022: =G2022*2 -> 0.8 | I2022: =(((F2022/70)+1)*0.6) -> 0.6 | J2022: =I2022+G2022 -> 1 | K2022: =J2022 -> 1 | L2022: =(F2022/4000)+1 -> 1 | M2022: =E2022/60 -> 3.3666667 | N2022: ACTIVE
A2023: 2022 | B2023: GREATER ACCRA | C2023: ECG | D2023: ECHO-MSC | E2023: 176 | F2023: 0 | G2023: =(((F2023/70)+1)*0.4) -> 0.4 | H2023: =G2023*2 -> 0.8 | I2023: =(((F2023/70)+1)*0.6) -> 0.6 | J2023: =I2023+G2023 -> 1 | K2023: =J2023 -> 1 | L2023: =(F2023/4000)+1 -> 1 | M2023: =E2023/60 -> 2.9333333 | N2023: ACTIVE
A2024: 2023 | B2024: GREATER ACCRA | C2024: ECG | D2024: AT-KUIPERS GH | E2024: 277 | F2024: 0 | G2024: =(((F2024/70)+1)*0.4) -> 0.4 | H2024: =G2024*2 -> 0.8 | I2024: =(((F2024/70)+1)*0.6) -> 0.6 | J2024: =I2024+G2024 -> 1 | K2024: =J2024 -> 1 | L2024: =(F2024/4000)+1 -> 1 | M2024: =E2024/60 -> 4.6166667 | N2024: ACTIVE
A2025: 2024 | B2025: GREATER ACCRA | C2025: ECG | D2025: OZONE ALIDU NASSER | E2025: 246 | F2025: 1200 | G2025: =(((F2025/70)+1)*0.4) -> 7.2571429 | H2025: =G2025*2 -> 14.514286 | I2025: =(((F2025/70)+1)*0.6) -> 10.885714 | J2025: =I2025+G2025 -> 18.142857 | K2025: =J2025 -> 18.142857 | L2025: =(F2025/4000)+1 -> 1.3 | M2025: =E2025/60 -> 4.1 | N2025: ACTIVE
A2026: 2025 | B2026: GREATER ACCRA | C2026: ECG | D2026: OZONE-ICU | E2026: 0 | F2026: 646 | G2026: =(((F2026/70)+1)*0.4) -> 4.0914286 | H2026: =G2026*2 -> 8.1828571 | I2026: =(((F2026/70)+1)*0.6) -> 6.1371429 | J2026: =I2026+G2026 -> 10.228571 | K2026: =J2026 -> 10.228571 | L2026: =(F2026/4000)+1 -> 1.1615 | M2026: =E2026/60 -> 0 | N2026: ACTIVE
A2027: 2026 | B2027: GREATER ACCRA | C2027: ECG | D2027: OZONE-IGTE | E2027: 0 | F2027: 302 | G2027: =(((F2027/70)+1)*0.4) -> 2.1257143 | H2027: =G2027*2 -> 4.2514286 | I2027: =(((F2027/70)+1)*0.6) -> 3.1885714 | J2027: =I2027+G2027 -> 5.3142857 | K2027: =J2027 -> 5.3142857 | L2027: =(F2027/4000)+1 -> 1.0755 | M2027: =E2027/60 -> 0 | N2027: ACTIVE
A2028: 2027 | B2028: GREATER ACCRA | C2028: ECG | D2028: IKLICK-BTS-STELLA GOMADO | E2028: 0 | F2028: 0 | G2028: =(((F2028/70)+1)*0.4) -> 0.4 | H2028: =G2028*2 -> 0.8 | I2028: =(((F2028/70)+1)*0.6) -> 0.6 | J2028: =I2028+G2028 -> 1 | K2028: =J2028 -> 1 | L2028: =(F2028/4000)+1 -> 1 | M2028: =E2028/60 -> 0 | N2028: ACTIVE
A2029: 2028 | B2029: GREATER ACCRA | C2029: ECG | D2029: IKLICK-BTS-FERDNARD GODZO ASAMOAH | E2029: 0 | F2029: 0 | G2029: =(((F2029/70)+1)*0.4) -> 0.4 | H2029: =G2029*2 -> 0.8 | I2029: =(((F2029/70)+1)*0.6) -> 0.6 | J2029: =I2029+G2029 -> 1 | K2029: =J2029 -> 1 | L2029: =(F2029/4000)+1 -> 1 | M2029: =E2029/60 -> 0 | N2029: ACTIVE
A2030: 2029 | B2030: GREATER ACCRA | C2030: ECG | D2030: OZONE MAGVILYN | E2030: 78 | F2030: 704 | G2030: =(((F2030/70)+1)*0.4) -> 4.4228571 | H2030: =G2030*2 -> 8.8457143 | I2030: =(((F2030/70)+1)*0.6) -> 6.6342857 | J2030: =I2030+G2030 -> 11.057143 | K2030: =J2030 -> 11.057143 | L2030: =(F2030/4000)+1 -> 1.176 | M2030: =E2030/60 -> 1.3 | N2030: ACTIVE
A2031: 2030 | B2031: GREATER ACCRA | C2031: ECG | D2031: OZONE INVESTCORP | E2031: 78 | F2031: 402 | G2031: =(((F2031/70)+1)*0.4) -> 2.6971429 | H2031: =G2031*2 -> 5.3942857 | I2031: =(((F2031/70)+1)*0.6) -> 4.0457143 | J2031: =I2031+G2031 -> 6.7428571 | K2031: =J2031 -> 6.7428571 | L2031: =(F2031/4000)+1 -> 1.1005 | M2031: =E2031/60 -> 1.3 | N2031: ACTIVE
A2032: 2031 | B2032: GREATER ACCRA | C2032: ECG | D2032: IKLICK-KINGSLEY DESTINY | E2032: 594 | F2032: 0 | G2032: =(((F2032/70)+1)*0.4) -> 0.4 | H2032: =G2032*2 -> 0.8 | I2032: =(((F2032/70)+1)*0.6) -> 0.6 | J2032: =I2032+G2032 -> 1 | K2032: =J2032 -> 1 | L2032: =(F2032/4000)+1 -> 1 | M2032: =E2032/60 -> 9.9 | N2032: ACTIVE
... A2096: 2095 | B2096: GREATER ACCRA | C2096: ECG | D2096: OZONE -NOKNOK SPINTEX | E2096: 300 | F2096: 0 | G2096: =(((F2096/70)+1)*0.4) -> 0.4 | H2096: =G2096*2 -> 0.8 | I2096: =(((F2096/70)+1)*0.6) -> 0.6 | J2096: =I2096+G2096 -> 1 | K2096: =J2096 -> 1 | L2096: =(F2096/4000)+1 -> 1 | M2096: =E2096/60 -> 5 | N2096: ACTIVE
A2097: 2096 | B2097: GREATER ACCRA | C2097: ECG | D2097: DDS-OMNIBSIC-WEIJA | E2097: 322 | F2097: 0 | G2097: NA | H2097: NA | I2097: NA | J2097: NA | K2097: NA | L2097: NA | M2097: =E2097/40 -> 8.05 | N2097: ACTIVE
A2098: 2097 | B2098: GREATER ACCRA | C2098: ECG | D2098: OZONE RESTORE PRAYER PARTNER | E2098: 206 | F2098: 0 | G2098: =(((F2098/70)+1)*0.4) -> 0.4 | H2098: =G2098*2 -> 0.8 | I2098: =(((F2098/70)+1)*0.6) -> 0.6 | J2098: =I2098+G2098 -> 1 | K2098: =J2098 -> 1 | L2098: =(F2098/4000)+1 -> 1 | M2098: =E2098/60 -> 3.4333333 | N2098: ACTIVE
A2099: 2098 | B2099: GREATER ACCRA | C2099: ECG | D2099: DDS-OMNNIBSIC-NORTH INDUSTRIAL AREA | E2099: 300 | F2099: 0 | G2099: =(((F2099/70)+1)*0.4) -> 0.4 | H2099: =G2099*2 -> 0.8 | I2099: =(((F2099/70)+1)*0.6) -> 0.6 | J2099: =I2099+G2099 -> 1 | K2099: =J2099 -> 1 | L2099: =(F2099/4000)+1 -> 1 | M2099: =E2099/60 -> 5 | N2099: ACTIVE
A2100: 2099 | B2100: GREATER ACCRA | C2100: ECG | D2100: DDS-OMNNIBSIC-ADABRAKA | E2100: 324 | F2100: 0 | G2100: =(((F2100/70)+1)*0.4) -> 0.4 | H2100: =G2100*2 -> 0.8 | I2100: =(((F2100/70)+1)*0.6) -> 0.6 | J2100: =I2100+G2100 -> 1 | K2100: =J2100 -> 1 | L2100: =(F2100/4000)+1 -> 1 | M2100: =E2100/60 -> 5.4 | N2100: ACTIVE
A2101: 2100 | B2101: GREATER ACCRA | C2101: ECG | D2101: IKLICK-KWASI-PREMPEH | E2101: 470 | F2101: 0 | G2101: =(((F2101/70)+1)*0.4) -> 0.4 | H2101: =G2101*2 -> 0.8 | I2101: =(((F2101/70)+1)*0.6) -> 0.6 | J2101: =I2101+G2101 -> 1 | K2101: =J2101 -> 1 | L2101: =(F2101/4000)+1 -> 1 | M2101: =E2101/60 -> 7.8333333 | N2101: ACTIVE
A2102: 2101 | B2102: GREATER ACCRA | C2102: ECG | D2102: DDS-OMNNIBSIC-NIMA | E2102: 200 | F2102: 1000 | G2102: =(((F2102/70)+1)*0.4) -> 6.1142857 | H2102: =G2102*2 -> 12.228571 | I2102: =(((F2102/70)+1)*0.6) -> 9.1714286 | J2102: =I2102+G2102 -> 15.285714 | K2102: =J2102 -> 15.285714 | L2102: =(F2102/4000)+1 -> 1.25 | M2102: =E2102/60 -> 3.3333333 | N2102: ACTIVE
A2103: 2102 | B2103: GREATER ACCRA | C2103: ECG | D2103: OZONE-FUTURE-SPACE | E2103: 100 | F2103: 0 | G2103: =(((F2103/70)+1)*0.4) -> 0.4 | H2103: =G2103*2 -> 0.8 | I2103: =(((F2103/70)+1)*0.6) -> 0.6 | J2103: =I2103+G2103 -> 1 | K2103: =J2103 -> 1 | L2103: =(F2103/4000)+1 -> 1 | M2103: =E2103/60 -> 1.6666667 | N2103: ACTIVE
A2104: 2103 | B2104: BRONG AHAFO | C2104: ECG | D2104: MAXINET -DONEWELL INSURANCE | E2104: 0 | F2104: 177 | G2104: =(((F2104/70)+1)*0.4) -> 1.4114286 | H2104: =G2104*2 -> 2.8228571 | I2104: =(((F2104/70)+1)*0.6) -> 2.1171429 | J2104: =I2104+G2104 -> 3.5285714 | K2104: =J2104 -> 3.5285714 | L2104: =(F2104/4000)+1 -> 1.04425 | M2104: =E2104/60 -> 0 | N2104: ACTIVE
A2105: 2104 | B2105: BRONG AHAFO | C2105: ECG | D2105: ECOBAND OSIRIS TRADING | E2105: 0 | F2105: 66 | G2105: =(((F2105/70)+1)*0.4) -> 0.77714286 | H2105: =G2105*2 -> 1.5542857 | I2105: =(((F2105/70)+1)*0.6) -> 1.1657143 | J2105: =I2105+G2105 -> 1.9428571 | K2105: =J2105 -> 1.9428571 | L2105: =(F2105/4000)+1 -> 1.0165 | M2105: =E2105/60 -> 0 | N2105: ACTIVE
A2106: 2105 | B2106: GREATER ACCRA | C2106: ECG | D2106: DDS-OMNNIBSIC-ACCRA CENTRAL | E2106: 0 | F2106: 208 | G2106: =(((F2106/70)+1)*0.4) -> 1.5885714 | H2106: =G2106*2 -> 3.1771429 | I2106: =(((F2106/70)+1)*0.6) -> 2.3828571 | J2106: =I2106+G2106 -> 3.9714286 | K2106: =J2106 -> 3.9714286 | L2106: =(F2106/4000)+1 -> 1.052 | M2106: =E2106/60 -> 0 | N2106: ACTIVE
A2107: 2106 | B2107: GREATER ACCRA | C2107: ECG | D2107: IKLICK-JOHN AIDOO 2 | E2107: 673 | F2107: 0 | G2107: =(((F2107/70)+1)*0.4) -> 0.4 | H2107: =G2107*2 -> 0.8 | I2107: =(((F2107/70)+1)*0.6) -> 0.6 | J2107: =I2107+G2107 -> 1 | K2107: =J2107 -> 1 | L2107: =(F2107/4000)+1 -> 1 | M2107: =E2107/60 -> 11.216667 | N2107: ACTIVE
A2108: 2107 | B2108: GREATER ACCRA | C2108: ECG | D2108: IKLICK-BTS-NANA-AMA-OT-DARKOWA | E2108: 338 | F2108: 0 | G2108: =(((F2108/70)+1)*0.4) -> 0.4 | H2108: =G2108*2 -> 0.8 | I2108: =(((F2108/70)+1)*0.6) -> 0.6 | J2108: =I2108+G2108 -> 1 | K2108: =J2108 -> 1 | L2108: =(F2108/4000)+1 -> 1 | M2108: =E2108/60 -> 5.6333333 | N2108: ACTIVE
A2109: 2108 | B2109: GREATER ACCRA | C2109: ECG | D2109: DDS-OMNNIBSIC-TEMA | E2109: 0 | F2109: 0 | G2109: =(((F2109/70)+1)*0.4) -> 0.4 | H2109: =G2109*2 -> 0.8 | I2109: =(((F2109/70)+1)*0.6) -> 0.6 | J2109: =I2109+G2109 -> 1 | K2109: =J2109 -> 1 | L2109: =(F2109/4000)+1 -> 1 | M2109: =E2109/60 -> 0 | N2109: ACTIVE
... A2111: 2110 | B2111: GREATER ACCRA | C2111: ECG | D2111: DDS-LDS-KASOA | E2111: 208 | F2111: 0 | G2111: =(((F2111/70)+1)*0.4) -> 0.4 | H2111: =G2111*2 -> 0.8 | I2111: =(((F2111/70)+1)*0.6) -> 0.6 | J2111: =I2111+G2111 -> 1 | K2111: =J2111 -> 1 | L2111: =(F2111/4000)+1 -> 1 | M2111: =E2111/60 -> 3.4666667 | N2111: ACTIVE
A2112: 2111 | B2112: CENTRAL | C2112: ECG | D2112: ECOBAND-SONOTECH | E2112: 0 | F2112: 981 | G2112: NA | H2112: NA | I2112: NA | J2112: NA | K2112: NA | L2112: NA | M2112: =E2112/40 -> 0 | N2112: ACTIVE
A2113: 2112 | B2113: WESTERN | C2113: ECG | D2113: MAXINET-DONEWELL-INSURANCE -TAKORADI | E2113: 0 | F2113: 632 | G2113: NA | H2113: NA | I2113: NA | J2113: NA | K2113: NA | L2113: NA | M2113: =E2113/40 -> 0 | N2113: ACTIVE
A2114: 2113 | B2114: GREATER ACCRA | C2114: ECG | D2114: IKLICK COP TESHIE MISSION HOUSE | E2114: 0 | F2114: 821 | G2114: NA | H2114: NA | I2114: NA | J2114: NA | K2114: NA | L2114: NA | M2114: =E2114/40 -> 0 | N2114: ACTIVE
A2115: 2114 | B2115: GREATER ACCRA | C2115: ECG | D2115: IKLICK-PIWC-SAKUMONO | E2115: 0 | F2115: 0 | G2115: =(((F2115/70)+1)*0.4) -> 0.4 | H2115: =G2115*2 -> 0.8 | I2115: =(((F2115/70)+1)*0.6) -> 0.6 | J2115: =I2115+G2115 -> 1 | K2115: =J2115 -> 1 | L2115: =(F2115/4000)+1 -> 1 | M2115: =E2115/60 -> 0 | N2115: ACTIVE
A2116: 2115 | B2116: VOLTA | C2116: ECG | D2116: MAXINET-DONEWELL-INSURANCE -HO | E2116: 271 | F2116: 0 | G2116: NA | H2116: NA | I2116: NA | J2116: NA | K2116: NA | L2116: NA | M2116: =E2116/40 -> 6.775 | N2116: ACTIVE
A2117: 2116 | B2117: GREATER ACCRA | C2117: ECG | D2117: OZONE DZIGBORDI RESIDENCE | E2117: 350 | F2117: 650 | G2117: =(((F2117/70)+1)*0.4) -> 4.1142857 | H2117: =G2117*2 -> 8.2285714 | I2117: =(((F2117/70)+1)*0.6) -> 6.1714286 | J2117: =I2117+G2117 -> 10.285714 | K2117: =J2117 -> 10.285714 | L2117: =(F2117/4000)+1 -> 1.1625 | M2117: =E2117/60 -> 5.8333333 | N2117: ACTIVE
A2118: 2117 | B2118: GREATER ACCRA | C2118: ECG | D2118: OZONE BWOODIN | E2118: 400 | F2118: 0 | G2118: =(((F2118/70)+1)*0.4) -> 0.4 | H2118: =G2118*2 -> 0.8 | I2118: =(((F2118/70)+1)*0.6) -> 0.6 | J2118: =I2118+G2118 -> 1 | K2118: =J2118 -> 1 | L2118: =(F2118/4000)+1 -> 1 | M2118: =E2118/60 -> 6.6666667 | N2118: ACTIVE
A2119: 2118 | B2119: GREATER ACCRA | C2119: ECG | D2119: ECHO-SDC-FINANCE OFFICE | E2119: 400 | F2119: 0 | G2119: =(((F2119/70)+1)*0.4) -> 0.4 | H2119: =G2119*2 -> 0.8 | I2119: =(((F2119/70)+1)*0.6) -> 0.6 | J2119: =I2119+G2119 -> 1 | K2119: =J2119 -> 1 | L2119: =(F2119/4000)+1 -> 1 | M2119: =E2119/60 -> 6.6666667 | N2119: ACTIVE
A2120: 2119 | B2120: GREATER ACCRA | C2120: ECG | D2120: PTBL-DOREEN CAROL ANNING GYEBI | E2120: 152 | F2120: 1000 | G2120: =(((F2120/70)+1)*0.4) -> 6.1142857 | H2120: =G2120*2 -> 12.228571 | I2120: =(((F2120/70)+1)*0.6) -> 9.1714286 | J2120: =I2120+G2120 -> 15.285714 | K2120: =J2120 -> 15.285714 | L2120: =(F2120/4000)+1 -> 1.25 | M2120: =E2120/60 -> 2.5333333 | N2120: ACTIVE
A2121: 2120 | B2121: NORTHERN | C2121: NEDCO | D2121: MAXINET-DONEWELL-INSURANCE -TAMALE | E2121: 0 | F2121: 336 | G2121: =(((F2121/70)+1)*0.4) -> 2.32 | H2121: =G2121*2 -> 4.64 | I2121: =(((F2121/70)+1)*0.6) -> 3.48 | J2121: =I2121+G2121 -> 5.8 | K2121: =J2121 -> 5.8 | L2121: =(F2121/4000)+1 -> 1.084 | M2121: =E2121/60 -> 0 | N2121: ACTIVE
A2122: 2121 | B2122: GREATER ACCRA | C2122: ECG | D2122: IKLICK-QUIST TOWN-ERNEST BOAKYE | E2122: 101 | F2122: 0 | G2122: =(((F2122/70)+1)*0.4) -> 0.4 | H2122: =G2122*2 -> 0.8 | I2122: =(((F2122/70)+1)*0.6) -> 0.6 | J2122: =I2122+G2122 -> 1 | K2122: =J2122 -> 1 | L2122: =(F2122/4000)+1 -> 1 | M2122: =E2122/60 -> 1.6833333 | N2122: ACTIVE
A2123: 2122 | B2123: ASHANTI | C2123: ECG | D2123: MAXINET-DONEWELL-INSURANCE -KUMASI | E2123: 458 | F2123: 0 | G2123: =(((F2123/70)+1)*0.4) -> 0.4 | H2123: =G2123*2 -> 0.8 | I2123: =(((F2123/70)+1)*0.6) -> 0.6 | J2123: =I2123+G2123 -> 1 | K2123: =J2123 -> 1 | L2123: =(F2123/4000)+1 -> 1 | M2123: =E2123/60 -> 7.6333333 | N2123: ACTIVE
A2124: 2123 | B2124: GREATER ACCRA | C2124: ECG | D2124: IKLICK -GARIBA- HARUNA | E2124: 128 | F2124: 0 | G2124: =(((F2124/70)+1)*0.4) -> 0.4 | H2124: =G2124*2 -> 0.8 | I2124: =(((F2124/70)+1)*0.6) -> 0.6 | J2124: =I2124+G2124 -> 1 | K2124: =J2124 -> 1 | L2124: =(F2124/4000)+1 -> 1 | M2124: =E2124/60 -> 2.1333333 | N2124: ACTIVE
A2125: 2124 | B2125: GREATER ACCRA | C2125: ECG | D2125: IKLICK-BTS-PHILLIP ANYAN OBENG | E2125: 17 | F2125: 0 | G2125: =(((F2125/70)+1)*0.4) -> 0.4 | H2125: =G2125*2 -> 0.8 | I2125: =(((F2125/70)+1)*0.6) -> 0.6 | J2125: =I2125+G2125 -> 1 | K2125: =J2125 -> 1 | L2125: =(F2125/4000)+1 -> 1 | M2125: =E2125/60 -> 0.28333333 | N2125: ACTIVE
A2126: 2125 | B2126: GREATER ACCRA | C2126: ECG | D2126: IKLICK-CUBE CONSULT-BRIDGET AKU AGBEY | E2126: 60 | F2126: 723 | G2126: =(((F2126/70)+1)*0.4) -> 4.5314286 | H2126: =G2126*2 -> 9.0628571 | I2126: =(((F2126/70)+1)*0.6) -> 6.7971429 | J2126: =I2126+G2126 -> 11.328571 | K2126: =J2126 -> 11.328571 | L2126: =(F2126/4000)+1 -> 1.18075 | M2126: =E2126/60 -> 1 | N2126: ACTIVE
A2127: 2126 | B2127: GREATER ACCRA | C2127: ECG | D2127: IKLICK-PENTECOST MISSION HOUSE | E2127: 0 | F2127: 821 | G2127: =(((F2127/70)+1)*0.4) -> 5.0914286 | H2127: =G2127*2 -> 10.182857 | I2127: =(((F2127/70)+1)*0.6) -> 7.6371429 | J2127: =I2127+G2127 -> 12.728571 | K2127: =J2127 -> 12.728571 | L2127: =(F2127/4000)+1 -> 1.20525 | M2127: =E2127/60 -> 0 | N2127: ACTIVE
A2128: 2127 | B2128: GREATER ACCRA | C2128: ECG | D2128: DATACOM MOHINANI - NORTH INDUSTRIAL | E2128: 95 | F2128: 0 | G2128: NA | H2128: NA | I2128: NA | J2128: NA | K2128: NA | L2128: NA | M2128: =E2128/40 -> 2.375 | N2128: ACTIVE
A2129: 2128 | B2129: GREATER ACCRA | C2129: ECG | D2129: FG&B -TRINITY THEOLOGICAL SEMINAR | E2129: 900 | F2129: 0 | G2129: =(((F2129/70)+1)*0.4) -> 0.4 | H2129: =G2129*2 -> 0.8 | I2129: =(((F2129/70)+1)*0.6) -> 0.6 | J2129: =I2129+G2129 -> 1 | K2129: =J2129 -> 1 | L2129: =(F2129/4000)+1 -> 1 | M2129: =E2129/60 -> 15 | N2129: ACTIVE
A2130: 2129 | B2130: GREATER ACCRA | C2130: ECG | D2130: IKLICK-COL-EMMANUEL NYANTE | E2130: 686 | F2130: 0 | G2130: =(((F2130/70)+1)*0.4) -> 0.4 | H2130: =G2130*2 -> 0.8 | I2130: =(((F2130/70)+1)*0.6) -> 0.6 | J2130: =I2130+G2130 -> 1 | K2130: =J2130 -> 1 | L2130: =(F2130/4000)+1 -> 1 | M2130: =E2130/60 -> 11.433333 | N2130: ACTIVE
A2131: 2130 | B2131: GREATER ACCRA | C2131: ECG | D2131: ECHO-METROHM CENTRAL AFRICA | E2131: 250 | F2131: 0 | G2131: =(((F2131/70)+1)*0.4) -> 0.4 | H2131: =G2131*2 -> 0.8 | I2131: =(((F2131/70)+1)*0.6) -> 0.6 | J2131: =I2131+G2131 -> 1 | K2131: =J2131 -> 1 | L2131: =(F2131/4000)+1 -> 1 | M2131: =E2131/60 -> 4.1666667 | N2131: ACTIVE
A2132: 2131 | B2132: GREATER ACCRA | C2132: ECG | D2132: ECHO-BAYPORT-AIRPORT | E2132: 0 | F2132: 750 | G2132: =(((F2132/70)+1)*0.4) -> 4.6857143 | H2132: =G2132*2 -> 9.3714286 | I2132: =(((F2132/70)+1)*0.6) -> 7.0285714 | J2132: =I2132+G2132 -> 11.714286 | K2132: =J2132 -> 11.714286 | L2132: =(F2132/4000)+1 -> 1.1875 | M2132: =E2132/60 -> 0 | N2132: ACTIVE
A2133: 2132 | B2133: ASHANTI | C2133: ECG | D2133: ECHO-BROLL-KUMASI CITY MALL | E2133: 173 | F2133: 757 | G2133: =(((F2133/70)+1)*0.4) -> 4.7257143 | H2133: =G2133*2 -> 9.4514286 | I2133: =(((F2133/70)+1)*0.6) -> 7.0885714 | J2133: =I2133+G2133 -> 11.814286 | K2133: =J2133 -> 11.814286 | L2133: =(F2133/4000)+1 -> 1.18925 | M2133: =E2133/60 -> 2.8833333 | N2133: ACTIVE
A2134: 2133 | B2134: GREATER ACCRA | C2134: ECG | D2134: COP SAKUMONO AREA MISSION HOUSE | E2134: 100 | F2134: 1000 | G2134: =(((F2134/70)+1)*0.4) -> 6.1142857 | H2134: =G2134*2 -> 12.228571 | I2134: =(((F2134/70)+1)*0.6) -> 9.1714286 | J2134: =I2134+G2134 -> 15.285714 | K2134: =J2134 -> 15.285714 | L2134: =(F2134/4000)+1 -> 1.25 | M2134: =E2134/60 -> 1.6666667 | N2134: ACTIVE
A2135: 2134 | B2135: GREATER ACCRA | C2135: ECG | D2135: DDS-OMNIBSIC-TEMA | E2135: 200 | F2135: 1000 | G2135: =(((F2135/70)+1)*0.4) -> 6.1142857 | H2135: =G2135*2 -> 12.228571 | I2135: =(((F2135/70)+1)*0.6) -> 9.1714286 | J2135: =I2135+G2135 -> 15.285714 | K2135: =J2135 -> 15.285714 | L2135: =(F2135/4000)+1 -> 1.25 | M2135: =E2135/60 -> 3.3333333 | N2135: ACTIVE
A2136: 2135 | B2136: GREATER ACCRA | C2136: ECG | D2136: SMARTINFRACO-SLTF | E2136: 75 | F2136: 0 | G2136: =(((F2136/70)+1)*0.4) -> 0.4 | H2136: =G2136*2 -> 0.8 | I2136: =(((F2136/70)+1)*0.6) -> 0.6 | J2136: =I2136+G2136 -> 1 | K2136: =J2136 -> 1 | L2136: =(F2136/4000)+1 -> 1 | M2136: =E2136/60 -> 1.25 | N2136: ACTIVE
A2137: 2136 | B2137: GREATER ACCRA | C2137: ECG | D2137: IKLICK PHYLIS GROBI | E2137: 100 | F2137: 850 | G2137: =(((F2137/70)+1)*0.4) -> 5.2571429 | H2137: =G2137*2 -> 10.514286 | I2137: =(((F2137/70)+1)*0.6) -> 7.8857143 | J2137: =I2137+G2137 -> 13.142857 | K2137: =J2137 -> 13.142857 | L2137: =(F2137/4000)+1 -> 1.2125 | M2137: =E2137/60 -> 1.6666667 | N2137: ACTIVE
A2138: 2137 | B2138: GREATER ACCRA | C2138: ECG | D2138: FG&B -LANSFIELD-DZORWULU | E2138: 0 | F2138: 736 | G2138: =(((F2138/70)+1)*0.4) -> 4.6057143 | H2138: =G2138*2 -> 9.2114286 | I2138: =(((F2138/70)+1)*0.6) -> 6.9085714 | J2138: =I2138+G2138 -> 11.514286 | K2138: =J2138 -> 11.514286 | L2138: =(F2138/4000)+1 -> 1.184 | M2138: =E2138/60 -> 0 | N2138: ACTIVE
A2139: 2138 | B2139: GREATER ACCRA | C2139: ECG | D2139: IKLICK-TS 11-SHEILA BANSAH | E2139: 162 | F2139: 0 | G2139: =(((F2139/70)+1)*0.4) -> 0.4 | H2139: =G2139*2 -> 0.8 | I2139: =(((F2139/70)+1)*0.6) -> 0.6 | J2139: =I2139+G2139 -> 1 | K2139: =J2139 -> 1 | L2139: =(F2139/4000)+1 -> 1 | M2139: =E2139/60 -> 2.7 | N2139: ACTIVE
A2140: 2139 | B2140: GREATER ACCRA | C2140: ECG | D2140: IKLICK-TS 11-AKOSUA DARKO | E2140: 238 | F2140: 0 | G2140: =(((F2140/70)+1)*0.4) -> 0.4 | H2140: =G2140*2 -> 0.8 | I2140: =(((F2140/70)+1)*0.6) -> 0.6 | J2140: =I2140+G2140 -> 1 | K2140: =J2140 -> 1 | L2140: =(F2140/4000)+1 -> 1 | M2140: =E2140/60 -> 3.9666667 | N2140: ACTIVE
A2141: 2140 | B2141: GREATER ACCRA | C2141: ECG | D2141: IKLICK-TS 11-KEITH TOOMER | E2141: 252 | F2141: 0 | G2141: NA | H2141: NA | I2141: NA | J2141: NA | K2141: NA | L2141: NA | M2141: =E2141/40 -> 6.3 | N2141: ACTIVE
A2142: 2141 | B2142: GREATER ACCRA | C2142: ECG | D2142: DIRECTORATE OF INFORMATION TECHNOLOGY | E2142: 0 | F2142: 155 | G2142: =(((F2142/70)+1)*0.4) -> 1.2857143 | H2142: =G2142*2 -> 2.5714286 | I2142: =(((F2142/70)+1)*0.6) -> 1.9285714 | J2142: =I2142+G2142 -> 3.2142857 | K2142: =J2142 -> 3.2142857 | L2142: =(F2142/4000)+1 -> 1.03875 | M2142: =E2142/60 -> 0 | N2142: ACTIVE
...
